Workbook
Name A: 'Faturamento RJ'!$A:$B
Name Estacionamento: #REF!
Name SegmentaçãodeDados_Categoria: #N/A
Name SegmentaçãodeDados_Categoria1: #N/A
Name SegmentaçãodeDados_Categoria2: #N/A
Name SegmentaçãodeDados_Categoria3: #N/A
Name SegmentaçãodeDados_Fornecedor: #N/A
Name SegmentaçãodeDados_Fornecedor1: #N/A
Name SegmentaçãodeDados_Fornecedor2: #N/A
Name SegmentaçãodeDados_Fornecedor3: #N/A
Name SegmentaçãodeDados_Mês: #N/A
Name SegmentaçãodeDados_Mês_de_referência_para_faturamento: #N/A
Name SegmentaçãodeDados_Unidade: #N/A
Name SegmentaçãodeDados_Unidade1: #N/A
Name SegmentaçãodeDados_Unidade2: #N/A
Name SegmentaçãodeDados_Unidade3: #N/A

Sheet Unidade
A1: Unidade | B1: Regional UF | C1: Regional PS | D1: Regional RS | E1: Cluster | F1: Portifólio
A2: Bangu Shopping | B2: RJ | C2: Sérgio P. | D2: Joana | E2: 3 | F2: Próprio
A3: Carioca Shopping | B3: RJ | C3: Sérgio P. | D3: Joana | E3: 3 | F3: Próprio
A4: Caxias Shopping | B4: RJ | C4: Sérgio P. | D4: Joana | E4: 2 | F4: Próprio
A5: Independência Shopping | B5: RJ | C5: Sérgio P. | D5: Joana | E5: 1 | F5: Próprio
A6: Norte Shopping | B6: RJ | C6: Sérgio P. | D6: Joana | E6: 4 | F6: Próprio
A7: Passeio Shopping | B7: RJ | C7: Sérgio P. | D7: Joana | E7: 1 | F7: Administrado
A8: Recreio Shopping | B8: RJ | C8: Sérgio P. | D8: Joana | E8: 2 | F8: Administrado
A9: Rio Design Leblon | B9: RJ | C9: Sérgio P. | D9: Joana | E9: 1 | F9: Próprio
A10: Shopping Grande Rio | B10: RJ | C10: Sérgio P. | D10: Joana | E10: 3 | F10: Próprio
A11: Shopping Leblon | B11: RJ | C11: Sérgio P. | D11: Joana | E11: 3 | F11: Próprio
A12: Shopping Vila Velha | B12: RJ | C12: Sérgio P. | D12: Joana | E12: 3 | F12: Próprio

Sheet HC
A1: Cluster | B1: Categoria | C1: HC_Min | D1: HC_Max
A2: 1 | B2: Manutenção | C2: 12 | D2: 18
A3: 2 | B3: Manutenção | C3: 16 | D3: 21
A4: 3 | B4: Manutenção | C4: 21 | D4: 29
A5: 4 | B5: Manutenção | C5: 27 | D5: 38
A6: 1 | B6: PMOC | C6: 2 | D6: 2
A7: 2 | B7: PMOC | C7: 2 | D7: 3
A8: 3 | B8: PMOC | C8: 3 | D8: 4
A9: 4 | B9: PMOC | C9: 5 | D9: 7

Sheet Fornecedor
A1: Fornecedor | B1: Brigada de Incêndio | C1: Estacionamento | D1: Limpeza | E1: Manutenção | F1: PMOC | G1: Portaria | H1: Vigilância | I1: Jardinagem | J1: Ascensorista | K1: Resíduos
A2: Action Fire | B2: FTR | C2: Índigo | D2: Verzani | E2: GPS | F2: Brasanitas | G2: GPS | H2: GPS | I2: Verzani | J2: Liderforte | K2: Império
A3: Agro Rio | B3: Onet | C3: GPS | D3: Brasanitas | E3: Brasanitas | F3: GPS | G3: Verzani | H3: Protege | I3: Flora Rocha | K3: GPS
A4: AgroGarden | B4: Medmais | C4: Brasil Park | D4: GPS | E4: Grupo Opus | F4: Grupo Opus | G4: Resolv | H4: Verzani | I4: C&C | K4: Verzani
A5: Agrotexas | B5: Grupo Altum | C5: Verzani | D5: Nova Rio | E5: Verzani | F5: Sethvac | G5: Veper | H5: Grupo Altum | I5: O Jardineiro | K5: Nova Rio
A6: Ambi Verde | B6: Brasanitas | C6: Parker | D6: Grupo Altum | E6: IMC Saste | F6: Verzani | G6: Grupo JLR | H6: Resolv | I6: Verzani | K6: Reambient
A7: AMPLA Resgate Treinamentos | B7: Proteção | C7: Sinart | D7: Grupo Serval | E7: BP Engenharia | F7: Tecnitest | G7: Protege | H7: Veper | I7: Art Garden | K7: Recicla Engenharia
A8: Art Garden | B8: GPS | D8: Seleto | F8: IMC Saste | G8: Grupo Altum | H8: Seleto | I8: L.F. Pinheiro Crepaldi | K8: Ambiente Verde
A9: Artemp | B9: CTA | D9: Limpcar | F9: PA COSTA | G9: Seleto | H9: Grupo JLR | I9: Seleto | K9: Recicla Engenharia
A10: Auto Park | B10: Viver Treinamentos | D10: SulClean | F10: Masstin | G10: Grupo RCR | H10: Grupo RCR | I10: Cheiro de Mata
A11: BM Serviços de Jardinagem | B11: Primazzia | D11: Pratica Service | F11: Artemp | G11: Primar | H11: GR | I11: AgroGarden
A12: Brasanitas | B12: CM Couto | D12: MAP | F12: Lorenzo | G12: SulClean | H12: SulClean | I12: GSBRU
A13: Brasil Gestão | B13: Solução | D13: LNR | G13: Segurpro | H13: Sioux | I13: Paisagismo Ouro
A14: Brasil Park | B14: Brasil Gestão | G14: GR | H14: Grupo Serval | I14: Vegetal
A15: Bravo Fire | B15: Bravo Fire | G15: Project | H15: Embavig | I15: Leve Paisagismo
A16: C&C | B16: AMPLA Resgate Treinamentos | G16: Protesul | H16: Project | I16: Marcia Novaes Paisagismo
A17: Chácara Phoenix | B17: Action Fire | H17: Sion | I17: Jardinando
A18: Cheiro de Mata | B18: Enseg | H18: Segurpro | I18: Marcia Lima Paisagismo
A19: CM Couto | H19: Protesul | I19: BM Serviços de Jardinagem
A20: Colecta | I20: Ambi Verde
A21: CTA | B21: Variações GPS | C21: Variações Verzani | D21: Variações Brasanitas | E21: Variações Grupo Altum | F21: Variações Seleto | G21: Variações Grupo JLR | I21: Floreada
A22: Embavig | B22: Top Service | C22: Veman | D22: Infralink | E22: Liberdade | F22: Líder | G22: Sudeste | I22: Chácara Phoenix
A23: EMOAR | B23: In Haus | E23: 5 estrelas | F23: Prosper | I23: Agrotexas
A24: Enseg | B24: Vivante | E24: Tecnoguarda | I24: Agro Rio
A25: Flora Rocha | B25: Graber | E25: Tecnoseg | I25: Rena's Paisagismo
A26: Floreada | B26: Sunset | E26: Master | I26: Oficina Jardim
A27: Fluency | B27: Visel | E27: Adversi | I27: Garden Green
A28: FTR | B28: Polo Norte | E28: 5SS | I28: Real Mudas
A29: GEBE Garden | B29: SERVIS
A30: GPS
A31: GR
A32: Grupo Altum
A33: Grupo JLR
A34: Grupo Opus
A35: Grupo RCR
A36: Grupo Serval
A37: GSBRU
A38: IMC Saste
A39: Império
A40: Índigo
A41: Jardinando
... A91: Ambiente Verde

Sheet Categoria
A1: RJ
A2: Brigada de Incêndio
A3: CAG Lojista
A4: Estacionamento
A5: Estacionamento|Portaria 1 atendente 6x1
A6: Fraldário
A7: Jardinagem
A8: Limpeza
A9: Limpeza - Barra Bonita
A10: Manutenção
A11: Manutenção CAG
A12: PMOC
... A19: Vigilância

Sheet tabShoppingsEmails
A1: Shopping | B1: E-mails consolidados | C1: E-mails teste
A2: Amazonas Shopping | B2: andrezza.gaona@allos.co; karen.lima@allos.co; larissa.enes@allos.co; roberto.filho@allos.co; gregori.saavedra@allos.co; pedro.mendes@allos.co
A3: Shopping da Bahia | B3: leidiane.santos@allos.co; antonio.carvalho@allos.co; jose.azevedo@allos.co; jose.fortes@allos.co; mauricio.cerqueira@allos.co; joeval.souza@allos.co; adolfo.klein@allos.co; adson.santos@allos.co; gilson.souza@allos.co
A4: Bangu Shopping | B4: alex.costa@allos.co; victor.fortunato@allos.co; valeria.grajauskas@allos.co; nathally.santos@allos.co; paulo.assis@allos.co; michele.ramos@allos.co; joana.malheiros@atlasinovacoes.com.br
A5: Boulevard Bauru | B5: kelly.bezerrra@boulevardshoppingbauru.com.br; yumi.leite@boulevardshoppingbauru.com.br; murillo.rosa@boulevardshoppingbauru.com.br; fabio.correa@boulevardshoppingbauru.com.br; higor.carneiro@boulevardshoppingbauru.com.br
A6: Boulevard Belém | B6: yugnarley.cintra@allos.co; jose.alfaia@allos.co; joelma.muniz@allos.co; jaqueline.silva@allos.co; alan.rodriguez@allos.co; favacho.junior@allos.co; ana.deoliveira@allos.co; cinthia.araujo@allos.co
A7: Boulevard BH | B7: carla.costa@allos.co; carla.mairinck@allos.co; davidson.pelolungo@allos.co; mariana.almeida@allos.co; denilson.sanches@allos.co; cassio.costa@allos.co; maressa.oliveira@allos.co
A8: Shopping Campo Grande | B8: wilson.lobo@allos.co; murillo.meyer@allos.co; alexandre.ramos@allos.co; ludimila.machado@allos.co
A9: Shopping Campo Limpo | B9: vania.assis@allos.co; gabriela.queiroz@allos.co; camila.pontes@allos.co; fabio.gurjao@allos.co; silvia.machado@allos.co; ricardo.santos@allos.co; fabio.correa@allos.co
A10: Carioca Shopping | B10: david.souza@allos.co; bruna.wanzeler@allos.co; priscilla.souza@allos.co; julio.spinelli@allos.co; andressa.vieira@allos.co; gd_geop.cariocashopping@allos.co; alessandro.gomes@allos.co
A11: Cariri Shopping | B11: rafaela.portilho@caririshopping.com.br; brenda.brito@caririshopping.com.br; vitoria.silva@caririshopping.com.br; emilly.santos@caririshopping.com.br; ana.andrade@caririshopping.com.br; jesualdo.farias@caririshopping.com.br
A12: Catuaí Shopping Londrina | B12: willian.elsner@allos.co; erminia.wada@allos.co; everton.stock@allos.co; giovani.junior@allos.co; tienne.rezende@allos.co
A13: Catuaí Shopping Maringá | B13: sandra.sakamoto@allos.co; marcelo.mizuta@allos.co; emerson.junior@allos.co; daniela.aldrovande@allos.co; lindomar.freitas@allos.co; jonas.godeny@allos.co elaine.oliveira@allos.co
... A50: Shopping Villa Lobos | B50: renan.mattos@allos.co; rita.silva@allos.co; kathleen.hoveler@allos.co; wellington.novaes@allos.co;alberto.oliveira@allos.co

Sheet Teste
A1: Shopping | B1: E-mails consolidados | C1: E-mails teste
A2: Amazonas Shopping | B2: andrezza.gaona@allos.co; karen.lima@allos.co; larissa.enes@allos.co; roberto.filho@allos.co; gregori.saavedra@allos.co; pedro.mendes@allos.co
A3: Shopping da Bahia | B3: leidiane.santos@allos.co; antonio.carvalho@allos.co; jose.azevedo@allos.co; jose.fortes@allos.co; mauricio.cerqueira@allos.co; joeval.souza@allos.co; adolfo.klein@allos.co; adson.santos@allos.co; gilson.souza@allos.co

Sheet Faturamento RJ
B1: Data de Envio | C1: Enviou/Retornou a Medição? | D1: Unidade | E1: Categoria | F1: Fornecedor | G1: HC Organograma | H1: HC Planilha | I1: Dias Faltas | J1: Horas Atrasos | K1: Valor Planilha | L1: Desconto de faltas solicitado pelo fornecedor | M1: Desconto Falta Validado Atlas | N1: Desconto de atrasos solicitado pelo fornecedor | O1: Desconto Atrasos Validado Atlas | P1: Desconto SLA Mês | Q1: Desconto SLA Retroativo | R1: Desconto Equipamentos | S1: Prêmio Assiduidade | T1: Outros descontos | U1: Vai descontar SLA? | V1: Valor mensal final | W1: Taxa de prorrogação do prazo pagamento | X1: Valor mensal com prorrogação do prazo pagamento | Y1: Retroativo de dissídio | Z1: Parcela (x/x) | AA1: Mês de referência para faturamento | AB1: Mês de emissão da NF | AC1: Extras Solicitado pelo fornecedor | AD1: Valor extras validado Atlas | AE1: Valor NF Extra | AF1: NF enviada sistema? | AG1: Valor NF | AH1: NF ok? | AI1: SEFIP Enviada Sistema? | AJ1: Saving Faltas | AK1: Saving Extras | AL1: Deduções Totais | AM1: Observações | AN1: E-mail
C2: Não | D2: Bangu Shopping | E2: Brigada de Incêndio | F2: FTR | G2: 16 | H2: 12 | I2: 0 | J2: 0 | K2: 77251.409 | L2: 0 | M2: 0 | N2: 0 | O2: 0 | P2: Preenchimento pendente | Q2: 0 | R2: 0 | S2: 0 | T2: 0 | V2: =IFERROR((K2+M2+R2+S2+T2+O2)+IF(U2="Sim",P2+Q2,0),(K2+R2+S2+T2)+IF(U2="Sim",P2+Q2,0)) -> 77251.409 | AA2: 45658 | AB2: {=IFERROR( IF( _xlfn.XLOOKUP( 1, ( ('Condições de Faturamento'!$C$2:$C$1000 = Tab_Faturamento_RJ[[#This Row],[Unidade]]) * ('Condições de Faturamento'!$D$2:$D$1000 = Tab_Faturamento_RJ[[#This Row],[Categoria]]) * ('Condições de Faturamento'!$E$2:$E$1000 = Tab_Faturamento_RJ[[#This Row],[Fornecedor]]) ), 'Condições de Faturamento'!$F$2:$F$1000 ) = "Emissão no mês da prestação do serviço", Tab_Faturamento_RJ[[#This Row],[Mês de referência para faturamento]], DATE( YEAR(Tab_Faturamento_RJ[[#This Row],[Mês de referência para faturamento]]), MONTH(Tab_Faturamento_RJ[[#This Row],[Mês de referência para faturamento]]) + 1, DAY(Tab_Faturamento_RJ[[#This Row],[Mês de referência para faturamento]]) ) ), DATE( YEAR(Tab_Faturamento_RJ[[#This Row],[Mês de referência para faturamento]]), MONTH(Tab_Faturamento_RJ[[#This Row],[Mês de referência para faturamento]]) + 1, DAY(Tab_Faturamento_RJ[[#This Row],[Mês de referência para faturamento]]) ) )} -> 45658 | AJ2: =IFERROR(L2-M2,0) -> 0 | AK2: =AC2-AD2 -> 0 | AL2: =K2-V2 -> 0 | AN2: kaike.costa@atlasinovacoes.com.br
C3: Não | D3: Bangu Shopping | E3: Brigada de Incêndio | F3: FTR | G3: 16 | H3: 12 | I3: Informação pendente | J3: Informação pendente | K3: 77251.409 | L3: 0 | M3: Informação pendente | N3: 0 | O3: Informação pendente | P3: Preenchimento pendente | Q3: 0 | R3: 0 | S3: 0 | T3: 0 | V3: =IFERROR((K3+M3+R3+S3+T3+O3)+IF(U3="Sim",P3+Q3,0),(K3+R3+S3+T3)+IF(U3="Sim",P3+Q3,0)) -> 77251.409 | AA3: 45689 | AB3: {=IFERROR( IF( _xlfn.XLOOKUP( 1, ( ('Condições de Faturamento'!$C$2:$C$1000 = Tab_Faturamento_RJ[[#This Row],[Unidade]]) * ('Condições de Faturamento'!$D$2:$D$1000 = Tab_Faturamento_RJ[[#This Row],[Categoria]]) * ('Condições de Faturamento'!$E$2:$E$1000 = Tab_Faturamento_RJ[[#This Row],[Fornecedor]]) ), 'Condições de Faturamento'!$F$2:$F$1000 ) = "Emissão no mês da prestação do serviço", Tab_Faturamento_RJ[[#This Row],[Mês de referência para faturamento]], DATE( YEAR(Tab_Faturamento_RJ[[#This Row],[Mês de referência para faturamento]]), MONTH(Tab_Faturamento_RJ[[#This Row],[Mês de referência para faturamento]]) + 1, DAY(Tab_Faturamento_RJ[[#This Row],[Mês de referência para faturamento]]) ) ), DATE( YEAR(Tab_Faturamento_RJ[[#This Row],[Mês de referência para faturamento]]), MONTH(Tab_Faturamento_RJ[[#This Row],[Mês de referência para faturamento]]) + 1, DAY(Tab_Faturamento_RJ[[#This Row],[Mês de referência para faturamento]]) ) )} -> 45689 | AJ3: =IFERROR(L3-M3,0) -> 0 | AK3: =AC3-AD3 -> 0 | AL3: =K3-V3 -> 0 | AN3: kaike.costa@atlasinovacoes.com.br
B4: 45748 | C4: Sim | D4: Bangu Shopping | E4: Brigada de Incêndio | F4: FTR | G4: 16 | H4: 12 | I4: 0 | J4: 0 | K4: 77251.409 | L4: 0 | M4: 0 | N4: 0 | O4: 0 | P4: 0 | Q4: 0 | R4: 0 | S4: 0 | T4: 0 | U4: Sim | V4: =IFERROR((K4+M4+R4+S4+T4+O4)+IF(U4="Sim",P4+Q4,0),(K4+R4+S4+T4)+IF(U4="Sim",P4+Q4,0)) -> 77251.409 | AA4: 45717 | AB4: {=IFERROR( IF( _xlfn.XLOOKUP( 1, ( ('Condições de Faturamento'!$C$2:$C$1000 = Tab_Faturamento_RJ[[#This Row],[Unidade]]) * ('Condições de Faturamento'!$D$2:$D$1000 = Tab_Faturamento_RJ[[#This Row],[Categoria]]) * ('Condições de Faturamento'!$E$2:$E$1000 = Tab_Faturamento_RJ[[#This Row],[Fornecedor]]) ), 'Condições de Faturamento'!$F$2:$F$1000 ) = "Emissão no mês da prestação do serviço", Tab_Faturamento_RJ[[#This Row],[Mês de referência para faturamento]], DATE( YEAR(Tab_Faturamento_RJ[[#This Row],[Mês de referência para faturamento]]), MONTH(Tab_Faturamento_RJ[[#This Row],[Mês de referência para faturamento]]) + 1, DAY(Tab_Faturamento_RJ[[#This Row],[Mês de referência para faturamento]]) ) ), DATE( YEAR(Tab_Faturamento_RJ[[#This Row],[Mês de referência para faturamento]]), MONTH(Tab_Faturamento_RJ[[#This Row],[Mês de referência para faturamento]]) + 1, DAY(Tab_Faturamento_RJ[[#This Row],[Mês de referência para faturamento]]) ) )} -> 45717 | AJ4: =IFERROR(L4-M4,0) -> 0 | AK4: =AC4-AD4 -> 0 | AL4: =K4-V4 -> 0 | AN4: kaike.costa@atlasinovacoes.com.br
C5: Não | D5: Bangu Shopping | E5: Brigada de Incêndio | F5: FTR | G5: 16 | H5: 12 | I5: 0 | J5: 0 | K5: 77251.409 | L5: 0 | M5: 0 | N5: 0 | O5: 0 | P5: 0 | Q5: 0 | R5: 0 | S5: 0 | T5: 0 | V5: =IFERROR((K5+M5+R5+S5+T5+O5)+IF(U5="Sim",P5+Q5,0),(K5+R5+S5+T5)+IF(U5="Sim",P5+Q5,0)) -> 77251.409 | AA5: 45748 | AB5: {=IFERROR( IF( _xlfn.XLOOKUP( 1, ( ('Condições de Faturamento'!$C$2:$C$1000 = Tab_Faturamento_RJ[[#This Row],[Unidade]]) * ('Condições de Faturamento'!$D$2:$D$1000 = Tab_Faturamento_RJ[[#This Row],[Categoria]]) * ('Condições de Faturamento'!$E$2:$E$1000 = Tab_Faturamento_RJ[[#This Row],[Fornecedor]]) ), 'Condições de Faturamento'!$F$2:$F$1000 ) = "Emissão no mês da prestação do serviço", Tab_Faturamento_RJ[[#This Row],[Mês de referência para faturamento]], DATE( YEAR(Tab_Faturamento_RJ[[#This Row],[Mês de referência para faturamento]]), MONTH(Tab_Faturamento_RJ[[#This Row],[Mês de referência para faturamento]]) + 1, DAY(Tab_Faturamento_RJ[[#This Row],[Mês de referência para faturamento]]) ) ), DATE( YEAR(Tab_Faturamento_RJ[[#This Row],[Mês de referência para faturamento]]), MONTH(Tab_Faturamento_RJ[[#This Row],[Mês de referência para faturamento]]) + 1, DAY(Tab_Faturamento_RJ[[#This Row],[Mês de referência para faturamento]]) ) )} -> 45748 | AJ5: =IFERROR(L5-M5,0) -> 0 | AK5: =AC5-AD5 -> 0 | AL5: =K5-V5 -> 0 | AN5: kaike.costa@atlasinovacoes.com.br
B6: 45812 | C6: Sim | D6: Bangu Shopping | E6: Brigada de Incêndio | F6: FTR | G6: 16 | H6: 12 | I6: 0 | J6: 0 | K6: 77251.409 | L6: 0 | M6: 0 | N6: 0 | O6: 0 | P6: 0 | Q6: 0 | R6: 0 | S6: 0 | T6: 0 | U6: Não | V6: =IFERROR((K6+M6+R6+S6+T6+O6)+IF(U6="Sim",P6+Q6,0),(K6+R6+S6+T6)+IF(U6="Sim",P6+Q6,0)) -> 77251.409 | AA6: 45778 | AB6: {=IFERROR( IF( _xlfn.XLOOKUP( 1, ( ('Condições de Faturamento'!$C$2:$C$1000 = Tab_Faturamento_RJ[[#This Row],[Unidade]]) * ('Condições de Faturamento'!$D$2:$D$1000 = Tab_Faturamento_RJ[[#This Row],[Categoria]]) * ('Condições de Faturamento'!$E$2:$E$1000 = Tab_Faturamento_RJ[[#This Row],[Fornecedor]]) ), 'Condições de Faturamento'!$F$2:$F$1000 ) = "Emissão no mês da prestação do serviço", Tab_Faturamento_RJ[[#This Row],[Mês de referência para faturamento]], DATE( YEAR(Tab_Faturamento_RJ[[#This Row],[Mês de referência para faturamento]]), MONTH(Tab_Faturamento_RJ[[#This Row],[Mês de referência para faturamento]]) + 1, DAY(Tab_Faturamento_RJ[[#This Row],[Mês de referência para faturamento]]) ) ), DATE( YEAR(Tab_Faturamento_RJ[[#This Row],[Mês de referência para faturamento]]), MONTH(Tab_Faturamento_RJ[[#This Row],[Mês de referência para faturamento]]) + 1, DAY(Tab_Faturamento_RJ[[#This Row],[Mês de referência para faturamento]]) ) )} -> 45778 | AJ6: =IFERROR(L6-M6,0) -> 0 | AK6: =AC6-AD6 -> 0 | AL6: =K6-V6 -> 0 | AN6: kaike.costa@atlasinovacoes.com.br
B7: 45839 | C7: Sim | D7: Bangu Shopping | E7: Brigada de Incêndio | F7: FTR | G7: 16 | H7: 12 | I7: 0 | J7: 0 | K7: 77251.409 | L7: 0 | M7: 0 | N7: 0 | O7: 0 | P7: Preenchimento pendente | Q7: 0 | R7: 0 | S7: 0 | T7: 0 | U7: Não | V7: =IFERROR((K7+M7+R7+S7+T7+O7)+IF(U7="Sim",P7+Q7,0),(K7+R7+S7+T7)+IF(U7="Sim",P7+Q7,0)) -> 77251.409 | AA7: 45809 | AB7: {=IFERROR( IF( _xlfn.XLOOKUP( 1, ( ('Condições de Faturamento'!$C$2:$C$1000 = Tab_Faturamento_RJ[[#This Row],[Unidade]]) * ('Condições de Faturamento'!$D$2:$D$1000 = Tab_Faturamento_RJ[[#This Row],[Categoria]]) * ('Condições de Faturamento'!$E$2:$E$1000 = Tab_Faturamento_RJ[[#This Row],[Fornecedor]]) ), 'Condições de Faturamento'!$F$2:$F$1000 ) = "Emissão no mês da prestação do serviço", Tab_Faturamento_RJ[[#This Row],[Mês de referência para faturamento]], DATE( YEAR(Tab_Faturamento_RJ[[#This Row],[Mês de referência para faturamento]]), MONTH(Tab_Faturamento_RJ[[#This Row],[Mês de referência para faturamento]]) + 1, DAY(Tab_Faturamento_RJ[[#This Row],[Mês de referência para faturamento]]) ) ), DATE( YEAR(Tab_Faturamento_RJ[[#This Row],[Mês de referência para faturamento]]), MONTH(Tab_Faturamento_RJ[[#This Row],[Mês de referência para faturamento]]) + 1, DAY(Tab_Faturamento_RJ[[#This Row],[Mês de referência para faturamento]]) ) )} -> 45809 | AJ7: =IFERROR(L7-M7,0) -> 0 | AK7: =AC7-AD7 -> 0 | AL7: =K7-V7 -> 0 | AN7: kaike.costa@atlasinovacoes.com.br
C8: Não | D8: Bangu Shopping | E8: Brigada de Incêndio | F8: FTR | G8: 16 | H8: 12 | I8: Informação pendente | J8: Informação pendente | K8: 81671.16 | L8: 0 | M8: Informação pendente | N8: 0 | O8: Informação pendente | P8: 0 | Q8: 0 | R8: 0 | S8: 0 | T8: 0 | V8: =IFERROR((K8+M8+R8+S8+T8+O8)+IF(U8="Sim",P8+Q8,0),(K8+R8+S8+T8)+IF(U8="Sim",P8+Q8,0)) -> 81671.16 | AA8: 45870 | AB8: {=IFERROR( IF( _xlfn.XLOOKUP( 1, ( ('Condições de Faturamento'!$C$2:$C$1000 = Tab_Faturamento_RJ[[#This Row],[Unidade]]) * ('Condições de Faturamento'!$D$2:$D$1000 = Tab_Faturamento_RJ[[#This Row],[Categoria]]) * ('Condições de Faturamento'!$E$2:$E$1000 = Tab_Faturamento_RJ[[#This Row],[Fornecedor]]) ), 'Condições de Faturamento'!$F$2:$F$1000 ) = "Emissão no mês da prestação do serviço", Tab_Faturamento_RJ[[#This Row],[Mês de referência para faturamento]], DATE( YEAR(Tab_Faturamento_RJ[[#This Row],[Mês de referência para faturamento]]), MONTH(Tab_Faturamento_RJ[[#This Row],[Mês de referência para faturamento]]) + 1, DAY(Tab_Faturamento_RJ[[#This Row],[Mês de referência para faturamento]]) ) ), DATE( YEAR(Tab_Faturamento_RJ[[#This Row],[Mês de referência para faturamento]]), MONTH(Tab_Faturamento_RJ[[#This Row],[Mês de referência para faturamento]]) + 1, DAY(Tab_Faturamento_RJ[[#This Row],[Mês de referência para faturamento]]) ) )} -> 45870 | AC8: 6699.5705 | AD8: 6699.5705 | AJ8: =IFERROR(L8-M8,0) -> 0 | AK8: =AC8-AD8 -> 0 | AL8: =K8-V8 -> 0 | AN8: kaike.costa@atlasinovacoes.com.br
B9: 45870 | C9: Sim | D9: Bangu Shopping | E9: Brigada de Incêndio | F9: FTR | G9: 16 | H9: 12 | I9: 0 | J9: 0 | K9: 81671.16 | L9: 0 | M9: 0 | N9: 0 | O9: 0 | P9: Preenchimento pendente | Q9: 0 | R9: 0 | S9: 0 | T9: 0 | V9: =IFERROR((K9+M9+R9+S9+T9+O9)+IF(U9="Sim",P9+Q9,0),(K9+R9+S9+T9)+IF(U9="Sim",P9+Q9,0)) -> 81671.16 | AA9: 45839 | AB9: {=IFERROR( IF( _xlfn.XLOOKUP( 1, ( ('Condições de Faturamento'!$C$2:$C$1000 = Tab_Faturamento_RJ[[#This Row],[Unidade]]) * ('Condições de Faturamento'!$D$2:$D$1000 = Tab_Faturamento_RJ[[#This Row],[Categoria]]) * ('Condições de Faturamento'!$E$2:$E$1000 = Tab_Faturamento_RJ[[#This Row],[Fornecedor]]) ), 'Condições de Faturamento'!$F$2:$F$1000 ) = "Emissão no mês da prestação do serviço", Tab_Faturamento_RJ[[#This Row],[Mês de referência para faturamento]], DATE( YEAR(Tab_Faturamento_RJ[[#This Row],[Mês de referência para faturamento]]), MONTH(Tab_Faturamento_RJ[[#This Row],[Mês de referência para faturamento]]) + 1, DAY(Tab_Faturamento_RJ[[#This Row],[Mês de referência para faturamento]]) ) ), DATE( YEAR(Tab_Faturamento_RJ[[#This Row],[Mês de referência para faturamento]]), MONTH(Tab_Faturamento_RJ[[#This Row],[Mês de referência para faturamento]]) + 1, DAY(Tab_Faturamento_RJ[[#This Row],[Mês de referência para faturamento]]) ) )} -> 45839 | AJ9: =IFERROR(L9-M9,0) -> 0 | AK9: =AC9-AD9 -> 0 | AL9: =K9-V9 -> 0 | AN9: kaike.costa@atlasinovacoes.com.br
C10: Não | D10: Bangu Shopping | E10: Brigada de Incêndio | F10: FTR | G10: 16 | H10: 12 | I10: Informação pendente | J10: Informação pendente | K10: 81671.16 | L10: 0 | M10: Informação pendente | N10: 0 | O10: Informação pendente | P10: 0 | Q10: 0 | R10: 0 | S10: 0 | T10: 0 | V10: =IFERROR((K10+M10+R10+S10+T10+O10)+IF(U10="Sim",P10+Q10,0),(K10+R10+S10+T10)+IF(U10="Sim",P10+Q10,0)) -> 81671.16 | AA10: 45901 | AB10: {=IFERROR( IF( _xlfn.XLOOKUP( 1, ( ('Condições de Faturamento'!$C$2:$C$1000 = Tab_Faturamento_RJ[[#This Row],[Unidade]]) * ('Condições de Faturamento'!$D$2:$D$1000 = Tab_Faturamento_RJ[[#This Row],[Categoria]]) * ('Condições de Faturamento'!$E$2:$E$1000 = Tab_Faturamento_RJ[[#This Row],[Fornecedor]]) ), 'Condições de Faturamento'!$F$2:$F$1000 ) = "Emissão no mês da prestação do serviço", Tab_Faturamento_RJ[[#This Row],[Mês de referência para faturamento]], DATE( YEAR(Tab_Faturamento_RJ[[#This Row],[Mês de referência para faturamento]]), MONTH(Tab_Faturamento_RJ[[#This Row],[Mês de referência para faturamento]]) + 1, DAY(Tab_Faturamento_RJ[[#This Row],[Mês de referência para faturamento]]) ) ), DATE( YEAR(Tab_Faturamento_RJ[[#This Row],[Mês de referência para faturamento]]), MONTH(Tab_Faturamento_RJ[[#This Row],[Mês de referência para faturamento]]) + 1, DAY(Tab_Faturamento_RJ[[#This Row],[Mês de referência para faturamento]]) ) )} -> 45901 | AD10: 3497.9 | AJ10: =IFERROR(L10-M10,0) -> 0 | AK10: =AC10-AD10 -> -3497.9 | AL10: =K10-V10 -> 0 | AN10: kaike.costa@atlasinovacoes.com.br
C11: Não | D11: Bangu Shopping | E11: Brigada de Incêndio | F11: FTR | G11: 16 | H11: 12 | I11: Informação pendente | J11: Informação pendente | K11: 81671.16 | M11: Informação pendente | O11: Informação pendente | P11: Preenchimento pendente | V11: =IFERROR((K11+M11+R11+S11+T11+O11)+IF(U11="Sim",P11+Q11,0),(K11+R11+S11+T11)+IF(U11="Sim",P11+Q11,0)) -> 81671.16 | AA11: 45931 | AB11: {=IFERROR( IF( _xlfn.XLOOKUP( 1, ( ('Condições de Faturamento'!$C$2:$C$1000 = Tab_Faturamento_RJ[[#This Row],[Unidade]]) * ('Condições de Faturamento'!$D$2:$D$1000 = Tab_Faturamento_RJ[[#This Row],[Categoria]]) * ('Condições de Faturamento'!$E$2:$E$1000 = Tab_Faturamento_RJ[[#This Row],[Fornecedor]]) ), 'Condições de Faturamento'!$F$2:$F$1000 ) = "Emissão no mês da prestação do serviço", Tab_Faturamento_RJ[[#This Row],[Mês de referência para faturamento]], DATE( YEAR(Tab_Faturamento_RJ[[#This Row],[Mês de referência para faturamento]]), MONTH(Tab_Faturamento_RJ[[#This Row],[Mês de referência para faturamento]]) + 1, DAY(Tab_Faturamento_RJ[[#This Row],[Mês de referência para faturamento]]) ) ), DATE( YEAR(Tab_Faturamento_RJ[[#This Row],[Mês de referência para faturamento]]), MONTH(Tab_Faturamento_RJ[[#This Row],[Mês de referência para faturamento]]) + 1, DAY(Tab_Faturamento_RJ[[#This Row],[Mês de referência para faturamento]]) ) )} -> 45931 | AJ11: =IFERROR(L11-M11,0) -> 0 | AK11: =AC11-AD11 -> 0 | AL11: =K11-V11 -> 0 | AN11: kaike.costa@atlasinovacoes.com.br
B12: 45842 | C12: Sim | D12: Bangu Shopping | E12: Limpeza | F12: Verzani | G12: 65 | H12: 60 | I12: 15 | J12: 0 | K12: 335112.54 | L12: 0 | M12: -2342.01 | N12: 0 | O12: 0 | P12: =-1675.56 -> -1675.56 | Q12: 0 | R12: 0 | S12: 0 | T12: 0 | U12: Sim | V12: =IFERROR((K12+M12+R12+S12+T12+O12)+IF(U12="Sim",P12+Q12,0),(K12+R12+S12+T12)+IF(U12="Sim",P12+Q12,0)) -> 331094.97 | Y12: =126534.36/4 -> 31633.59 | Z12: 3|4 | AA12: 45839 | AB12: {=IFERROR( IF( _xlfn.XLOOKUP( 1, ( ('Condições de Faturamento'!$C$2:$C$1000 = Tab_Faturamento_RJ[[#This Row],[Unidade]]) * ('Condições de Faturamento'!$D$2:$D$1000 = Tab_Faturamento_RJ[[#This Row],[Categoria]]) * ('Condições de Faturamento'!$E$2:$E$1000 = Tab_Faturamento_RJ[[#This Row],[Fornecedor]]) ), 'Condições de Faturamento'!$F$2:$F$1000 ) = "Emissão no mês da prestação do serviço", Tab_Faturamento_RJ[[#This Row],[Mês de referência para faturamento]], DATE( YEAR(Tab_Faturamento_RJ[[#This Row],[Mês de referência para faturamento]]), MONTH(Tab_Faturamento_RJ[[#This Row],[Mês de referência para faturamento]]) + 1, DAY(Tab_Faturamento_RJ[[#This Row],[Mês de referência para faturamento]]) ) ), DATE( YEAR(Tab_Faturamento_RJ[[#This Row],[Mês de referência para faturamento]]), MONTH(Tab_Faturamento_RJ[[#This Row],[Mês de referência para faturamento]]) + 1, DAY(Tab_Faturamento_RJ[[#This Row],[Mês de referência para faturamento]]) ) )} -> 45839 | AJ12: =IFERROR(L12-M12,0) -> 2342.01 | AK12: =AC12-AD12 -> 0 | AL12: =K12-V12 -> 4017.57 | AN12: kaike.costa@atlasinovacoes.com.br
D13: Bangu Shopping | E13: Brigada de Incêndio | F13: FTR | G13: 16 | V13: =IFERROR((K13+M13+R13+S13+T13+O13)+IF(U13="Sim",P13+Q13,0),(K13+R13+S13+T13)+IF(U13="Sim",P13+Q13,0)) -> 0 | AA13: 45962 | AB13: {=IFERROR( IF( _xlfn.XLOOKUP( 1, ( ('Condições de Faturamento'!$C$2:$C$1000 = Tab_Faturamento_RJ[[#This Row],[Unidade]]) * ('Condições de Faturamento'!$D$2:$D$1000 = Tab_Faturamento_RJ[[#This Row],[Categoria]]) * ('Condições de Faturamento'!$E$2:$E$1000 = Tab_Faturamento_RJ[[#This Row],[Fornecedor]]) ), 'Condições de Faturamento'!$F$2:$F$1000 ) = "Emissão no mês da prestação do serviço", Tab_Faturamento_RJ[[#This Row],[Mês de referência para faturamento]], DATE( YEAR(Tab_Faturamento_RJ[[#This Row],[Mês de referência para faturamento]]), MONTH(Tab_Faturamento_RJ[[#This Row],[Mês de referência para faturamento]]) + 1, DAY(Tab_Faturamento_RJ[[#This Row],[Mês de referência para faturamento]]) ) ), DATE( YEAR(Tab_Faturamento_RJ[[#This Row],[Mês de referência para faturamento]]), MONTH(Tab_Faturamento_RJ[[#This Row],[Mês de referência para faturamento]]) + 1, DAY(Tab_Faturamento_RJ[[#This Row],[Mês de referência para faturamento]]) ) )} -> 45962 | AJ13: =IFERROR(L13-M13,0) -> 0 | AK13: =AC13-AD13 -> 0 | AL13: =K13-V13 -> 0 | AN13: kaike.costa@atlasinovacoes.com.br
D14: Bangu Shopping | E14: Brigada de Incêndio | F14: FTR | G14: 16 | V14: =IFERROR((K14+M14+R14+S14+T14+O14)+IF(U14="Sim",P14+Q14,0),(K14+R14+S14+T14)+IF(U14="Sim",P14+Q14,0)) -> 0 | AA14: 45992 | AB14: {=IFERROR( IF( _xlfn.XLOOKUP( 1, ( ('Condições de Faturamento'!$C$2:$C$1000 = Tab_Faturamento_RJ[[#This Row],[Unidade]]) * ('Condições de Faturamento'!$D$2:$D$1000 = Tab_Faturamento_RJ[[#This Row],[Categoria]]) * ('Condições de Faturamento'!$E$2:$E$1000 = Tab_Faturamento_RJ[[#This Row],[Fornecedor]]) ), 'Condições de Faturamento'!$F$2:$F$1000 ) = "Emissão no mês da prestação do serviço", Tab_Faturamento_RJ[[#This Row],[Mês de referência para faturamento]], DATE( YEAR(Tab_Faturamento_RJ[[#This Row],[Mês de referência para faturamento]]), MONTH(Tab_Faturamento_RJ[[#This Row],[Mês de referência para faturamento]]) + 1, DAY(Tab_Faturamento_RJ[[#This Row],[Mês de referência para faturamento]]) ) ), DATE( YEAR(Tab_Faturamento_RJ[[#This Row],[Mês de referência para faturamento]]), MONTH(Tab_Faturamento_RJ[[#This Row],[Mês de referência para faturamento]]) + 1, DAY(Tab_Faturamento_RJ[[#This Row],[Mês de referência para faturamento]]) ) )} -> 45992 | AD14: 2882.57 | AJ14: =IFERROR(L14-M14,0) -> 0 | AK14: =AC14-AD14 -> -2882.57 | AL14: =K14-V14 -> 0 | AN14: kaike.costa@atlasinovacoes.com.br
C15: Sim | D15: Bangu Shopping | E15: Fraldário | F15: Verzani | G15: 2 | H15: 2 | I15: 0 | J15: 0 | K15: =8163.51/30.4375*9 -> 2413.851 | L15: 0 | M15: 0 | N15: 0 | O15: 0 | P15: 0 | Q15: 0 | R15: 0 | S15: 0 | T15: 0 | U15: Sim | V15: =IFERROR((K15+M15+R15+S15+T15+O15)+IF(U15="Sim",P15+Q15,0),(K15+R15+S15+T15)+IF(U15="Sim",P15+Q15,0)) -> 2413.851 | AA15: 45717 | AB15: {=IFERROR( IF( _xlfn.XLOOKUP( 1, ( ('Condições de Faturamento'!$C$2:$C$1000 = Tab_Faturamento_RJ[[#This Row],[Unidade]]) * ('Condições de Faturamento'!$D$2:$D$1000 = Tab_Faturamento_RJ[[#This Row],[Categoria]]) * ('Condições de Faturamento'!$E$2:$E$1000 = Tab_Faturamento_RJ[[#This Row],[Fornecedor]]) ), 'Condições de Faturamento'!$F$2:$F$1000 ) = "Emissão no mês da prestação do serviço", Tab_Faturamento_RJ[[#This Row],[Mês de referência para faturamento]], DATE( YEAR(Tab_Faturamento_RJ[[#This Row],[Mês de referência para faturamento]]), MONTH(Tab_Faturamento_RJ[[#This Row],[Mês de referência para faturamento]]) + 1, DAY(Tab_Faturamento_RJ[[#This Row],[Mês de referência para faturamento]]) ) ), DATE( YEAR(Tab_Faturamento_RJ[[#This Row],[Mês de referência para faturamento]]), MONTH(Tab_Faturamento_RJ[[#This Row],[Mês de referência para faturamento]]) + 1, DAY(Tab_Faturamento_RJ[[#This Row],[Mês de referência para faturamento]]) ) )} -> 45748 | AJ15: =IFERROR(L15-M15,0) -> 0 | AK15: =AC15-AD15 -> 0 | AL15: =K15-V15 -> 0 | AN15: kaike.costa@atlasinovacoes.com.br
B16: 45660 | C16: Sim | D16: Bangu Shopping | E16: Fraldário | F16: Verzani | G16: 2 | H16: 2 | I16: 0 | J16: 0 | K16: 8163.51 | L16: 0 | M16: 0 | N16: 0 | O16: 0 | P16: 0 | Q16: 0 | R16: 0 | S16: 0 | T16: 0 | U16: Não | V16: =IFERROR((K16+M16+R16+S16+T16+O16)+IF(U16="Sim",P16+Q16,0),(K16+R16+S16+T16)+IF(U16="Sim",P16+Q16,0)) -> 8163.51 | AA16: 45658 | AB16: {=IFERROR( IF( _xlfn.XLOOKUP( 1, ( ('Condições de Faturamento'!$C$2:$C$1000 = Tab_Faturamento_RJ[[#This Row],[Unidade]]) * ('Condições de Faturamento'!$D$2:$D$1000 = Tab_Faturamento_RJ[[#This Row],[Categoria]]) * ('Condições de Faturamento'!$E$2:$E$1000 = Tab_Faturamento_RJ[[#This Row],[Fornecedor]]) ), 'Condições de Faturamento'!$F$2:$F$1000 ) = "Emissão no mês da prestação do serviço", Tab_Faturamento_RJ[[#This Row],[Mês de referência para faturamento]], DATE( YEAR(Tab_Faturamento_RJ[[#This Row],[Mês de referência para faturamento]]), MONTH(Tab_Faturamento_RJ[[#This Row],[Mês de referência para faturamento]]) + 1, DAY(Tab_Faturamento_RJ[[#This Row],[Mês de referência para faturamento]]) ) ), DATE( YEAR(Tab_Faturamento_RJ[[#This Row],[Mês de referência para faturamento]]), MONTH(Tab_Faturamento_RJ[[#This Row],[Mês de referência para faturamento]]) + 1, DAY(Tab_Faturamento_RJ[[#This Row],[Mês de referência para faturamento]]) ) )} -> 45689 | AJ16: =IFERROR(L16-M16,0) -> 0 | AK16: =AC16-AD16 -> 0 | AL16: =K16-V16 -> 0 | AN16: kaike.costa@atlasinovacoes.com.br
B17: 45700 | C17: Sim | D17: Bangu Shopping | E17: Fraldário | F17: Verzani | G17: 2 | H17: 2 | I17: 0 | J17: 0 | K17: 8163.51 | L17: 0 | M17: 0 | N17: 0 | O17: 0 | P17: 0 | Q17: 0 | R17: 0 | S17: 0 | T17: 0 | U17: Não | V17: =IFERROR((K17+M17+R17+S17+T17+O17)+IF(U17="Sim",P17+Q17,0),(K17+R17+S17+T17)+IF(U17="Sim",P17+Q17,0)) -> 8163.51 | AA17: 45689 | AB17: {=IFERROR( IF( _xlfn.XLOOKUP( 1, ( ('Condições de Faturamento'!$C$2:$C$1000 = Tab_Faturamento_RJ[[#This Row],[Unidade]]) * ('Condições de Faturamento'!$D$2:$D$1000 = Tab_Faturamento_RJ[[#This Row],[Categoria]]) * ('Condições de Faturamento'!$E$2:$E$1000 = Tab_Faturamento_RJ[[#This Row],[Fornecedor]]) ), 'Condições de Faturamento'!$F$2:$F$1000 ) = "Emissão no mês da prestação do serviço", Tab_Faturamento_RJ[[#This Row],[Mês de referência para faturamento]], DATE( YEAR(Tab_Faturamento_RJ[[#This Row],[Mês de referência para faturamento]]), MONTH(Tab_Faturamento_RJ[[#This Row],[Mês de referência para faturamento]]) + 1, DAY(Tab_Faturamento_RJ[[#This Row],[Mês de referência para faturamento]]) ) ), DATE( YEAR(Tab_Faturamento_RJ[[#This Row],[Mês de referência para faturamento]]), MONTH(Tab_Faturamento_RJ[[#This Row],[Mês de referência para faturamento]]) + 1, DAY(Tab_Faturamento_RJ[[#This Row],[Mês de referência para faturamento]]) ) )} -> 45717 | AJ17: =IFERROR(L17-M17,0) -> 0 | AK17: =AC17-AD17 -> 0 | AL17: =K17-V17 -> 0 | AN17: kaike.costa@atlasinovacoes.com.br
B18: 45700 | C18: Sim | D18: Bangu Shopping | E18: Limpeza | F18: Verzani | G18: 65 | H18: 61 | I18: 9 | J18: 0 | K18: 298159.67 | L18: 0 | M18: -1258.03 | N18: 0 | O18: 0 | P18: -496.93 | Q18: 0 | R18: 0 | S18: 0 | T18: 0 | U18: Sim | V18: =IFERROR((K18+M18+R18+S18+T18+O18)+IF(U18="Sim",P18+Q18,0),(K18+R18+S18+T18)+IF(U18="Sim",P18+Q18,0)) -> 296404.71 | AA18: 45689 | AB18: {=IFERROR( IF( _xlfn.XLOOKUP( 1, ( ('Condições de Faturamento'!$C$2:$C$1000 = Tab_Faturamento_RJ[[#This Row],[Unidade]]) * ('Condições de Faturamento'!$D$2:$D$1000 = Tab_Faturamento_RJ[[#This Row],[Categoria]]) * ('Condições de Faturamento'!$E$2:$E$1000 = Tab_Faturamento_RJ[[#This Row],[Fornecedor]]) ), 'Condições de Faturamento'!$F$2:$F$1000 ) = "Emissão no mês da prestação do serviço", Tab_Faturamento_RJ[[#This Row],[Mês de referência para faturamento]], DATE( YEAR(Tab_Faturamento_RJ[[#This Row],[Mês de referência para faturamento]]), MONTH(Tab_Faturamento_RJ[[#This Row],[Mês de referência para faturamento]]) + 1, DAY(Tab_Faturamento_RJ[[#This Row],[Mês de referência para faturamento]]) ) ), DATE( YEAR(Tab_Faturamento_RJ[[#This Row],[Mês de referência para faturamento]]), MONTH(Tab_Faturamento_RJ[[#This Row],[Mês de referência para faturamento]]) + 1, DAY(Tab_Faturamento_RJ[[#This Row],[Mês de referência para faturamento]]) ) )} -> 45689 | AC18: 6047.1549 | AD18: 6047.1549 | AJ18: =IFERROR(L18-M18,0) -> 1258.03 | AK18: =AC18-AD18 -> 0 | AL18: =K18-V18 -> 1754.96 | AN18: kaike.costa@atlasinovacoes.com.br
B19: 45660 | C19: Sim | D19: Bangu Shopping | E19: Limpeza | F19: Verzani | G19: 65 | H19: 61 | I19: 0 | J19: 184 | K19: 298159.67 | L19: 0 | M19: 0 | N19: 0 | O19: -3445.92 | P19: 0 | Q19: 0 | R19: 0 | S19: 0 | T19: 0 | U19: Sim | V19: =IFERROR((K19+M19+R19+S19+T19+O19)+IF(U19="Sim",P19+Q19,0),(K19+R19+S19+T19)+IF(U19="Sim",P19+Q19,0)) -> 294713.75 | AA19: 45658 | AB19: {=IFERROR( IF( _xlfn.XLOOKUP( 1, ( ('Condições de Faturamento'!$C$2:$C$1000 = Tab_Faturamento_RJ[[#This Row],[Unidade]]) * ('Condições de Faturamento'!$D$2:$D$1000 = Tab_Faturamento_RJ[[#This Row],[Categoria]]) * ('Condições de Faturamento'!$E$2:$E$1000 = Tab_Faturamento_RJ[[#This Row],[Fornecedor]]) ), 'Condições de Faturamento'!$F$2:$F$1000 ) = "Emissão no mês da prestação do serviço", Tab_Faturamento_RJ[[#This Row],[Mês de referência para faturamento]], DATE( YEAR(Tab_Faturamento_RJ[[#This Row],[Mês de referência para faturamento]]), MONTH(Tab_Faturamento_RJ[[#This Row],[Mês de referência para faturamento]]) + 1, DAY(Tab_Faturamento_RJ[[#This Row],[Mês de referência para faturamento]]) ) ), DATE( YEAR(Tab_Faturamento_RJ[[#This Row],[Mês de referência para faturamento]]), MONTH(Tab_Faturamento_RJ[[#This Row],[Mês de referência para faturamento]]) + 1, DAY(Tab_Faturamento_RJ[[#This Row],[Mês de referência para faturamento]]) ) )} -> 45658 | AJ19: =IFERROR(L19-M19,0) -> 0 | AK19: =AC19-AD19 -> 0 | AL19: =K19-V19 -> 3445.92 | AN19: kaike.costa@atlasinovacoes.com.br
B20: 45722 | C20: Sim | D20: Bangu Shopping | E20: Limpeza | F20: Verzani | G20: 65 | H20: 61 | I20: 25 | J20: 0 | K20: 298159.67 | L20: 0 | M20: -3481.45 | N20: 0 | O20: 0 | P20: 0 | Q20: 0 | R20: 0 | S20: 0 | T20: 0 | U20: Sim | V20: =IFERROR((K20+M20+R20+S20+T20+O20)+IF(U20="Sim",P20+Q20,0),(K20+R20+S20+T20)+IF(U20="Sim",P20+Q20,0)) -> 294678.22 | AA20: 45717 | AB20: {=IFERROR( IF( _xlfn.XLOOKUP( 1, ( ('Condições de Faturamento'!$C$2:$C$1000 = Tab_Faturamento_RJ[[#This Row],[Unidade]]) * ('Condições de Faturamento'!$D$2:$D$1000 = Tab_Faturamento_RJ[[#This Row],[Categoria]]) * ('Condições de Faturamento'!$E$2:$E$1000 = Tab_Faturamento_RJ[[#This Row],[Fornecedor]]) ), 'Condições de Faturamento'!$F$2:$F$1000 ) = "Emissão no mês da prestação do serviço", Tab_Faturamento_RJ[[#This Row],[Mês de referência para faturamento]], DATE( YEAR(Tab_Faturamento_RJ[[#This Row],[Mês de referência para faturamento]]), MONTH(Tab_Faturamento_RJ[[#This Row],[Mês de referência para faturamento]]) + 1, DAY(Tab_Faturamento_RJ[[#This Row],[Mês de referência para faturamento]]) ) ), DATE( YEAR(Tab_Faturamento_RJ[[#This Row],[Mês de referência para faturamento]]), MONTH(Tab_Faturamento_RJ[[#This Row],[Mês de referência para faturamento]]) + 1, DAY(Tab_Faturamento_RJ[[#This Row],[Mês de referência para faturamento]]) ) )} -> 45717 | AC20: 4881.8859 | AD20: 4881.8859 | AJ20: =IFERROR(L20-M20,0) -> 3481.45 | AK20: =AC20-AD20 -> 0 | AL20: =K20-V20 -> 3481.45 | AN20: kaike.costa@atlasinovacoes.com.br
B21: 45754 | C21: Sim | D21: Bangu Shopping | E21: Limpeza | F21: Verzani | G21: 65 | H21: 61 | I21: 0 | J21: 0 | K21: 298159.67 | L21: 0 | M21: 0 | N21: 0 | O21: 0 | P21: 0 | Q21: 0 | R21: 0 | S21: 0 | T21: 0 | V21: =IFERROR((K21+M21+R21+S21+T21+O21)+IF(U21="Sim",P21+Q21,0),(K21+R21+S21+T21)+IF(U21="Sim",P21+Q21,0)) -> 298159.67 | AA21: 45748 | AB21: {=IFERROR( IF( _xlfn.XLOOKUP( 1, ( ('Condições de Faturamento'!$C$2:$C$1000 = Tab_Faturamento_RJ[[#This Row],[Unidade]]) * ('Condições de Faturamento'!$D$2:$D$1000 = Tab_Faturamento_RJ[[#This Row],[Categoria]]) * ('Condições de Faturamento'!$E$2:$E$1000 = Tab_Faturamento_RJ[[#This Row],[Fornecedor]]) ), 'Condições de Faturamento'!$F$2:$F$1000 ) = "Emissão no mês da prestação do serviço", Tab_Faturamento_RJ[[#This Row],[Mês de referência para faturamento]], DATE( YEAR(Tab_Faturamento_RJ[[#This Row],[Mês de referência para faturamento]]), MONTH(Tab_Faturamento_RJ[[#This Row],[Mês de referência para faturamento]]) + 1, DAY(Tab_Faturamento_RJ[[#This Row],[Mês de referência para faturamento]]) ) ), DATE( YEAR(Tab_Faturamento_RJ[[#This Row],[Mês de referência para faturamento]]), MONTH(Tab_Faturamento_RJ[[#This Row],[Mês de referência para faturamento]]) + 1, DAY(Tab_Faturamento_RJ[[#This Row],[Mês de referência para faturamento]]) ) )} -> 45748 | AJ21: =IFERROR(L21-M21,0) -> 0 | AK21: =AC21-AD21 -> 0 | AL21: =K21-V21 -> 0 | AN21: kaike.costa@atlasinovacoes.com.br
B22: 45789 | C22: Sim | D22: Bangu Shopping | E22: Limpeza | F22: Verzani | G22: 65 | H22: 61 | I22: 0 | J22: 0 | K22: 298159.67 | L22: 0 | M22: 0 | N22: 0 | O22: 0 | P22: 0 | Q22: 0 | R22: 0 | S22: 0 | T22: 0 | U22: Sim | V22: =IFERROR((K22+M22+R22+S22+T22+O22)+IF(U22="Sim",P22+Q22,0),(K22+R22+S22+T22)+IF(U22="Sim",P22+Q22,0)) -> 298159.67 | Y22: =126534.36/4 -> 31633.59 | Z22: 1|4 | AA22: 45778 | AB22: {=IFERROR( IF( _xlfn.XLOOKUP( 1, ( ('Condições de Faturamento'!$C$2:$C$1000 = Tab_Faturamento_RJ[[#This Row],[Unidade]]) * ('Condições de Faturamento'!$D$2:$D$1000 = Tab_Faturamento_RJ[[#This Row],[Categoria]]) * ('Condições de Faturamento'!$E$2:$E$1000 = Tab_Faturamento_RJ[[#This Row],[Fornecedor]]) ), 'Condições de Faturamento'!$F$2:$F$1000 ) = "Emissão no mês da prestação do serviço", Tab_Faturamento_RJ[[#This Row],[Mês de referência para faturamento]], DATE( YEAR(Tab_Faturamento_RJ[[#This Row],[Mês de referência para faturamento]]), MONTH(Tab_Faturamento_RJ[[#This Row],[Mês de referência para faturamento]]) + 1, DAY(Tab_Faturamento_RJ[[#This Row],[Mês de referência para faturamento]]) ) ), DATE( YEAR(Tab_Faturamento_RJ[[#This Row],[Mês de referência para faturamento]]), MONTH(Tab_Faturamento_RJ[[#This Row],[Mês de referência para faturamento]]) + 1, DAY(Tab_Faturamento_RJ[[#This Row],[Mês de referência para faturamento]]) ) )} -> 45778 | AJ22: =IFERROR(L22-M22,0) -> 0 | AK22: =AC22-AD22 -> 0 | AL22: =K22-V22 -> 0 | AN22: kaike.costa@atlasinovacoes.com.br
B23: 45903 | C23: Sim | D23: Bangu Shopping | E23: Limpeza | F23: Verzani | G23: 65 | H23: 60 | I23: 23 | J23: 0 | K23: 335112.54 | L23: 0 | M23: -3167.48 | N23: 0 | O23: 0 | P23: -3351.13 | Q23: 0 | R23: 0 | S23: 0 | T23: 0 | U23: Sim | V23: =IFERROR((K23+M23+R23+S23+T23+O23)+IF(U23="Sim",P23+Q23,0),(K23+R23+S23+T23)+IF(U23="Sim",P23+Q23,0)) -> 328593.93 | AA23: 45901 | AB23: {=IFERROR( IF( _xlfn.XLOOKUP( 1, ( ('Condições de Faturamento'!$C$2:$C$1000 = Tab_Faturamento_RJ[[#This Row],[Unidade]]) * ('Condições de Faturamento'!$D$2:$D$1000 = Tab_Faturamento_RJ[[#This Row],[Categoria]]) * ('Condições de Faturamento'!$E$2:$E$1000 = Tab_Faturamento_RJ[[#This Row],[Fornecedor]]) ), 'Condições de Faturamento'!$F$2:$F$1000 ) = "Emissão no mês da prestação do serviço", Tab_Faturamento_RJ[[#This Row],[Mês de referência para faturamento]], DATE( YEAR(Tab_Faturamento_RJ[[#This Row],[Mês de referência para faturamento]]), MONTH(Tab_Faturamento_RJ[[#This Row],[Mês de referência para faturamento]]) + 1, DAY(Tab_Faturamento_RJ[[#This Row],[Mês de referência para faturamento]]) ) ), DATE( YEAR(Tab_Faturamento_RJ[[#This Row],[Mês de referência para faturamento]]), MONTH(Tab_Faturamento_RJ[[#This Row],[Mês de referência para faturamento]]) + 1, DAY(Tab_Faturamento_RJ[[#This Row],[Mês de referência para faturamento]]) ) )} -> 45901 | AJ23: =IFERROR(L23-M23,0) -> 3167.48 | AK23: =AC23-AD23 -> 0 | AL23: =K23-V23 -> 6518.61 | AN23: kaike.costa@atlasinovacoes.com.br
B24: 45818 | C24: Sim | D24: Bangu Shopping | E24: Limpeza | F24: Verzani | G24: 65 | H24: 61 | I24: 23 | J24: 0 | K24: 335112.54 | L24: 0 | M24: -3504.9 | N24: 0 | O24: 0 | P24: -2981.6 | Q24: 0 | R24: 0 | S24: 0 | T24: 0 | U24: Sim | V24: =IFERROR((K24+M24+R24+S24+T24+O24)+IF(U24="Sim",P24+Q24,0),(K24+R24+S24+T24)+IF(U24="Sim",P24+Q24,0)) -> 328626.04 | Y24: =126534.36/4 -> 31633.59 | Z24: 2|4 | AA24: 45809 | AB24: {=IFERROR( IF( _xlfn.XLOOKUP( 1, ( ('Condições de Faturamento'!$C$2:$C$1000 = Tab_Faturamento_RJ[[#This Row],[Unidade]]) * ('Condições de Faturamento'!$D$2:$D$1000 = Tab_Faturamento_RJ[[#This Row],[Categoria]]) * ('Condições de Faturamento'!$E$2:$E$1000 = Tab_Faturamento_RJ[[#This Row],[Fornecedor]]) ), 'Condições de Faturamento'!$F$2:$F$1000 ) = "Emissão no mês da prestação do serviço", Tab_Faturamento_RJ[[#This Row],[Mês de referência para faturamento]], DATE( YEAR(Tab_Faturamento_RJ[[#This Row],[Mês de referência para faturamento]]), MONTH(Tab_Faturamento_RJ[[#This Row],[Mês de referência para faturamento]]) + 1, DAY(Tab_Faturamento_RJ[[#This Row],[Mês de referência para faturamento]]) ) ), DATE( YEAR(Tab_Faturamento_RJ[[#This Row],[Mês de referência para faturamento]]), MONTH(Tab_Faturamento_RJ[[#This Row],[Mês de referência para faturamento]]) + 1, DAY(Tab_Faturamento_RJ[[#This Row],[Mês de referência para faturamento]]) ) )} -> 45809 | AJ24: =IFERROR(L24-M24,0) -> 3504.9 | AK24: =AC24-AD24 -> 0 | AL24: =K24-V24 -> 6486.5 | AN24: kaike.costa@atlasinovacoes.com.br
B25: 45887 | C25: Sim | D25: Bangu Shopping | E25: Manutenção | F25: GPS | G25: 29 | H25: 17 | I25: 0 | J25: 0 | K25: 137066.55 | L25: 0 | M25: 0 | N25: 0 | O25: 0 | P25: 0 | Q25: 0 | R25: 0 | S25: 0 | T25: 0 | U25: Sim | V25: =IFERROR((K25+M25+R25+S25+T25+O25)+IF(U25="Sim",P25+Q25,0),(K25+R25+S25+T25)+IF(U25="Sim",P25+Q25,0)) -> 137066.55 | AA25: 45839 | AB25: {=IFERROR( IF( _xlfn.XLOOKUP( 1, ( ('Condições de Faturamento'!$C$2:$C$1000 = Tab_Faturamento_RJ[[#This Row],[Unidade]]) * ('Condições de Faturamento'!$D$2:$D$1000 = Tab_Faturamento_RJ[[#This Row],[Categoria]]) * ('Condições de Faturamento'!$E$2:$E$1000 = Tab_Faturamento_RJ[[#This Row],[Fornecedor]]) ), 'Condições de Faturamento'!$F$2:$F$1000 ) = "Emissão no mês da prestação do serviço", Tab_Faturamento_RJ[[#This Row],[Mês de referência para faturamento]], DATE( YEAR(Tab_Faturamento_RJ[[#This Row],[Mês de referência para faturamento]]), MONTH(Tab_Faturamento_RJ[[#This Row],[Mês de referência para faturamento]]) + 1, DAY(Tab_Faturamento_RJ[[#This Row],[Mês de referência para faturamento]]) ) ), DATE( YEAR(Tab_Faturamento_RJ[[#This Row],[Mês de referência para faturamento]]), MONTH(Tab_Faturamento_RJ[[#This Row],[Mês de referência para faturamento]]) + 1, DAY(Tab_Faturamento_RJ[[#This Row],[Mês de referência para faturamento]]) ) )} -> 45839 | AJ25: =IFERROR(L25-M25,0) -> 0 | AK25: =AC25-AD25 -> 0 | AL25: =K25-V25 -> 0 | AN25: kaike.costa@atlasinovacoes.com.br
B26: 45877 | C26: Sim | D26: Bangu Shopping | E26: Limpeza | F26: Verzani | G26: 65 | H26: 60 | I26: 25 | J26: 0 | K26: 335112.54 | L26: 0 | M26: -3727.6 | N26: 0 | O26: 0 | P26: -3351.13 | Q26: 0 | R26: 0 | S26: 0 | T26: 0 | U26: Sim | V26: =IFERROR((K26+M26+R26+S26+T26+O26)+IF(U26="Sim",P26+Q26,0),(K26+R26+S26+T26)+IF(U26="Sim",P26+Q26,0)) -> 328033.81 | Y26: =126534.36/4 -> 31633.59 | Z26: 4|4 | AA26: 45870 | AB26: {=IFERROR( IF( _xlfn.XLOOKUP( 1, ( ('Condições de Faturamento'!$C$2:$C$1000 = Tab_Faturamento_RJ[[#This Row],[Unidade]]) * ('Condições de Faturamento'!$D$2:$D$1000 = Tab_Faturamento_RJ[[#This Row],[Categoria]]) * ('Condições de Faturamento'!$E$2:$E$1000 = Tab_Faturamento_RJ[[#This Row],[Fornecedor]]) ), 'Condições de Faturamento'!$F$2:$F$1000 ) = "Emissão no mês da prestação do serviço", Tab_Faturamento_RJ[[#This Row],[Mês de referência para faturamento]], DATE( YEAR(Tab_Faturamento_RJ[[#This Row],[Mês de referência para faturamento]]), MONTH(Tab_Faturamento_RJ[[#This Row],[Mês de referência para faturamento]]) + 1, DAY(Tab_Faturamento_RJ[[#This Row],[Mês de referência para faturamento]]) ) ), DATE( YEAR(Tab_Faturamento_RJ[[#This Row],[Mês de referência para faturamento]]), MONTH(Tab_Faturamento_RJ[[#This Row],[Mês de referência para faturamento]]) + 1, DAY(Tab_Faturamento_RJ[[#This Row],[Mês de referência para faturamento]]) ) )} -> 45870 | AD26: 4448.29 | AE26: 4448.29 | AJ26: =IFERROR(L26-M26,0) -> 3727.6 | AK26: =AC26-AD26 -> -4448.29 | AL26: =K26-V26 -> 7078.73 | AN26: kaike.costa@atlasinovacoes.com.br
B27: 45931 | C27: Sim | D27: Bangu Shopping | E27: Limpeza | F27: Verzani | G27: 65 | H27: 60 | I27: 21 | J27: 0 | K27: 335112.54 | M27: -2927.02 | O27: 0 | P27: -3351.13 | Q27: 0 | R27: 0 | S27: 0 | T27: 0 | U27: Sim | V27: =IFERROR((K27+M27+R27+S27+T27+O27)+IF(U27="Sim",P27+Q27,0),(K27+R27+S27+T27)+IF(U27="Sim",P27+Q27,0)) -> 328834.39 | AA27: 45931 | AB27: {=IFERROR( IF( _xlfn.XLOOKUP( 1, ( ('Condições de Faturamento'!$C$2:$C$1000 = Tab_Faturamento_RJ[[#This Row],[Unidade]]) * ('Condições de Faturamento'!$D$2:$D$1000 = Tab_Faturamento_RJ[[#This Row],[Categoria]]) * ('Condições de Faturamento'!$E$2:$E$1000 = Tab_Faturamento_RJ[[#This Row],[Fornecedor]]) ), 'Condições de Faturamento'!$F$2:$F$1000 ) = "Emissão no mês da prestação do serviço", Tab_Faturamento_RJ[[#This Row],[Mês de referência para faturamento]], DATE( YEAR(Tab_Faturamento_RJ[[#This Row],[Mês de referência para faturamento]]), MONTH(Tab_Faturamento_RJ[[#This Row],[Mês de referência para faturamento]]) + 1, DAY(Tab_Faturamento_RJ[[#This Row],[Mês de referência para faturamento]]) ) ), DATE( YEAR(Tab_Faturamento_RJ[[#This Row],[Mês de referência para faturamento]]), MONTH(Tab_Faturamento_RJ[[#This Row],[Mês de referência para faturamento]]) + 1, DAY(Tab_Faturamento_RJ[[#This Row],[Mês de referência para faturamento]]) ) )} -> 45931 | AJ27: =IFERROR(L27-M27,0) -> 2927.02 | AK27: =AC27-AD27 -> 0 | AL27: =K27-V27 -> 6278.15 | AN27: kaike.costa@atlasinovacoes.com.br
D28: Bangu Shopping | E28: Limpeza | F28: Verzani | G28: 65 | H28: 60 | V28: =IFERROR((K28+M28+R28+S28+T28+O28)+IF(U28="Sim",P28+Q28,0),(K28+R28+S28+T28)+IF(U28="Sim",P28+Q28,0)) -> 0 | AA28: 45962 | AB28: {=IFERROR( IF( _xlfn.XLOOKUP( 1, ( ('Condições de Faturamento'!$C$2:$C$1000 = Tab_Faturamento_RJ[[#This Row],[Unidade]]) * ('Condições de Faturamento'!$D$2:$D$1000 = Tab_Faturamento_RJ[[#This Row],[Categoria]]) * ('Condições de Faturamento'!$E$2:$E$1000 = Tab_Faturamento_RJ[[#This Row],[Fornecedor]]) ), 'Condições de Faturamento'!$F$2:$F$1000 ) = "Emissão no mês da prestação do serviço", Tab_Faturamento_RJ[[#This Row],[Mês de referência para faturamento]], DATE( YEAR(Tab_Faturamento_RJ[[#This Row],[Mês de referência para faturamento]]), MONTH(Tab_Faturamento_RJ[[#This Row],[Mês de referência para faturamento]]) + 1, DAY(Tab_Faturamento_RJ[[#This Row],[Mês de referência para faturamento]]) ) ), DATE( YEAR(Tab_Faturamento_RJ[[#This Row],[Mês de referência para faturamento]]), MONTH(Tab_Faturamento_RJ[[#This Row],[Mês de referência para faturamento]]) + 1, DAY(Tab_Faturamento_RJ[[#This Row],[Mês de referência para faturamento]]) ) )} -> 45962 | AJ28: =IFERROR(L28-M28,0) -> 0 | AK28: =AC28-AD28 -> 0 | AL28: =K28-V28 -> 0 | AN28: kaike.costa@atlasinovacoes.com.br
D29: Bangu Shopping | E29: Limpeza | F29: Verzani | G29: 65 | H29: 60 | V29: =IFERROR((K29+M29+R29+S29+T29+O29)+IF(U29="Sim",P29+Q29,0),(K29+R29+S29+T29)+IF(U29="Sim",P29+Q29,0)) -> 0 | AA29: 45992 | AB29: {=IFERROR( IF( _xlfn.XLOOKUP( 1, ( ('Condições de Faturamento'!$C$2:$C$1000 = Tab_Faturamento_RJ[[#This Row],[Unidade]]) * ('Condições de Faturamento'!$D$2:$D$1000 = Tab_Faturamento_RJ[[#This Row],[Categoria]]) * ('Condições de Faturamento'!$E$2:$E$1000 = Tab_Faturamento_RJ[[#This Row],[Fornecedor]]) ), 'Condições de Faturamento'!$F$2:$F$1000 ) = "Emissão no mês da prestação do serviço", Tab_Faturamento_RJ[[#This Row],[Mês de referência para faturamento]], DATE( YEAR(Tab_Faturamento_RJ[[#This Row],[Mês de referência para faturamento]]), MONTH(Tab_Faturamento_RJ[[#This Row],[Mês de referência para faturamento]]) + 1, DAY(Tab_Faturamento_RJ[[#This Row],[Mês de referência para faturamento]]) ) ), DATE( YEAR(Tab_Faturamento_RJ[[#This Row],[Mês de referência para faturamento]]), MONTH(Tab_Faturamento_RJ[[#This Row],[Mês de referência para faturamento]]) + 1, DAY(Tab_Faturamento_RJ[[#This Row],[Mês de referência para faturamento]]) ) )} -> 45992 | AJ29: =IFERROR(L29-M29,0) -> 0 | AK29: =AC29-AD29 -> 0 | AL29: =K29-V29 -> 0 | AN29: kaike.costa@atlasinovacoes.com.br
C30: Não | D30: Bangu Shopping | E30: Manutenção | F30: GPS | G30: 29 | H30: 17 | I30: Informação pendente | J30: Informação pendente | K30: 130282.08 | L30: 0 | M30: Informação pendente | N30: 0 | O30: Informação pendente | P30: 0 | Q30: 0 | R30: 0 | S30: 0 | T30: 0 | V30: =IFERROR((K30+M30+R30+S30+T30+O30)+IF(U30="Sim",P30+Q30,0),(K30+R30+S30+T30)+IF(U30="Sim",P30+Q30,0)) -> 130282.08 | AA30: 45658 | AB30: {=IFERROR( IF( _xlfn.XLOOKUP( 1, ( ('Condições de Faturamento'!$C$2:$C$1000 = Tab_Faturamento_RJ[[#This Row],[Unidade]]) * ('Condições de Faturamento'!$D$2:$D$1000 = Tab_Faturamento_RJ[[#This Row],[Categoria]]) * ('Condições de Faturamento'!$E$2:$E$1000 = Tab_Faturamento_RJ[[#This Row],[Fornecedor]]) ), 'Condições de Faturamento'!$F$2:$F$1000 ) = "Emissão no mês da prestação do serviço", Tab_Faturamento_RJ[[#This Row],[Mês de referência para faturamento]], DATE( YEAR(Tab_Faturamento_RJ[[#This Row],[Mês de referência para faturamento]]), MONTH(Tab_Faturamento_RJ[[#This Row],[Mês de referência para faturamento]]) + 1, DAY(Tab_Faturamento_RJ[[#This Row],[Mês de referência para faturamento]]) ) ), DATE( YEAR(Tab_Faturamento_RJ[[#This Row],[Mês de referência para faturamento]]), MONTH(Tab_Faturamento_RJ[[#This Row],[Mês de referência para faturamento]]) + 1, DAY(Tab_Faturamento_RJ[[#This Row],[Mês de referência para faturamento]]) ) )} -> 45658 | AC30: 242.57 | AD30: 242.57 | AJ30: =IFERROR(L30-M30,0) -> 0 | AK30: =AC30-AD30 -> 0 | AL30: =K30-V30 -> 0 | AN30: kaike.costa@atlasinovacoes.com.br
C31: Não | D31: Bangu Shopping | E31: Manutenção | F31: GPS | G31: 29 | H31: 17 | I31: Informação pendente | J31: Informação pendente | K31: 130282.08 | L31: 0 | M31: Informação pendente | N31: 0 | O31: Informação pendente | P31: 0 | Q31: 0 | R31: 0 | S31: 0 | T31: 0 | V31: =IFERROR((K31+M31+R31+S31+T31+O31)+IF(U31="Sim",P31+Q31,0),(K31+R31+S31+T31)+IF(U31="Sim",P31+Q31,0)) -> 130282.08 | AA31: 45689 | AB31: {=IFERROR( IF( _xlfn.XLOOKUP( 1, ( ('Condições de Faturamento'!$C$2:$C$1000 = Tab_Faturamento_RJ[[#This Row],[Unidade]]) * ('Condições de Faturamento'!$D$2:$D$1000 = Tab_Faturamento_RJ[[#This Row],[Categoria]]) * ('Condições de Faturamento'!$E$2:$E$1000 = Tab_Faturamento_RJ[[#This Row],[Fornecedor]]) ), 'Condições de Faturamento'!$F$2:$F$1000 ) = "Emissão no mês da prestação do serviço", Tab_Faturamento_RJ[[#This Row],[Mês de referência para faturamento]], DATE( YEAR(Tab_Faturamento_RJ[[#This Row],[Mês de referência para faturamento]]), MONTH(Tab_Faturamento_RJ[[#This Row],[Mês de referência para faturamento]]) + 1, DAY(Tab_Faturamento_RJ[[#This Row],[Mês de referência para faturamento]]) ) ), DATE( YEAR(Tab_Faturamento_RJ[[#This Row],[Mês de referência para faturamento]]), MONTH(Tab_Faturamento_RJ[[#This Row],[Mês de referência para faturamento]]) + 1, DAY(Tab_Faturamento_RJ[[#This Row],[Mês de referência para faturamento]]) ) )} -> 45689 | AJ31: =IFERROR(L31-M31,0) -> 0 | AK31: =AC31-AD31 -> 0 | AL31: =K31-V31 -> 0 | AN31: kaike.costa@atlasinovacoes.com.br
C32: Não | D32: Bangu Shopping | E32: Manutenção | F32: GPS | G32: 29 | H32: 17 | I32: 0 | J32: 0 | K32: 130282.08 | L32: 0 | M32: 0 | N32: 0 | O32: 0 | P32: 0 | Q32: 0 | R32: 0 | S32: 0 | T32: 0 | U32: Sim | V32: =IFERROR((K32+M32+R32+S32+T32+O32)+IF(U32="Sim",P32+Q32,0),(K32+R32+S32+T32)+IF(U32="Sim",P32+Q32,0)) -> 130282.08 | AA32: 45717 | AB32: {=IFERROR( IF( _xlfn.XLOOKUP( 1, ( ('Condições de Faturamento'!$C$2:$C$1000 = Tab_Faturamento_RJ[[#This Row],[Unidade]]) * ('Condições de Faturamento'!$D$2:$D$1000 = Tab_Faturamento_RJ[[#This Row],[Categoria]]) * ('Condições de Faturamento'!$E$2:$E$1000 = Tab_Faturamento_RJ[[#This Row],[Fornecedor]]) ), 'Condições de Faturamento'!$F$2:$F$1000 ) = "Emissão no mês da prestação do serviço", Tab_Faturamento_RJ[[#This Row],[Mês de referência para faturamento]], DATE( YEAR(Tab_Faturamento_RJ[[#This Row],[Mês de referência para faturamento]]), MONTH(Tab_Faturamento_RJ[[#This Row],[Mês de referência para faturamento]]) + 1, DAY(Tab_Faturamento_RJ[[#This Row],[Mês de referência para faturamento]]) ) ), DATE( YEAR(Tab_Faturamento_RJ[[#This Row],[Mês de referência para faturamento]]), MONTH(Tab_Faturamento_RJ[[#This Row],[Mês de referência para faturamento]]) + 1, DAY(Tab_Faturamento_RJ[[#This Row],[Mês de referência para faturamento]]) ) )} -> 45717 | AC32: 1548.2 | AD32: 1548.2 | AJ32: =IFERROR(L32-M32,0) -> 0 | AK32: =AC32-AD32 -> 0 | AL32: =K32-V32 -> 0 | AN32: kaike.costa@atlasinovacoes.com.br
C33: Não | D33: Bangu Shopping | E33: Manutenção | F33: GPS | G33: 29 | H33: 17 | I33: Informação pendente | J33: Informação pendente | K33: 130282.08 | L33: 0 | M33: Informação pendente | N33: 0 | O33: Informação pendente | P33: Preenchimento pendente | Q33: 0 | R33: 0 | S33: 0 | T33: 0 | V33: =IFERROR((K33+M33+R33+S33+T33+O33)+IF(U33="Sim",P33+Q33,0),(K33+R33+S33+T33)+IF(U33="Sim",P33+Q33,0)) -> 130282.08 | AA33: 45748 | AB33: {=IFERROR( IF( _xlfn.XLOOKUP( 1, ( ('Condições de Faturamento'!$C$2:$C$1000 = Tab_Faturamento_RJ[[#This Row],[Unidade]]) * ('Condições de Faturamento'!$D$2:$D$1000 = Tab_Faturamento_RJ[[#This Row],[Categoria]]) * ('Condições de Faturamento'!$E$2:$E$1000 = Tab_Faturamento_RJ[[#This Row],[Fornecedor]]) ), 'Condições de Faturamento'!$F$2:$F$1000 ) = "Emissão no mês da prestação do serviço", Tab_Faturamento_RJ[[#This Row],[Mês de referência para faturamento]], DATE( YEAR(Tab_Faturamento_RJ[[#This Row],[Mês de referência para faturamento]]), MONTH(Tab_Faturamento_RJ[[#This Row],[Mês de referência para faturamento]]) + 1, DAY(Tab_Faturamento_RJ[[#This Row],[Mês de referência para faturamento]]) ) ), DATE( YEAR(Tab_Faturamento_RJ[[#This Row],[Mês de referência para faturamento]]), MONTH(Tab_Faturamento_RJ[[#This Row],[Mês de referência para faturamento]]) + 1, DAY(Tab_Faturamento_RJ[[#This Row],[Mês de referência para faturamento]]) ) )} -> 45748 | AC33: 4724.23 | AD33: 4724.23 | AE33: 4505.88 | AJ33: =IFERROR(L33-M33,0) -> 0 | AK33: =AC33-AD33 -> 0 | AL33: =K33-V33 -> 0 | AN33: kaike.costa@atlasinovacoes.com.br
C34: Não | D34: Bangu Shopping | E34: Manutenção | F34: GPS | G34: 29 | H34: 17 | I34: 0 | J34: 0 | K34: 130282.08 | L34: 0 | M34: 0 | N34: 0 | O34: 0 | P34: 0 | Q34: 0 | R34: 0 | S34: 0 | T34: 0 | U34: Não | V34: =IFERROR((K34+M34+R34+S34+T34+O34)+IF(U34="Sim",P34+Q34,0),(K34+R34+S34+T34)+IF(U34="Sim",P34+Q34,0)) -> 130282.08 | AA34: 45778 | AB34: {=IFERROR( IF( _xlfn.XLOOKUP( 1, ( ('Condições de Faturamento'!$C$2:$C$1000 = Tab_Faturamento_RJ[[#This Row],[Unidade]]) * ('Condições de Faturamento'!$D$2:$D$1000 = Tab_Faturamento_RJ[[#This Row],[Categoria]]) * ('Condições de Faturamento'!$E$2:$E$1000 = Tab_Faturamento_RJ[[#This Row],[Fornecedor]]) ), 'Condições de Faturamento'!$F$2:$F$1000 ) = "Emissão no mês da prestação do serviço", Tab_Faturamento_RJ[[#This Row],[Mês de referência para faturamento]], DATE( YEAR(Tab_Faturamento_RJ[[#This Row],[Mês de referência para faturamento]]), MONTH(Tab_Faturamento_RJ[[#This Row],[Mês de referência para faturamento]]) + 1, DAY(Tab_Faturamento_RJ[[#This Row],[Mês de referência para faturamento]]) ) ), DATE( YEAR(Tab_Faturamento_RJ[[#This Row],[Mês de referência para faturamento]]), MONTH(Tab_Faturamento_RJ[[#This Row],[Mês de referência para faturamento]]) + 1, DAY(Tab_Faturamento_RJ[[#This Row],[Mês de referência para faturamento]]) ) )} -> 45778 | AJ34: =IFERROR(L34-M34,0) -> 0 | AK34: =AC34-AD34 -> 0 | AL34: =K34-V34 -> 0 | AN34: kaike.costa@atlasinovacoes.com.br
C35: Não | D35: Bangu Shopping | E35: Manutenção | F35: GPS | G35: 29 | H35: 17 | I35: Informação pendente | J35: Informação pendente | K35: 130282.08 | L35: 0 | M35: Informação pendente | N35: 0 | O35: Informação pendente | P35: Preenchimento pendente | Q35: 0 | R35: 0 | S35: 0 | T35: 0 | U35: Não | V35: =IFERROR((K35+M35+R35+S35+T35+O35)+IF(U35="Sim",P35+Q35,0),(K35+R35+S35+T35)+IF(U35="Sim",P35+Q35,0)) -> 130282.08 | AA35: 45809 | AB35: {=IFERROR( IF( _xlfn.XLOOKUP( 1, ( ('Condições de Faturamento'!$C$2:$C$1000 = Tab_Faturamento_RJ[[#This Row],[Unidade]]) * ('Condições de Faturamento'!$D$2:$D$1000 = Tab_Faturamento_RJ[[#This Row],[Categoria]]) * ('Condições de Faturamento'!$E$2:$E$1000 = Tab_Faturamento_RJ[[#This Row],[Fornecedor]]) ), 'Condições de Faturamento'!$F$2:$F$1000 ) = "Emissão no mês da prestação do serviço", Tab_Faturamento_RJ[[#This Row],[Mês de referência para faturamento]], DATE( YEAR(Tab_Faturamento_RJ[[#This Row],[Mês de referência para faturamento]]), MONTH(Tab_Faturamento_RJ[[#This Row],[Mês de referência para faturamento]]) + 1, DAY(Tab_Faturamento_RJ[[#This Row],[Mês de referência para faturamento]]) ) ), DATE( YEAR(Tab_Faturamento_RJ[[#This Row],[Mês de referência para faturamento]]), MONTH(Tab_Faturamento_RJ[[#This Row],[Mês de referência para faturamento]]) + 1, DAY(Tab_Faturamento_RJ[[#This Row],[Mês de referência para faturamento]]) ) )} -> 45809 | AJ35: =IFERROR(L35-M35,0) -> 0 | AK35: =AC35-AD35 -> 0 | AL35: =K35-V35 -> 0 | AN35: kaike.costa@atlasinovacoes.com.br
C36: Não | D36: Bangu Shopping | E36: Manutenção | F36: GPS | G36: 29 | H36: 17 | I36: Informação pendente | J36: Informação pendente | K36: 137066.55 | L36: 0 | M36: Informação pendente | N36: 0 | O36: Informação pendente | P36: Preenchimento pendente | Q36: 0 | R36: 0 | S36: 0 | T36: 0 | V36: =IFERROR((K36+M36+R36+S36+T36+O36)+IF(U36="Sim",P36+Q36,0),(K36+R36+S36+T36)+IF(U36="Sim",P36+Q36,0)) -> 137066.55 | AA36: 45870 | AB36: {=IFERROR( IF( _xlfn.XLOOKUP( 1, ( ('Condições de Faturamento'!$C$2:$C$1000 = Tab_Faturamento_RJ[[#This Row],[Unidade]]) * ('Condições de Faturamento'!$D$2:$D$1000 = Tab_Faturamento_RJ[[#This Row],[Categoria]]) * ('Condições de Faturamento'!$E$2:$E$1000 = Tab_Faturamento_RJ[[#This Row],[Fornecedor]]) ), 'Condições de Faturamento'!$F$2:$F$1000 ) = "Emissão no mês da prestação do serviço", Tab_Faturamento_RJ[[#This Row],[Mês de referência para faturamento]], DATE( YEAR(Tab_Faturamento_RJ[[#This Row],[Mês de referência para faturamento]]), MONTH(Tab_Faturamento_RJ[[#This Row],[Mês de referência para faturamento]]) + 1, DAY(Tab_Faturamento_RJ[[#This Row],[Mês de referência para faturamento]]) ) ), DATE( YEAR(Tab_Faturamento_RJ[[#This Row],[Mês de referência para faturamento]]), MONTH(Tab_Faturamento_RJ[[#This Row],[Mês de referência para faturamento]]) + 1, DAY(Tab_Faturamento_RJ[[#This Row],[Mês de referência para faturamento]]) ) )} -> 45870 | AC36: 5356.83 | AD36: 5282.1994 | AJ36: =IFERROR(L36-M36,0) -> 0 | AK36: =AC36-AD36 -> 74.630576 | AL36: =K36-V36 -> 0 | AN36: kaike.costa@atlasinovacoes.com.br
C37: Não | D37: Bangu Shopping | E37: PMOC | F37: GPS | G37: 4 | H37: 3 | I37: Informação pendente | J37: Informação pendente | K37: 27438.272 | L37: 0 | M37: Informação pendente | N37: 0 | O37: Informação pendente | P37: preenchimento pendente | Q37: 0 | R37: 0 | S37: 0 | T37: 0 | V37: =IFERROR((K37+M37+R37+S37+T37+O37)+IF(U37="Sim",P37+Q37,0),(K37+R37+S37+T37)+IF(U37="Sim",P37+Q37,0)) -> 27438.272 | AA37: 45839 | AB37: {=IFERROR( IF( _xlfn.XLOOKUP( 1, ( ('Condições de Faturamento'!$C$2:$C$1000 = Tab_Faturamento_RJ[[#This Row],[Unidade]]) * ('Condições de Faturamento'!$D$2:$D$1000 = Tab_Faturamento_RJ[[#This Row],[Categoria]]) * ('Condições de Faturamento'!$E$2:$E$1000 = Tab_Faturamento_RJ[[#This Row],[Fornecedor]]) ), 'Condições de Faturamento'!$F$2:$F$1000 ) = "Emissão no mês da prestação do serviço", Tab_Faturamento_RJ[[#This Row],[Mês de referência para faturamento]], DATE( YEAR(Tab_Faturamento_RJ[[#This Row],[Mês de referência para faturamento]]), MONTH(Tab_Faturamento_RJ[[#This Row],[Mês de referência para faturamento]]) + 1, DAY(Tab_Faturamento_RJ[[#This Row],[Mês de referência para faturamento]]) ) ), DATE( YEAR(Tab_Faturamento_RJ[[#This Row],[Mês de referência para faturamento]]), MONTH(Tab_Faturamento_RJ[[#This Row],[Mês de referência para faturamento]]) + 1, DAY(Tab_Faturamento_RJ[[#This Row],[Mês de referência para faturamento]]) ) )} -> 45839 | AJ37: =IFERROR(L37-M37,0) -> 0 | AK37: =AC37-AD37 -> 0 | AL37: =K37-V37 -> 0 | AN37: kaike.costa@atlasinovacoes.com.br
C38: Não | D38: Bangu Shopping | E38: Manutenção | F38: GPS | G38: 29 | H38: 20 | I38: Informação pendente | J38: Informação pendente | K38: 155292.79 | L38: 0 | M38: Informação pendente | N38: 0 | O38: Informação pendente | P38: Preenchimento pendente | Q38: 0 | R38: 0 | S38: 0 | T38: 0 | V38: =IFERROR((K38+M38+R38+S38+T38+O38)+IF(U38="Sim",P38+Q38,0),(K38+R38+S38+T38)+IF(U38="Sim",P38+Q38,0)) -> 155292.79 | AA38: 45901 | AB38: {=IFERROR( IF( _xlfn.XLOOKUP( 1, ( ('Condições de Faturamento'!$C$2:$C$1000 = Tab_Faturamento_RJ[[#This Row],[Unidade]]) * ('Condições de Faturamento'!$D$2:$D$1000 = Tab_Faturamento_RJ[[#This Row],[Categoria]]) * ('Condições de Faturamento'!$E$2:$E$1000 = Tab_Faturamento_RJ[[#This Row],[Fornecedor]]) ), 'Condições de Faturamento'!$F$2:$F$1000 ) = "Emissão no mês da prestação do serviço", Tab_Faturamento_RJ[[#This Row],[Mês de referência para faturamento]], DATE( YEAR(Tab_Faturamento_RJ[[#This Row],[Mês de referência para faturamento]]), MONTH(Tab_Faturamento_RJ[[#This Row],[Mês de referência para faturamento]]) + 1, DAY(Tab_Faturamento_RJ[[#This Row],[Mês de referência para faturamento]]) ) ), DATE( YEAR(Tab_Faturamento_RJ[[#This Row],[Mês de referência para faturamento]]), MONTH(Tab_Faturamento_RJ[[#This Row],[Mês de referência para faturamento]]) + 1, DAY(Tab_Faturamento_RJ[[#This Row],[Mês de referência para faturamento]]) ) )} -> 45901 | AC38: 7501.85 | AD38: 7351.9726 | AJ38: =IFERROR(L38-M38,0) -> 0 | AK38: =AC38-AD38 -> 149.87743 | AL38: =K38-V38 -> 0 | AN38: kaike.costa@atlasinovacoes.com.br
C39: Não | D39: Bangu Shopping | E39: Manutenção | F39: GPS | G39: 29 | H39: 20 | I39: Informação pendente | J39: Informação pendente | K39: 155292.79 | M39: Informação pendente | O39: Informação pendente | P39: Preenchimento pendente | Q39: Informação pendente | V39: =IFERROR((K39+M39+R39+S39+T39+O39)+IF(U39="Sim",P39+Q39,0),(K39+R39+S39+T39)+IF(U39="Sim",P39+Q39,0)) -> 155292.79 | AA39: 45931 | AB39: {=IFERROR( IF( _xlfn.XLOOKUP( 1, ( ('Condições de Faturamento'!$C$2:$C$1000 = Tab_Faturamento_RJ[[#This Row],[Unidade]]) * ('Condições de Faturamento'!$D$2:$D$1000 = Tab_Faturamento_RJ[[#This Row],[Categoria]]) * ('Condições de Faturamento'!$E$2:$E$1000 = Tab_Faturamento_RJ[[#This Row],[Fornecedor]]) ), 'Condições de Faturamento'!$F$2:$F$1000 ) = "Emissão no mês da prestação do serviço", Tab_Faturamento_RJ[[#This Row],[Mês de referência para faturamento]], DATE( YEAR(Tab_Faturamento_RJ[[#This Row],[Mês de referência para faturamento]]), MONTH(Tab_Faturamento_RJ[[#This Row],[Mês de referência para faturamento]]) + 1, DAY(Tab_Faturamento_RJ[[#This Row],[Mês de referência para faturamento]]) ) ), DATE( YEAR(Tab_Faturamento_RJ[[#This Row],[Mês de referência para faturamento]]), MONTH(Tab_Faturamento_RJ[[#This Row],[Mês de referência para faturamento]]) + 1, DAY(Tab_Faturamento_RJ[[#This Row],[Mês de referência para faturamento]]) ) )} -> 45931 | AJ39: =IFERROR(L39-M39,0) -> 0 | AK39: =AC39-AD39 -> 0 | AL39: =K39-V39 -> 0 | AN39: kaike.costa@atlasinovacoes.com.br
D40: Bangu Shopping | E40: Manutenção | F40: GPS | G40: 29 | V40: =IFERROR((K40+M40+R40+S40+T40+O40)+IF(U40="Sim",P40+Q40,0),(K40+R40+S40+T40)+IF(U40="Sim",P40+Q40,0)) -> 0 | AA40: 45962 | AB40: {=IFERROR( IF( _xlfn.XLOOKUP( 1, ( ('Condições de Faturamento'!$C$2:$C$1000 = Tab_Faturamento_RJ[[#This Row],[Unidade]]) * ('Condições de Faturamento'!$D$2:$D$1000 = Tab_Faturamento_RJ[[#This Row],[Categoria]]) * ('Condições de Faturamento'!$E$2:$E$1000 = Tab_Faturamento_RJ[[#This Row],[Fornecedor]]) ), 'Condições de Faturamento'!$F$2:$F$1000 ) = "Emissão no mês da prestação do serviço", Tab_Faturamento_RJ[[#This Row],[Mês de referência para faturamento]], DATE( YEAR(Tab_Faturamento_RJ[[#This Row],[Mês de referência para faturamento]]), MONTH(Tab_Faturamento_RJ[[#This Row],[Mês de referência para faturamento]]) + 1, DAY(Tab_Faturamento_RJ[[#This Row],[Mês de referência para faturamento]]) ) ), DATE( YEAR(Tab_Faturamento_RJ[[#This Row],[Mês de referência para faturamento]]), MONTH(Tab_Faturamento_RJ[[#This Row],[Mês de referência para faturamento]]) + 1, DAY(Tab_Faturamento_RJ[[#This Row],[Mês de referência para faturamento]]) ) )} -> 45962 | AJ40: =IFERROR(L40-M40,0) -> 0 | AK40: =AC40-AD40 -> 0 | AL40: =K40-V40 -> 0 | AN40: kaike.costa@atlasinovacoes.com.br
D41: Bangu Shopping | E41: Manutenção | F41: GPS | G41: 29 | V41: =IFERROR((K41+M41+R41+S41+T41+O41)+IF(U41="Sim",P41+Q41,0),(K41+R41+S41+T41)+IF(U41="Sim",P41+Q41,0)) -> 0 | AA41: 45992 | AB41: {=IFERROR( IF( _xlfn.XLOOKUP( 1, ( ('Condições de Faturamento'!$C$2:$C$1000 = Tab_Faturamento_RJ[[#This Row],[Unidade]]) * ('Condições de Faturamento'!$D$2:$D$1000 = Tab_Faturamento_RJ[[#This Row],[Categoria]]) * ('Condições de Faturamento'!$E$2:$E$1000 = Tab_Faturamento_RJ[[#This Row],[Fornecedor]]) ), 'Condições de Faturamento'!$F$2:$F$1000 ) = "Emissão no mês da prestação do serviço", Tab_Faturamento_RJ[[#This Row],[Mês de referência para faturamento]], DATE( YEAR(Tab_Faturamento_RJ[[#This Row],[Mês de referência para faturamento]]), MONTH(Tab_Faturamento_RJ[[#This Row],[Mês de referência para faturamento]]) + 1, DAY(Tab_Faturamento_RJ[[#This Row],[Mês de referência para faturamento]]) ) ), DATE( YEAR(Tab_Faturamento_RJ[[#This Row],[Mês de referência para faturamento]]), MONTH(Tab_Faturamento_RJ[[#This Row],[Mês de referência para faturamento]]) + 1, DAY(Tab_Faturamento_RJ[[#This Row],[Mês de referência para faturamento]]) ) )} -> 45992 | AJ41: =IFERROR(L41-M41,0) -> 0 | AK41: =AC41-AD41 -> 0 | AL41: =K41-V41 -> 0 | AN41: kaike.costa@atlasinovacoes.com.br
C42: Não | D42: Bangu Shopping | E42: PMOC | F42: GPS | G42: 4 | H42: 3 | I42: Informação pendente | J42: Informação pendente | K42: 26027.65 | L42: 0 | M42: Informação pendente | N42: 0 | O42: Informação pendente | P42: 0 | Q42: 0 | R42: 0 | S42: 0 | T42: 0 | V42: =IFERROR((K42+M42+R42+S42+T42+O42)+IF(U42="Sim",P42+Q42,0),(K42+R42+S42+T42)+IF(U42="Sim",P42+Q42,0)) -> 26027.65 | AA42: 45658 | AB42: {=IFERROR( IF( _xlfn.XLOOKUP( 1, ( ('Condições de Faturamento'!$C$2:$C$1000 = Tab_Faturamento_RJ[[#This Row],[Unidade]]) * ('Condições de Faturamento'!$D$2:$D$1000 = Tab_Faturamento_RJ[[#This Row],[Categoria]]) * ('Condições de Faturamento'!$E$2:$E$1000 = Tab_Faturamento_RJ[[#This Row],[Fornecedor]]) ), 'Condições de Faturamento'!$F$2:$F$1000 ) = "Emissão no mês da prestação do serviço", Tab_Faturamento_RJ[[#This Row],[Mês de referência para faturamento]], DATE( YEAR(Tab_Faturamento_RJ[[#This Row],[Mês de referência para faturamento]]), MONTH(Tab_Faturamento_RJ[[#This Row],[Mês de referência para faturamento]]) + 1, DAY(Tab_Faturamento_RJ[[#This Row],[Mês de referência para faturamento]]) ) ), DATE( YEAR(Tab_Faturamento_RJ[[#This Row],[Mês de referência para faturamento]]), MONTH(Tab_Faturamento_RJ[[#This Row],[Mês de referência para faturamento]]) + 1, DAY(Tab_Faturamento_RJ[[#This Row],[Mês de referência para faturamento]]) ) )} -> 45658 | AJ42: =IFERROR(L42-M42,0) -> 0 | AK42: =AC42-AD42 -> 0 | AL42: =K42-V42 -> 0 | AN42: kaike.costa@atlasinovacoes.com.br
C43: Não | D43: Bangu Shopping | E43: PMOC | F43: GPS | G43: 4 | H43: 3 | I43: Informação pendente | J43: Informação pendente | K43: 26027.65 | L43: 0 | M43: Informação pendente | N43: 0 | O43: Informação pendente | P43: 0 | Q43: 0 | R43: 0 | S43: 0 | T43: 0 | V43: =IFERROR((K43+M43+R43+S43+T43+O43)+IF(U43="Sim",P43+Q43,0),(K43+R43+S43+T43)+IF(U43="Sim",P43+Q43,0)) -> 26027.65 | AA43: 45689 | AB43: {=IFERROR( IF( _xlfn.XLOOKUP( 1, ( ('Condições de Faturamento'!$C$2:$C$1000 = Tab_Faturamento_RJ[[#This Row],[Unidade]]) * ('Condições de Faturamento'!$D$2:$D$1000 = Tab_Faturamento_RJ[[#This Row],[Categoria]]) * ('Condições de Faturamento'!$E$2:$E$1000 = Tab_Faturamento_RJ[[#This Row],[Fornecedor]]) ), 'Condições de Faturamento'!$F$2:$F$1000 ) = "Emissão no mês da prestação do serviço", Tab_Faturamento_RJ[[#This Row],[Mês de referência para faturamento]], DATE( YEAR(Tab_Faturamento_RJ[[#This Row],[Mês de referência para faturamento]]), MONTH(Tab_Faturamento_RJ[[#This Row],[Mês de referência para faturamento]]) + 1, DAY(Tab_Faturamento_RJ[[#This Row],[Mês de referência para faturamento]]) ) ), DATE( YEAR(Tab_Faturamento_RJ[[#This Row],[Mês de referência para faturamento]]), MONTH(Tab_Faturamento_RJ[[#This Row],[Mês de referência para faturamento]]) + 1, DAY(Tab_Faturamento_RJ[[#This Row],[Mês de referência para faturamento]]) ) )} -> 45689 | AJ43: =IFERROR(L43-M43,0) -> 0 | AK43: =AC43-AD43 -> 0 | AL43: =K43-V43 -> 0 | AN43: kaike.costa@atlasinovacoes.com.br
C44: Não | D44: Bangu Shopping | E44: PMOC | F44: GPS | G44: 4 | H44: 3 | I44: 0 | J44: 0 | K44: 26027.65 | L44: 0 | M44: 0 | N44: 0 | O44: 0 | P44: 0 | Q44: 0 | R44: 0 | S44: 0 | T44: 0 | U44: Sim | V44: =IFERROR((K44+M44+R44+S44+T44+O44)+IF(U44="Sim",P44+Q44,0),(K44+R44+S44+T44)+IF(U44="Sim",P44+Q44,0)) -> 26027.65 | AA44: 45717 | AB44: {=IFERROR( IF( _xlfn.XLOOKUP( 1, ( ('Condições de Faturamento'!$C$2:$C$1000 = Tab_Faturamento_RJ[[#This Row],[Unidade]]) * ('Condições de Faturamento'!$D$2:$D$1000 = Tab_Faturamento_RJ[[#This Row],[Categoria]]) * ('Condições de Faturamento'!$E$2:$E$1000 = Tab_Faturamento_RJ[[#This Row],[Fornecedor]]) ), 'Condições de Faturamento'!$F$2:$F$1000 ) = "Emissão no mês da prestação do serviço", Tab_Faturamento_RJ[[#This Row],[Mês de referência para faturamento]], DATE( YEAR(Tab_Faturamento_RJ[[#This Row],[Mês de referência para faturamento]]), MONTH(Tab_Faturamento_RJ[[#This Row],[Mês de referência para faturamento]]) + 1, DAY(Tab_Faturamento_RJ[[#This Row],[Mês de referência para faturamento]]) ) ), DATE( YEAR(Tab_Faturamento_RJ[[#This Row],[Mês de referência para faturamento]]), MONTH(Tab_Faturamento_RJ[[#This Row],[Mês de referência para faturamento]]) + 1, DAY(Tab_Faturamento_RJ[[#This Row],[Mês de referência para faturamento]]) ) )} -> 45717 | AJ44: =IFERROR(L44-M44,0) -> 0 | AK44: =AC44-AD44 -> 0 | AL44: =K44-V44 -> 0 | AN44: kaike.costa@atlasinovacoes.com.br
C45: Não | D45: Bangu Shopping | E45: PMOC | F45: GPS | G45: 4 | H45: 3 | I45: Informação pendente | J45: Informação pendente | K45: 26027.65 | L45: 0 | M45: Informação pendente | N45: 0 | O45: Informação pendente | P45: 0 | Q45: 0 | R45: 0 | S45: 0 | T45: 0 | V45: =IFERROR((K45+M45+R45+S45+T45+O45)+IF(U45="Sim",P45+Q45,0),(K45+R45+S45+T45)+IF(U45="Sim",P45+Q45,0)) -> 26027.65 | AA45: 45748 | AB45: {=IFERROR( IF( _xlfn.XLOOKUP( 1, ( ('Condições de Faturamento'!$C$2:$C$1000 = Tab_Faturamento_RJ[[#This Row],[Unidade]]) * ('Condições de Faturamento'!$D$2:$D$1000 = Tab_Faturamento_RJ[[#This Row],[Categoria]]) * ('Condições de Faturamento'!$E$2:$E$1000 = Tab_Faturamento_RJ[[#This Row],[Fornecedor]]) ), 'Condições de Faturamento'!$F$2:$F$1000 ) = "Emissão no mês da prestação do serviço", Tab_Faturamento_RJ[[#This Row],[Mês de referência para faturamento]], DATE( YEAR(Tab_Faturamento_RJ[[#This Row],[Mês de referência para faturamento]]), MONTH(Tab_Faturamento_RJ[[#This Row],[Mês de referência para faturamento]]) + 1, DAY(Tab_Faturamento_RJ[[#This Row],[Mês de referência para faturamento]]) ) ), DATE( YEAR(Tab_Faturamento_RJ[[#This Row],[Mês de referência para faturamento]]), MONTH(Tab_Faturamento_RJ[[#This Row],[Mês de referência para faturamento]]) + 1, DAY(Tab_Faturamento_RJ[[#This Row],[Mês de referência para faturamento]]) ) )} -> 45748 | AJ45: =IFERROR(L45-M45,0) -> 0 | AK45: =AC45-AD45 -> 0 | AL45: =K45-V45 -> 0 | AN45: kaike.costa@atlasinovacoes.com.br
C46: Não | D46: Bangu Shopping | E46: PMOC | F46: GPS | G46: 4 | H46: 3 | I46: 0 | J46: 0 | K46: 26027.65 | L46: 0 | M46: 0 | N46: 0 | O46: 0 | P46: 0 | Q46: 0 | R46: 0 | S46: 0 | T46: 0 | U46: Não | V46: =IFERROR((K46+M46+R46+S46+T46+O46)+IF(U46="Sim",P46+Q46,0),(K46+R46+S46+T46)+IF(U46="Sim",P46+Q46,0)) -> 26027.65 | AA46: 45778 | AB46: {=IFERROR( IF( _xlfn.XLOOKUP( 1, ( ('Condições de Faturamento'!$C$2:$C$1000 = Tab_Faturamento_RJ[[#This Row],[Unidade]]) * ('Condições de Faturamento'!$D$2:$D$1000 = Tab_Faturamento_RJ[[#This Row],[Categoria]]) * ('Condições de Faturamento'!$E$2:$E$1000 = Tab_Faturamento_RJ[[#This Row],[Fornecedor]]) ), 'Condições de Faturamento'!$F$2:$F$1000 ) = "Emissão no mês da prestação do serviço", Tab_Faturamento_RJ[[#This Row],[Mês de referência para faturamento]], DATE( YEAR(Tab_Faturamento_RJ[[#This Row],[Mês de referência para faturamento]]), MONTH(Tab_Faturamento_RJ[[#This Row],[Mês de referência para faturamento]]) + 1, DAY(Tab_Faturamento_RJ[[#This Row],[Mês de referência para faturamento]]) ) ), DATE( YEAR(Tab_Faturamento_RJ[[#This Row],[Mês de referência para faturamento]]), MONTH(Tab_Faturamento_RJ[[#This Row],[Mês de referência para faturamento]]) + 1, DAY(Tab_Faturamento_RJ[[#This Row],[Mês de referência para faturamento]]) ) )} -> 45778 | AJ46: =IFERROR(L46-M46,0) -> 0 | AK46: =AC46-AD46 -> 0 | AL46: =K46-V46 -> 0 | AN46: kaike.costa@atlasinovacoes.com.br
C47: Não | D47: Bangu Shopping | E47: PMOC | F47: GPS | G47: 4 | H47: 3 | I47: Informação pendente | J47: Informação pendente | K47: 26027.65 | L47: 0 | M47: Informação pendente | N47: 0 | O47: Informação pendente | P47: preenchimento pendente | Q47: 0 | R47: 0 | S47: 0 | T47: 0 | U47: Não | V47: =IFERROR((K47+M47+R47+S47+T47+O47)+IF(U47="Sim",P47+Q47,0),(K47+R47+S47+T47)+IF(U47="Sim",P47+Q47,0)) -> 26027.65 | AA47: 45809 | AB47: {=IFERROR( IF( _xlfn.XLOOKUP( 1, ( ('Condições de Faturamento'!$C$2:$C$1000 = Tab_Faturamento_RJ[[#This Row],[Unidade]]) * ('Condições de Faturamento'!$D$2:$D$1000 = Tab_Faturamento_RJ[[#This Row],[Categoria]]) * ('Condições de Faturamento'!$E$2:$E$1000 = Tab_Faturamento_RJ[[#This Row],[Fornecedor]]) ), 'Condições de Faturamento'!$F$2:$F$1000 ) = "Emissão no mês da prestação do serviço", Tab_Faturamento_RJ[[#This Row],[Mês de referência para faturamento]], DATE( YEAR(Tab_Faturamento_RJ[[#This Row],[Mês de referência para faturamento]]), MONTH(Tab_Faturamento_RJ[[#This Row],[Mês de referência para faturamento]]) + 1, DAY(Tab_Faturamento_RJ[[#This Row],[Mês de referência para faturamento]]) ) ), DATE( YEAR(Tab_Faturamento_RJ[[#This Row],[Mês de referência para faturamento]]), MONTH(Tab_Faturamento_RJ[[#This Row],[Mês de referência para faturamento]]) + 1, DAY(Tab_Faturamento_RJ[[#This Row],[Mês de referência para faturamento]]) ) )} -> 45809 | AJ47: =IFERROR(L47-M47,0) -> 0 | AK47: =AC47-AD47 -> 0 | AL47: =K47-V47 -> 0 | AN47: kaike.costa@atlasinovacoes.com.br
B48: 45887 | C48: Sim | D48: Bangu Shopping | E48: PMOC | F48: GPS | G48: 4 | H48: 3 | I48: 0 | J48: 0 | K48: 27438.272 | L48: 0 | M48: 0 | N48: 0 | O48: 0 | P48: 0 | Q48: 0 | R48: 0 | S48: 0 | T48: 0 | U48: Sim | V48: =IFERROR((K48+M48+R48+S48+T48+O48)+IF(U48="Sim",P48+Q48,0),(K48+R48+S48+T48)+IF(U48="Sim",P48+Q48,0)) -> 27438.272 | AA48: 45870 | AB48: {=IFERROR( IF( _xlfn.XLOOKUP( 1, ( ('Condições de Faturamento'!$C$2:$C$1000 = Tab_Faturamento_RJ[[#This Row],[Unidade]]) * ('Condições de Faturamento'!$D$2:$D$1000 = Tab_Faturamento_RJ[[#This Row],[Categoria]]) * ('Condições de Faturamento'!$E$2:$E$1000 = Tab_Faturamento_RJ[[#This Row],[Fornecedor]]) ), 'Condições de Faturamento'!$F$2:$F$1000 ) = "Emissão no mês da prestação do serviço", Tab_Faturamento_RJ[[#This Row],[Mês de referência para faturamento]], DATE( YEAR(Tab_Faturamento_RJ[[#This Row],[Mês de referência para faturamento]]), MONTH(Tab_Faturamento_RJ[[#This Row],[Mês de referência para faturamento]]) + 1, DAY(Tab_Faturamento_RJ[[#This Row],[Mês de referência para faturamento]]) ) ), DATE( YEAR(Tab_Faturamento_RJ[[#This Row],[Mês de referência para faturamento]]), MONTH(Tab_Faturamento_RJ[[#This Row],[Mês de referência para faturamento]]) + 1, DAY(Tab_Faturamento_RJ[[#This Row],[Mês de referência para faturamento]]) ) )} -> 45870 | AJ48: =IFERROR(L48-M48,0) -> 0 | AK48: =AC48-AD48 -> 0 | AL48: =K48-V48 -> 0 | AN48: kaike.costa@atlasinovacoes.com.br
B49: 45887 | C49: Sim | D49: Bangu Shopping | E49: Portaria | F49: GPS | G49: 28 | H49: 30 | I49: 0 | J49: 0 | K49: 149200.68 | L49: 0 | M49: 0 | N49: 0 | O49: 0 | P49: 0 | Q49: 0 | R49: 0 | S49: 0 | T49: 0 | U49: Sim | V49: =IFERROR((K49+M49+R49+S49+T49+O49)+IF(U49="Sim",P49+Q49,0),(K49+R49+S49+T49)+IF(U49="Sim",P49+Q49,0)) -> 149200.68 | Y49: =51069.0262382281/3 -> 17023.009 | Z49: 1|1 | AA49: 45839 | AB49: {=IFERROR( IF( _xlfn.XLOOKUP( 1, ( ('Condições de Faturamento'!$C$2:$C$1000 = Tab_Faturamento_RJ[[#This Row],[Unidade]]) * ('Condições de Faturamento'!$D$2:$D$1000 = Tab_Faturamento_RJ[[#This Row],[Categoria]]) * ('Condições de Faturamento'!$E$2:$E$1000 = Tab_Faturamento_RJ[[#This Row],[Fornecedor]]) ), 'Condições de Faturamento'!$F$2:$F$1000 ) = "Emissão no mês da prestação do serviço", Tab_Faturamento_RJ[[#This Row],[Mês de referência para faturamento]], DATE( YEAR(Tab_Faturamento_RJ[[#This Row],[Mês de referência para faturamento]]), MONTH(Tab_Faturamento_RJ[[#This Row],[Mês de referência para faturamento]]) + 1, DAY(Tab_Faturamento_RJ[[#This Row],[Mês de referência para faturamento]]) ) ), DATE( YEAR(Tab_Faturamento_RJ[[#This Row],[Mês de referência para faturamento]]), MONTH(Tab_Faturamento_RJ[[#This Row],[Mês de referência para faturamento]]) + 1, DAY(Tab_Faturamento_RJ[[#This Row],[Mês de referência para faturamento]]) ) )} -> 45839 | AJ49: =IFERROR(L49-M49,0) -> 0 | AK49: =AC49-AD49 -> 0 | AL49: =K49-V49 -> 0 | AN49: kaike.costa@atlasinovacoes.com.br
B50: 45887 | C50: Sim | D50: Bangu Shopping | E50: PMOC | F50: GPS | G50: 4 | H50: 3 | I50: 0 | J50: 0 | K50: 27438.272 | L50: 0 | M50: 0 | N50: 0 | O50: 0 | P50: 0 | Q50: 0 | R50: 0 | S50: 0 | T50: 0 | U50: Sim | V50: =IFERROR((K50+M50+R50+S50+T50+O50)+IF(U50="Sim",P50+Q50,0),(K50+R50+S50+T50)+IF(U50="Sim",P50+Q50,0)) -> 27438.272 | AA50: 45901 | AB50: {=IFERROR( IF( _xlfn.XLOOKUP( 1, ( ('Condições de Faturamento'!$C$2:$C$1000 = Tab_Faturamento_RJ[[#This Row],[Unidade]]) * ('Condições de Faturamento'!$D$2:$D$1000 = Tab_Faturamento_RJ[[#This Row],[Categoria]]) * ('Condições de Faturamento'!$E$2:$E$1000 = Tab_Faturamento_RJ[[#This Row],[Fornecedor]]) ), 'Condições de Faturamento'!$F$2:$F$1000 ) = "Emissão no mês da prestação do serviço", Tab_Faturamento_RJ[[#This Row],[Mês de referência para faturamento]], DATE( YEAR(Tab_Faturamento_RJ[[#This Row],[Mês de referência para faturamento]]), MONTH(Tab_Faturamento_RJ[[#This Row],[Mês de referência para faturamento]]) + 1, DAY(Tab_Faturamento_RJ[[#This Row],[Mês de referência para faturamento]]) ) ), DATE( YEAR(Tab_Faturamento_RJ[[#This Row],[Mês de referência para faturamento]]), MONTH(Tab_Faturamento_RJ[[#This Row],[Mês de referência para faturamento]]) + 1, DAY(Tab_Faturamento_RJ[[#This Row],[Mês de referência para faturamento]]) ) )} -> 45901 | AJ50: =IFERROR(L50-M50,0) -> 0 | AK50: =AC50-AD50 -> 0 | AL50: =K50-V50 -> 0 | AN50: kaike.costa@atlasinovacoes.com.br
C51: Não | D51: Bangu Shopping | E51: PMOC | F51: GPS | G51: 4 | H51: 3 | I51: Informação pendente | J51: Informação pendente | K51: 27438.272 | M51: Informação pendente | O51: Informação pendente | P51: Preenchimento pendente | Q51: Informação pendente | V51: =IFERROR((K51+M51+R51+S51+T51+O51)+IF(U51="Sim",P51+Q51,0),(K51+R51+S51+T51)+IF(U51="Sim",P51+Q51,0)) -> 27438.272 | AA51: 45931 | AB51: {=IFERROR( IF( _xlfn.XLOOKUP( 1, ( ('Condições de Faturamento'!$C$2:$C$1000 = Tab_Faturamento_RJ[[#This Row],[Unidade]]) * ('Condições de Faturamento'!$D$2:$D$1000 = Tab_Faturamento_RJ[[#This Row],[Categoria]]) * ('Condições de Faturamento'!$E$2:$E$1000 = Tab_Faturamento_RJ[[#This Row],[Fornecedor]]) ), 'Condições de Faturamento'!$F$2:$F$1000 ) = "Emissão no mês da prestação do serviço", Tab_Faturamento_RJ[[#This Row],[Mês de referência para faturamento]], DATE( YEAR(Tab_Faturamento_RJ[[#This Row],[Mês de referência para faturamento]]), MONTH(Tab_Faturamento_RJ[[#This Row],[Mês de referência para faturamento]]) + 1, DAY(Tab_Faturamento_RJ[[#This Row],[Mês de referência para faturamento]]) ) ), DATE( YEAR(Tab_Faturamento_RJ[[#This Row],[Mês de referência para faturamento]]), MONTH(Tab_Faturamento_RJ[[#This Row],[Mês de referência para faturamento]]) + 1, DAY(Tab_Faturamento_RJ[[#This Row],[Mês de referência para faturamento]]) ) )} -> 45931 | AJ51: =IFERROR(L51-M51,0) -> 0 | AK51: =AC51-AD51 -> 0 | AL51: =K51-V51 -> 0 | AN51: kaike.costa@atlasinovacoes.com.br
D52: Bangu Shopping | E52: PMOC | F52: GPS | G52: 4 | V52: =IFERROR((K52+M52+R52+S52+T52+O52)+IF(U52="Sim",P52+Q52,0),(K52+R52+S52+T52)+IF(U52="Sim",P52+Q52,0)) -> 0 | AA52: 45962 | AB52: {=IFERROR( IF( _xlfn.XLOOKUP( 1, ( ('Condições de Faturamento'!$C$2:$C$1000 = Tab_Faturamento_RJ[[#This Row],[Unidade]]) * ('Condições de Faturamento'!$D$2:$D$1000 = Tab_Faturamento_RJ[[#This Row],[Categoria]]) * ('Condições de Faturamento'!$E$2:$E$1000 = Tab_Faturamento_RJ[[#This Row],[Fornecedor]]) ), 'Condições de Faturamento'!$F$2:$F$1000 ) = "Emissão no mês da prestação do serviço", Tab_Faturamento_RJ[[#This Row],[Mês de referência para faturamento]], DATE( YEAR(Tab_Faturamento_RJ[[#This Row],[Mês de referência para faturamento]]), MONTH(Tab_Faturamento_RJ[[#This Row],[Mês de referência para faturamento]]) + 1, DAY(Tab_Faturamento_RJ[[#This Row],[Mês de referência para faturamento]]) ) ), DATE( YEAR(Tab_Faturamento_RJ[[#This Row],[Mês de referência para faturamento]]), MONTH(Tab_Faturamento_RJ[[#This Row],[Mês de referência para faturamento]]) + 1, DAY(Tab_Faturamento_RJ[[#This Row],[Mês de referência para faturamento]]) ) )} -> 45962 | AJ52: =IFERROR(L52-M52,0) -> 0 | AK52: =AC52-AD52 -> 0 | AL52: =K52-V52 -> 0 | AN52: kaike.costa@atlasinovacoes.com.br
D53: Bangu Shopping | E53: PMOC | F53: GPS | G53: 4 | V53: =IFERROR((K53+M53+R53+S53+T53+O53)+IF(U53="Sim",P53+Q53,0),(K53+R53+S53+T53)+IF(U53="Sim",P53+Q53,0)) -> 0 | AA53: 45992 | AB53: {=IFERROR( IF( _xlfn.XLOOKUP( 1, ( ('Condições de Faturamento'!$C$2:$C$1000 = Tab_Faturamento_RJ[[#This Row],[Unidade]]) * ('Condições de Faturamento'!$D$2:$D$1000 = Tab_Faturamento_RJ[[#This Row],[Categoria]]) * ('Condições de Faturamento'!$E$2:$E$1000 = Tab_Faturamento_RJ[[#This Row],[Fornecedor]]) ), 'Condições de Faturamento'!$F$2:$F$1000 ) = "Emissão no mês da prestação do serviço", Tab_Faturamento_RJ[[#This Row],[Mês de referência para faturamento]], DATE( YEAR(Tab_Faturamento_RJ[[#This Row],[Mês de referência para faturamento]]), MONTH(Tab_Faturamento_RJ[[#This Row],[Mês de referência para faturamento]]) + 1, DAY(Tab_Faturamento_RJ[[#This Row],[Mês de referência para faturamento]]) ) ), DATE( YEAR(Tab_Faturamento_RJ[[#This Row],[Mês de referência para faturamento]]), MONTH(Tab_Faturamento_RJ[[#This Row],[Mês de referência para faturamento]]) + 1, DAY(Tab_Faturamento_RJ[[#This Row],[Mês de referência para faturamento]]) ) )} -> 45992 | AJ53: =IFERROR(L53-M53,0) -> 0 | AK53: =AC53-AD53 -> 0 | AL53: =K53-V53 -> 0 | AN53: kaike.costa@atlasinovacoes.com.br
C54: Não | D54: Bangu Shopping | E54: Portaria | F54: GPS | G54: 28 | H54: 30 | I54: Informação pendente | J54: Informação pendente | K54: 138986.87 | L54: 0 | M54: Informação pendente | N54: 0 | O54: Informação pendente | P54: 0 | Q54: 0 | R54: 0 | S54: 0 | T54: 0 | V54: =IFERROR((K54+M54+R54+S54+T54+O54)+IF(U54="Sim",P54+Q54,0),(K54+R54+S54+T54)+IF(U54="Sim",P54+Q54,0)) -> 138986.87 | AA54: 45658 | AB54: {=IFERROR( IF( _xlfn.XLOOKUP( 1, ( ('Condições de Faturamento'!$C$2:$C$1000 = Tab_Faturamento_RJ[[#This Row],[Unidade]]) * ('Condições de Faturamento'!$D$2:$D$1000 = Tab_Faturamento_RJ[[#This Row],[Categoria]]) * ('Condições de Faturamento'!$E$2:$E$1000 = Tab_Faturamento_RJ[[#This Row],[Fornecedor]]) ), 'Condições de Faturamento'!$F$2:$F$1000 ) = "Emissão no mês da prestação do serviço", Tab_Faturamento_RJ[[#This Row],[Mês de referência para faturamento]], DATE( YEAR(Tab_Faturamento_RJ[[#This Row],[Mês de referência para faturamento]]), MONTH(Tab_Faturamento_RJ[[#This Row],[Mês de referência para faturamento]]) + 1, DAY(Tab_Faturamento_RJ[[#This Row],[Mês de referência para faturamento]]) ) ), DATE( YEAR(Tab_Faturamento_RJ[[#This Row],[Mês de referência para faturamento]]), MONTH(Tab_Faturamento_RJ[[#This Row],[Mês de referência para faturamento]]) + 1, DAY(Tab_Faturamento_RJ[[#This Row],[Mês de referência para faturamento]]) ) )} -> 45658 | AJ54: =IFERROR(L54-M54,0) -> 0 | AK54: =AC54-AD54 -> 0 | AL54: =K54-V54 -> 0 | AN54: kaike.costa@atlasinovacoes.com.br
C55: Não | D55: Bangu Shopping | E55: Portaria | F55: GPS | G55: 28 | H55: 30 | I55: Informação pendente | J55: Informação pendente | K55: 138986.87 | L55: 0 | M55: Informação pendente | N55: 0 | O55: Informação pendente | P55: 0 | Q55: 0 | R55: 0 | S55: 0 | T55: 0 | V55: =IFERROR((K55+M55+R55+S55+T55+O55)+IF(U55="Sim",P55+Q55,0),(K55+R55+S55+T55)+IF(U55="Sim",P55+Q55,0)) -> 138986.87 | AA55: 45689 | AB55: {=IFERROR( IF( _xlfn.XLOOKUP( 1, ( ('Condições de Faturamento'!$C$2:$C$1000 = Tab_Faturamento_RJ[[#This Row],[Unidade]]) * ('Condições de Faturamento'!$D$2:$D$1000 = Tab_Faturamento_RJ[[#This Row],[Categoria]]) * ('Condições de Faturamento'!$E$2:$E$1000 = Tab_Faturamento_RJ[[#This Row],[Fornecedor]]) ), 'Condições de Faturamento'!$F$2:$F$1000 ) = "Emissão no mês da prestação do serviço", Tab_Faturamento_RJ[[#This Row],[Mês de referência para faturamento]], DATE( YEAR(Tab_Faturamento_RJ[[#This Row],[Mês de referência para faturamento]]), MONTH(Tab_Faturamento_RJ[[#This Row],[Mês de referência para faturamento]]) + 1, DAY(Tab_Faturamento_RJ[[#This Row],[Mês de referência para faturamento]]) ) ), DATE( YEAR(Tab_Faturamento_RJ[[#This Row],[Mês de referência para faturamento]]), MONTH(Tab_Faturamento_RJ[[#This Row],[Mês de referência para faturamento]]) + 1, DAY(Tab_Faturamento_RJ[[#This Row],[Mês de referência para faturamento]]) ) )} -> 45689 | AJ55: =IFERROR(L55-M55,0) -> 0 | AK55: =AC55-AD55 -> 0 | AL55: =K55-V55 -> 0 | AN55: kaike.costa@atlasinovacoes.com.br
C56: Não | D56: Bangu Shopping | E56: Portaria | F56: GPS | G56: 28 | H56: 30 | I56: 0 | J56: 0 | K56: 138986.87 | L56: 0 | M56: 0 | N56: 0 | O56: 0 | P56: 0 | Q56: 0 | R56: 0 | S56: 0 | T56: 0 | U56: Sim | V56: =IFERROR((K56+M56+R56+S56+T56+O56)+IF(U56="Sim",P56+Q56,0),(K56+R56+S56+T56)+IF(U56="Sim",P56+Q56,0)) -> 138986.87 | AA56: 45717 | AB56: {=IFERROR( IF( _xlfn.XLOOKUP( 1, ( ('Condições de Faturamento'!$C$2:$C$1000 = Tab_Faturamento_RJ[[#This Row],[Unidade]]) * ('Condições de Faturamento'!$D$2:$D$1000 = Tab_Faturamento_RJ[[#This Row],[Categoria]]) * ('Condições de Faturamento'!$E$2:$E$1000 = Tab_Faturamento_RJ[[#This Row],[Fornecedor]]) ), 'Condições de Faturamento'!$F$2:$F$1000 ) = "Emissão no mês da prestação do serviço", Tab_Faturamento_RJ[[#This Row],[Mês de referência para faturamento]], DATE( YEAR(Tab_Faturamento_RJ[[#This Row],[Mês de referência para faturamento]]), MONTH(Tab_Faturamento_RJ[[#This Row],[Mês de referência para faturamento]]) + 1, DAY(Tab_Faturamento_RJ[[#This Row],[Mês de referência para faturamento]]) ) ), DATE( YEAR(Tab_Faturamento_RJ[[#This Row],[Mês de referência para faturamento]]), MONTH(Tab_Faturamento_RJ[[#This Row],[Mês de referência para faturamento]]) + 1, DAY(Tab_Faturamento_RJ[[#This Row],[Mês de referência para faturamento]]) ) )} -> 45717 | AJ56: =IFERROR(L56-M56,0) -> 0 | AK56: =AC56-AD56 -> 0 | AL56: =K56-V56 -> 0 | AN56: kaike.costa@atlasinovacoes.com.br
C57: Não | D57: Bangu Shopping | E57: Portaria | F57: GPS | G57: 28 | H57: 30 | I57: 0 | J57: 0 | K57: 138986.87 | L57: 0 | M57: 0 | N57: 0 | O57: 0 | P57: 0 | Q57: 0 | R57: 0 | S57: 0 | T57: 0 | U57: Não | V57: =IFERROR((K57+M57+R57+S57+T57+O57)+IF(U57="Sim",P57+Q57,0),(K57+R57+S57+T57)+IF(U57="Sim",P57+Q57,0)) -> 138986.87 | AA57: 45748 | AB57: {=IFERROR( IF( _xlfn.XLOOKUP( 1, ( ('Condições de Faturamento'!$C$2:$C$1000 = Tab_Faturamento_RJ[[#This Row],[Unidade]]) * ('Condições de Faturamento'!$D$2:$D$1000 = Tab_Faturamento_RJ[[#This Row],[Categoria]]) * ('Condições de Faturamento'!$E$2:$E$1000 = Tab_Faturamento_RJ[[#This Row],[Fornecedor]]) ), 'Condições de Faturamento'!$F$2:$F$1000 ) = "Emissão no mês da prestação do serviço", Tab_Faturamento_RJ[[#This Row],[Mês de referência para faturamento]], DATE( YEAR(Tab_Faturamento_RJ[[#This Row],[Mês de referência para faturamento]]), MONTH(Tab_Faturamento_RJ[[#This Row],[Mês de referência para faturamento]]) + 1, DAY(Tab_Faturamento_RJ[[#This Row],[Mês de referência para faturamento]]) ) ), DATE( YEAR(Tab_Faturamento_RJ[[#This Row],[Mês de referência para faturamento]]), MONTH(Tab_Faturamento_RJ[[#This Row],[Mês de referência para faturamento]]) + 1, DAY(Tab_Faturamento_RJ[[#This Row],[Mês de referência para faturamento]]) ) )} -> 45748 | AJ57: =IFERROR(L57-M57,0) -> 0 | AK57: =AC57-AD57 -> 0 | AL57: =K57-V57 -> 0 | AN57: kaike.costa@atlasinovacoes.com.br
C58: Não | D58: Bangu Shopping | E58: Portaria | F58: GPS | G58: 28 | H58: 30 | I58: 0 | J58: 0 | K58: 138986.87 | L58: 0 | M58: 0 | N58: 0 | O58: 0 | P58: 0 | Q58: 0 | R58: 0 | S58: 0 | T58: 0 | U58: Não | V58: =IFERROR((K58+M58+R58+S58+T58+O58)+IF(U58="Sim",P58+Q58,0),(K58+R58+S58+T58)+IF(U58="Sim",P58+Q58,0)) -> 138986.87 | AA58: 45778 | AB58: {=IFERROR( IF( _xlfn.XLOOKUP( 1, ( ('Condições de Faturamento'!$C$2:$C$1000 = Tab_Faturamento_RJ[[#This Row],[Unidade]]) * ('Condições de Faturamento'!$D$2:$D$1000 = Tab_Faturamento_RJ[[#This Row],[Categoria]]) * ('Condições de Faturamento'!$E$2:$E$1000 = Tab_Faturamento_RJ[[#This Row],[Fornecedor]]) ), 'Condições de Faturamento'!$F$2:$F$1000 ) = "Emissão no mês da prestação do serviço", Tab_Faturamento_RJ[[#This Row],[Mês de referência para faturamento]], DATE( YEAR(Tab_Faturamento_RJ[[#This Row],[Mês de referência para faturamento]]), MONTH(Tab_Faturamento_RJ[[#This Row],[Mês de referência para faturamento]]) + 1, DAY(Tab_Faturamento_RJ[[#This Row],[Mês de referência para faturamento]]) ) ), DATE( YEAR(Tab_Faturamento_RJ[[#This Row],[Mês de referência para faturamento]]), MONTH(Tab_Faturamento_RJ[[#This Row],[Mês de referência para faturamento]]) + 1, DAY(Tab_Faturamento_RJ[[#This Row],[Mês de referência para faturamento]]) ) )} -> 45778 | AJ58: =IFERROR(L58-M58,0) -> 0 | AK58: =AC58-AD58 -> 0 | AL58: =K58-V58 -> 0 | AN58: kaike.costa@atlasinovacoes.com.br
C59: Não | D59: Bangu Shopping | E59: Portaria | F59: GPS | G59: 28 | H59: 30 | I59: Informação pendente | J59: Informação pendente | K59: 138986.87 | L59: 0 | M59: Informação pendente | N59: 0 | O59: Informação pendente | P59: Preenchimento pendente | Q59: 0 | R59: 0 | S59: 0 | T59: 0 | U59: Não | V59: =IFERROR((K59+M59+R59+S59+T59+O59)+IF(U59="Sim",P59+Q59,0),(K59+R59+S59+T59)+IF(U59="Sim",P59+Q59,0)) -> 138986.87 | AA59: 45809 | AB59: {=IFERROR( IF( _xlfn.XLOOKUP( 1, ( ('Condições de Faturamento'!$C$2:$C$1000 = Tab_Faturamento_RJ[[#This Row],[Unidade]]) * ('Condições de Faturamento'!$D$2:$D$1000 = Tab_Faturamento_RJ[[#This Row],[Categoria]]) * ('Condições de Faturamento'!$E$2:$E$1000 = Tab_Faturamento_RJ[[#This Row],[Fornecedor]]) ), 'Condições de Faturamento'!$F$2:$F$1000 ) = "Emissão no mês da prestação do serviço", Tab_Faturamento_RJ[[#This Row],[Mês de referência para faturamento]], DATE( YEAR(Tab_Faturamento_RJ[[#This Row],[Mês de referência para faturamento]]), MONTH(Tab_Faturamento_RJ[[#This Row],[Mês de referência para faturamento]]) + 1, DAY(Tab_Faturamento_RJ[[#This Row],[Mês de referência para faturamento]]) ) ), DATE( YEAR(Tab_Faturamento_RJ[[#This Row],[Mês de referência para faturamento]]), MONTH(Tab_Faturamento_RJ[[#This Row],[Mês de referência para faturamento]]) + 1, DAY(Tab_Faturamento_RJ[[#This Row],[Mês de referência para faturamento]]) ) )} -> 45809 | AJ59: =IFERROR(L59-M59,0) -> 0 | AK59: =AC59-AD59 -> 0 | AL59: =K59-V59 -> 0 | AN59: kaike.costa@atlasinovacoes.com.br
C60: Não | D60: Bangu Shopping | E60: Portaria | F60: GPS | G60: 28 | H60: 30 | I60: Informação pendente | J60: Informação pendente | K60: 149200.68 | L60: 0 | M60: Informação pendente | N60: 0 | O60: Informação pendente | P60: 0 | Q60: 0 | R60: 0 | S60: 0 | T60: 0 | V60: =IFERROR((K60+M60+R60+S60+T60+O60)+IF(U60="Sim",P60+Q60,0),(K60+R60+S60+T60)+IF(U60="Sim",P60+Q60,0)) -> 149200.68 | Y60: =51069.0262382281/3 -> 17023.009 | Z60: 1|2 | AA60: 45870 | AB60: {=IFERROR( IF( _xlfn.XLOOKUP( 1, ( ('Condições de Faturamento'!$C$2:$C$1000 = Tab_Faturamento_RJ[[#This Row],[Unidade]]) * ('Condições de Faturamento'!$D$2:$D$1000 = Tab_Faturamento_RJ[[#This Row],[Categoria]]) * ('Condições de Faturamento'!$E$2:$E$1000 = Tab_Faturamento_RJ[[#This Row],[Fornecedor]]) ), 'Condições de Faturamento'!$F$2:$F$1000 ) = "Emissão no mês da prestação do serviço", Tab_Faturamento_RJ[[#This Row],[Mês de referência para faturamento]], DATE( YEAR(Tab_Faturamento_RJ[[#This Row],[Mês de referência para faturamento]]), MONTH(Tab_Faturamento_RJ[[#This Row],[Mês de referência para faturamento]]) + 1, DAY(Tab_Faturamento_RJ[[#This Row],[Mês de referência para faturamento]]) ) ), DATE( YEAR(Tab_Faturamento_RJ[[#This Row],[Mês de referência para faturamento]]), MONTH(Tab_Faturamento_RJ[[#This Row],[Mês de referência para faturamento]]) + 1, DAY(Tab_Faturamento_RJ[[#This Row],[Mês de referência para faturamento]]) ) )} -> 45870 | AJ60: =IFERROR(L60-M60,0) -> 0 | AK60: =AC60-AD60 -> 0 | AL60: =K60-V60 -> 0 | AN60: kaike.costa@atlasinovacoes.com.br
B61: 45848 | C61: Sim | D61: Bangu Shopping | E61: Prensa | F61: Verzani | G61: 1 | H61: 1 | I61: 0 | J61: 0 | K61: 6254.8924 | L61: 0 | M61: 0 | N61: 0 | O61: 0 | P61: 0 | Q61: 0 | R61: 0 | S61: 0 | T61: 0 | V61: =IFERROR((K61+M61+R61+S61+T61+O61)+IF(U61="Sim",P61+Q61,0),(K61+R61+S61+T61)+IF(U61="Sim",P61+Q61,0)) -> 6254.8924 | AA61: 45839 | AB61: {=IFERROR( IF( _xlfn.XLOOKUP( 1, ( ('Condições de Faturamento'!$C$2:$C$1000 = Tab_Faturamento_RJ[[#This Row],[Unidade]]) * ('Condições de Faturamento'!$D$2:$D$1000 = Tab_Faturamento_RJ[[#This Row],[Categoria]]) * ('Condições de Faturamento'!$E$2:$E$1000 = Tab_Faturamento_RJ[[#This Row],[Fornecedor]]) ), 'Condições de Faturamento'!$F$2:$F$1000 ) = "Emissão no mês da prestação do serviço", Tab_Faturamento_RJ[[#This Row],[Mês de referência para faturamento]], DATE( YEAR(Tab_Faturamento_RJ[[#This Row],[Mês de referência para faturamento]]), MONTH(Tab_Faturamento_RJ[[#This Row],[Mês de referência para faturamento]]) + 1, DAY(Tab_Faturamento_RJ[[#This Row],[Mês de referência para faturamento]]) ) ), DATE( YEAR(Tab_Faturamento_RJ[[#This Row],[Mês de referência para faturamento]]), MONTH(Tab_Faturamento_RJ[[#This Row],[Mês de referência para faturamento]]) + 1, DAY(Tab_Faturamento_RJ[[#This Row],[Mês de referência para faturamento]]) ) )} -> 45870 | AJ61: =IFERROR(L61-M61,0) -> 0 | AK61: =AC61-AD61 -> 0 | AL61: =K61-V61 -> 0 | AN61: kaike.costa@atlasinovacoes.com.br
C62: Não | D62: Bangu Shopping | E62: Portaria | F62: GPS | G62: 28 | H62: 30 | I62: Informação pendente | J62: Informação pendente | K62: 149200.68 | L62: 0 | M62: Informação pendente | N62: 0 | O62: Informação pendente | P62: Preenchimento pendente | Q62: 0 | R62: 0 | S62: 0 | T62: 0 | V62: =IFERROR((K62+M62+R62+S62+T62+O62)+IF(U62="Sim",P62+Q62,0),(K62+R62+S62+T62)+IF(U62="Sim",P62+Q62,0)) -> 149200.68 | Y62: =51069.0262382281/3 -> 17023.009 | Z62: 1|3 | AA62: 45901 | AB62: {=IFERROR( IF( _xlfn.XLOOKUP( 1, ( ('Condições de Faturamento'!$C$2:$C$1000 = Tab_Faturamento_RJ[[#This Row],[Unidade]]) * ('Condições de Faturamento'!$D$2:$D$1000 = Tab_Faturamento_RJ[[#This Row],[Categoria]]) * ('Condições de Faturamento'!$E$2:$E$1000 = Tab_Faturamento_RJ[[#This Row],[Fornecedor]]) ), 'Condições de Faturamento'!$F$2:$F$1000 ) = "Emissão no mês da prestação do serviço", Tab_Faturamento_RJ[[#This Row],[Mês de referência para faturamento]], DATE( YEAR(Tab_Faturamento_RJ[[#This Row],[Mês de referência para faturamento]]), MONTH(Tab_Faturamento_RJ[[#This Row],[Mês de referência para faturamento]]) + 1, DAY(Tab_Faturamento_RJ[[#This Row],[Mês de referência para faturamento]]) ) ), DATE( YEAR(Tab_Faturamento_RJ[[#This Row],[Mês de referência para faturamento]]), MONTH(Tab_Faturamento_RJ[[#This Row],[Mês de referência para faturamento]]) + 1, DAY(Tab_Faturamento_RJ[[#This Row],[Mês de referência para faturamento]]) ) )} -> 45901 | AD62: 3710.33 | AJ62: =IFERROR(L62-M62,0) -> 0 | AK62: =AC62-AD62 -> -3710.33 | AL62: =K62-V62 -> 0 | AN62: kaike.costa@atlasinovacoes.com.br
C63: Não | D63: Bangu Shopping | E63: Portaria | F63: GPS | G63: 28 | H63: 30 | I63: Informação pendente | J63: Informação pendente | K63: 149200.68 | M63: Informação pendente | O63: Informação pendente | P63: Preenchimento pendente | Q63: Informação pendente | R63: Informação pendente | S63: Informação pendente | T63: Informação pendente | V63: =IFERROR((K63+M63+R63+S63+T63+#REF!)+IF(U63="Sim",P63+Q63,0),(K63+R63+S63+T63)+IF(U63="Sim",P63+Q63,0)) -> #VALUE! | AA63: 45931 | AB63: {=IFERROR( IF( _xlfn.XLOOKUP( 1, ( ('Condições de Faturamento'!$C$2:$C$1000 = Tab_Faturamento_RJ[[#This Row],[Unidade]]) * ('Condições de Faturamento'!$D$2:$D$1000 = Tab_Faturamento_RJ[[#This Row],[Categoria]]) * ('Condições de Faturamento'!$E$2:$E$1000 = Tab_Faturamento_RJ[[#This Row],[Fornecedor]]) ), 'Condições de Faturamento'!$F$2:$F$1000 ) = "Emissão no mês da prestação do serviço", Tab_Faturamento_RJ[[#This Row],[Mês de referência para faturamento]], DATE( YEAR(Tab_Faturamento_RJ[[#This Row],[Mês de referência para faturamento]]), MONTH(Tab_Faturamento_RJ[[#This Row],[Mês de referência para faturamento]]) + 1, DAY(Tab_Faturamento_RJ[[#This Row],[Mês de referência para faturamento]]) ) ), DATE( YEAR(Tab_Faturamento_RJ[[#This Row],[Mês de referência para faturamento]]), MONTH(Tab_Faturamento_RJ[[#This Row],[Mês de referência para faturamento]]) + 1, DAY(Tab_Faturamento_RJ[[#This Row],[Mês de referência para faturamento]]) ) )} -> 45931 | AD63: 8132.42 | AJ63: =IFERROR(L63-M63,0) -> 0 | AK63: =AC63-AD63 -> -8132.42 | AL63: =K63-V63 -> #VALUE! | AN63: kaike.costa@atlasinovacoes.com.br
D64: Bangu Shopping | E64: Portaria | F64: GPS | G64: 28 | V64: =IFERROR((K64+M64+R64+S64+T64+O64)+IF(U64="Sim",P64+Q64,0),(K64+R64+S64+T64)+IF(U64="Sim",P64+Q64,0)) -> 0 | AA64: 45962 | AB64: {=IFERROR( IF( _xlfn.XLOOKUP( 1, ( ('Condições de Faturamento'!$C$2:$C$1000 = Tab_Faturamento_RJ[[#This Row],[Unidade]]) * ('Condições de Faturamento'!$D$2:$D$1000 = Tab_Faturamento_RJ[[#This Row],[Categoria]]) * ('Condições de Faturamento'!$E$2:$E$1000 = Tab_Faturamento_RJ[[#This Row],[Fornecedor]]) ), 'Condições de Faturamento'!$F$2:$F$1000 ) = "Emissão no mês da prestação do serviço", Tab_Faturamento_RJ[[#This Row],[Mês de referência para faturamento]], DATE( YEAR(Tab_Faturamento_RJ[[#This Row],[Mês de referência para faturamento]]), MONTH(Tab_Faturamento_RJ[[#This Row],[Mês de referência para faturamento]]) + 1, DAY(Tab_Faturamento_RJ[[#This Row],[Mês de referência para faturamento]]) ) ), DATE( YEAR(Tab_Faturamento_RJ[[#This Row],[Mês de referência para faturamento]]), MONTH(Tab_Faturamento_RJ[[#This Row],[Mês de referência para faturamento]]) + 1, DAY(Tab_Faturamento_RJ[[#This Row],[Mês de referência para faturamento]]) ) )} -> 45962 | AJ64: =IFERROR(L64-M64,0) -> 0 | AK64: =AC64-AD64 -> 0 | AL64: =K64-V64 -> 0 | AN64: kaike.costa@atlasinovacoes.com.br
D65: Bangu Shopping | E65: Portaria | F65: GPS | G65: 28 | V65: =IFERROR((K65+M65+R65+S65+T65+O65)+IF(U65="Sim",P65+Q65,0),(K65+R65+S65+T65)+IF(U65="Sim",P65+Q65,0)) -> 0 | AA65: 45992 | AB65: {=IFERROR( IF( _xlfn.XLOOKUP( 1, ( ('Condições de Faturamento'!$C$2:$C$1000 = Tab_Faturamento_RJ[[#This Row],[Unidade]]) * ('Condições de Faturamento'!$D$2:$D$1000 = Tab_Faturamento_RJ[[#This Row],[Categoria]]) * ('Condições de Faturamento'!$E$2:$E$1000 = Tab_Faturamento_RJ[[#This Row],[Fornecedor]]) ), 'Condições de Faturamento'!$F$2:$F$1000 ) = "Emissão no mês da prestação do serviço", Tab_Faturamento_RJ[[#This Row],[Mês de referência para faturamento]], DATE( YEAR(Tab_Faturamento_RJ[[#This Row],[Mês de referência para faturamento]]), MONTH(Tab_Faturamento_RJ[[#This Row],[Mês de referência para faturamento]]) + 1, DAY(Tab_Faturamento_RJ[[#This Row],[Mês de referência para faturamento]]) ) ), DATE( YEAR(Tab_Faturamento_RJ[[#This Row],[Mês de referência para faturamento]]), MONTH(Tab_Faturamento_RJ[[#This Row],[Mês de referência para faturamento]]) + 1, DAY(Tab_Faturamento_RJ[[#This Row],[Mês de referência para faturamento]]) ) )} -> 45992 | AC65: 7519.04 | AD65: 8132.42 | AJ65: =IFERROR(L65-M65,0) -> 0 | AK65: =AC65-AD65 -> -613.38 | AL65: =K65-V65 -> 0 | AN65: kaike.costa@atlasinovacoes.com.br
B66: 45818 | C66: Sim | D66: Bangu Shopping | E66: Prensa | F66: Verzani | G66: 1 | H66: 1 | I66: 0 | J66: 0 | K66: 6254.8924 | L66: 0 | M66: 0 | N66: 0 | O66: 0 | P66: 0 | Q66: 0 | R66: 0 | S66: 0 | T66: 0 | U66: Não | V66: =IFERROR((K66+M66+R66+S66+T66+O66)+IF(U66="Sim",P66+Q66,0),(K66+R66+S66+T66)+IF(U66="Sim",P66+Q66,0)) -> 6254.8924 | AA66: 45809 | AB66: {=IFERROR( IF( _xlfn.XLOOKUP( 1, ( ('Condições de Faturamento'!$C$2:$C$1000 = Tab_Faturamento_RJ[[#This Row],[Unidade]]) * ('Condições de Faturamento'!$D$2:$D$1000 = Tab_Faturamento_RJ[[#This Row],[Categoria]]) * ('Condições de Faturamento'!$E$2:$E$1000 = Tab_Faturamento_RJ[[#This Row],[Fornecedor]]) ), 'Condições de Faturamento'!$F$2:$F$1000 ) = "Emissão no mês da prestação do serviço", Tab_Faturamento_RJ[[#This Row],[Mês de referência para faturamento]], DATE( YEAR(Tab_Faturamento_RJ[[#This Row],[Mês de referência para faturamento]]), MONTH(Tab_Faturamento_RJ[[#This Row],[Mês de referência para faturamento]]) + 1, DAY(Tab_Faturamento_RJ[[#This Row],[Mês de referência para faturamento]]) ) ), DATE( YEAR(Tab_Faturamento_RJ[[#This Row],[Mês de referência para faturamento]]), MONTH(Tab_Faturamento_RJ[[#This Row],[Mês de referência para faturamento]]) + 1, DAY(Tab_Faturamento_RJ[[#This Row],[Mês de referência para faturamento]]) ) )} -> 45839 | AJ66: =IFERROR(L66-M66,0) -> 0 | AK66: =AC66-AD66 -> 0 | AL66: =K66-V66 -> 0 | AN66: kaike.costa@atlasinovacoes.com.br
B67: 45842 | C67: Sim | D67: Bangu Shopping | E67: Resíduos | F67: Verzani | G67: =Tab_Faturamento_RJ[[#This Row],[HC Planilha]] -> 2 | H67: 2 | I67: 0 | J67: 0 | K67: 12461.142 | L67: 0 | M67: 0 | N67: 0 | O67: 0 | P67: 0 | Q67: 0 | R67: 0 | S67: 0 | T67: 0 | U67: Sim | V67: =IFERROR((K67+M67+R67+S67+T67+O67)+IF(U67="Sim",P67+Q67,0),(K67+R67+S67+T67)+IF(U67="Sim",P67+Q67,0)) -> 12461.142 | Y67: =2565.17176354316/4 -> 641.29294 | Z67: 3|4 | AA67: 45839 | AB67: {=IFERROR( IF( _xlfn.XLOOKUP( 1, ( ('Condições de Faturamento'!$C$2:$C$1000 = Tab_Faturamento_RJ[[#This Row],[Unidade]]) * ('Condições de Faturamento'!$D$2:$D$1000 = Tab_Faturamento_RJ[[#This Row],[Categoria]]) * ('Condições de Faturamento'!$E$2:$E$1000 = Tab_Faturamento_RJ[[#This Row],[Fornecedor]]) ), 'Condições de Faturamento'!$F$2:$F$1000 ) = "Emissão no mês da prestação do serviço", Tab_Faturamento_RJ[[#This Row],[Mês de referência para faturamento]], DATE( YEAR(Tab_Faturamento_RJ[[#This Row],[Mês de referência para faturamento]]), MONTH(Tab_Faturamento_RJ[[#This Row],[Mês de referência para faturamento]]) + 1, DAY(Tab_Faturamento_RJ[[#This Row],[Mês de referência para faturamento]]) ) ), DATE( YEAR(Tab_Faturamento_RJ[[#This Row],[Mês de referência para faturamento]]), MONTH(Tab_Faturamento_RJ[[#This Row],[Mês de referência para faturamento]]) + 1, DAY(Tab_Faturamento_RJ[[#This Row],[Mês de referência para faturamento]]) ) )} -> 45839 | AJ67: =IFERROR(L67-M67,0) -> 0 | AK67: =AC67-AD67 -> 0 | AL67: =K67-V67 -> 0 | AN67: kaike.costa@atlasinovacoes.com.br
B68: 45877 | C68: Sim | D68: Bangu Shopping | E68: Prensa | F68: Verzani | G68: 1 | H68: 1 | I68: 0 | J68: 0 | K68: 6254.8924 | L68: 0 | M68: 0 | N68: 0 | O68: 0 | P68: 0 | Q68: 0 | R68: 0 | S68: 0 | T68: 0 | U68: Sim | V68: =IFERROR((K68+M68+R68+S68+T68+O68)+IF(U68="Sim",P68+Q68,0),(K68+R68+S68+T68)+IF(U68="Sim",P68+Q68,0)) -> 6254.8924 | AA68: 45870 | AB68: {=IFERROR( IF( _xlfn.XLOOKUP( 1, ( ('Condições de Faturamento'!$C$2:$C$1000 = Tab_Faturamento_RJ[[#This Row],[Unidade]]) * ('Condições de Faturamento'!$D$2:$D$1000 = Tab_Faturamento_RJ[[#This Row],[Categoria]]) * ('Condições de Faturamento'!$E$2:$E$1000 = Tab_Faturamento_RJ[[#This Row],[Fornecedor]]) ), 'Condições de Faturamento'!$F$2:$F$1000 ) = "Emissão no mês da prestação do serviço", Tab_Faturamento_RJ[[#This Row],[Mês de referência para faturamento]], DATE( YEAR(Tab_Faturamento_RJ[[#This Row],[Mês de referência para faturamento]]), MONTH(Tab_Faturamento_RJ[[#This Row],[Mês de referência para faturamento]]) + 1, DAY(Tab_Faturamento_RJ[[#This Row],[Mês de referência para faturamento]]) ) ), DATE( YEAR(Tab_Faturamento_RJ[[#This Row],[Mês de referência para faturamento]]), MONTH(Tab_Faturamento_RJ[[#This Row],[Mês de referência para faturamento]]) + 1, DAY(Tab_Faturamento_RJ[[#This Row],[Mês de referência para faturamento]]) ) )} -> 45901 | AJ68: =IFERROR(L68-M68,0) -> 0 | AK68: =AC68-AD68 -> 0 | AL68: =K68-V68 -> 0 | AN68: kaike.costa@atlasinovacoes.com.br
B69: 45908 | C69: Sim | D69: Bangu Shopping | E69: Prensa | F69: Verzani | G69: 1 | H69: 1 | I69: 0 | J69: 0 | K69: 6254.8924 | L69: 0 | M69: 0 | N69: 0 | O69: 0 | P69: 0 | Q69: 0 | R69: 0 | S69: 0 | T69: 0 | U69: Sim | V69: =IFERROR((K69+M69+R69+S69+T69+O69)+IF(U69="Sim",P69+Q69,0),(K69+R69+S69+T69)+IF(U69="Sim",P69+Q69,0)) -> 6254.8924 | AA69: 45901 | AB69: {=IFERROR( IF( _xlfn.XLOOKUP( 1, ( ('Condições de Faturamento'!$C$2:$C$1000 = Tab_Faturamento_RJ[[#This Row],[Unidade]]) * ('Condições de Faturamento'!$D$2:$D$1000 = Tab_Faturamento_RJ[[#This Row],[Categoria]]) * ('Condições de Faturamento'!$E$2:$E$1000 = Tab_Faturamento_RJ[[#This Row],[Fornecedor]]) ), 'Condições de Faturamento'!$F$2:$F$1000 ) = "Emissão no mês da prestação do serviço", Tab_Faturamento_RJ[[#This Row],[Mês de referência para faturamento]], DATE( YEAR(Tab_Faturamento_RJ[[#This Row],[Mês de referência para faturamento]]), MONTH(Tab_Faturamento_RJ[[#This Row],[Mês de referência para faturamento]]) + 1, DAY(Tab_Faturamento_RJ[[#This Row],[Mês de referência para faturamento]]) ) ), DATE( YEAR(Tab_Faturamento_RJ[[#This Row],[Mês de referência para faturamento]]), MONTH(Tab_Faturamento_RJ[[#This Row],[Mês de referência para faturamento]]) + 1, DAY(Tab_Faturamento_RJ[[#This Row],[Mês de referência para faturamento]]) ) )} -> 45931 | AJ69: =IFERROR(L69-M69,0) -> 0 | AK69: =AC69-AD69 -> 0 | AL69: =K69-V69 -> 0 | AN69: kaike.costa@atlasinovacoes.com.br
B70: 45931 | C70: Sim | D70: Bangu Shopping | E70: Prensa | F70: Verzani | G70: 1 | H70: 1 | I70: 0 | J70: 0 | K70: =(K69/30.44)*10 -> 2054.8267 | M70: 0 | O70: 0 | P70: 0 | Q70: 0 | R70: 0 | S70: 0 | T70: 0 | U70: Sim | V70: =IFERROR((K70+M70+R70+S70+T70+O70)+IF(U70="Sim",P70+Q70,0),(K70+R70+S70+T70)+IF(U70="Sim",P70+Q70,0)) -> 2054.8267 | AA70: 45931 | AB70: {=IFERROR( IF( _xlfn.XLOOKUP( 1, ( ('Condições de Faturamento'!$C$2:$C$1000 = Tab_Faturamento_RJ[[#This Row],[Unidade]]) * ('Condições de Faturamento'!$D$2:$D$1000 = Tab_Faturamento_RJ[[#This Row],[Categoria]]) * ('Condições de Faturamento'!$E$2:$E$1000 = Tab_Faturamento_RJ[[#This Row],[Fornecedor]]) ), 'Condições de Faturamento'!$F$2:$F$1000 ) = "Emissão no mês da prestação do serviço", Tab_Faturamento_RJ[[#This Row],[Mês de referência para faturamento]], DATE( YEAR(Tab_Faturamento_RJ[[#This Row],[Mês de referência para faturamento]]), MONTH(Tab_Faturamento_RJ[[#This Row],[Mês de referência para faturamento]]) + 1, DAY(Tab_Faturamento_RJ[[#This Row],[Mês de referência para faturamento]]) ) ), DATE( YEAR(Tab_Faturamento_RJ[[#This Row],[Mês de referência para faturamento]]), MONTH(Tab_Faturamento_RJ[[#This Row],[Mês de referência para faturamento]]) + 1, DAY(Tab_Faturamento_RJ[[#This Row],[Mês de referência para faturamento]]) ) )} -> 45962 | AJ70: =IFERROR(L70-M70,0) -> 0 | AK70: =AC70-AD70 -> 0 | AL70: =K70-V70 -> 0 | AN70: kaike.costa@atlasinovacoes.com.br
D71: Bangu Shopping | E71: Prensa | F71: Verzani | G71: 1 | H71: 1 | V71: =IFERROR((K71+M71+R71+S71+T71+O71)+IF(U71="Sim",P71+Q71,0),(K71+R71+S71+T71)+IF(U71="Sim",P71+Q71,0)) -> 0 | AA71: 45962 | AB71: {=IFERROR( IF( _xlfn.XLOOKUP( 1, ( ('Condições de Faturamento'!$C$2:$C$1000 = Tab_Faturamento_RJ[[#This Row],[Unidade]]) * ('Condições de Faturamento'!$D$2:$D$1000 = Tab_Faturamento_RJ[[#This Row],[Categoria]]) * ('Condições de Faturamento'!$E$2:$E$1000 = Tab_Faturamento_RJ[[#This Row],[Fornecedor]]) ), 'Condições de Faturamento'!$F$2:$F$1000 ) = "Emissão no mês da prestação do serviço", Tab_Faturamento_RJ[[#This Row],[Mês de referência para faturamento]], DATE( YEAR(Tab_Faturamento_RJ[[#This Row],[Mês de referência para faturamento]]), MONTH(Tab_Faturamento_RJ[[#This Row],[Mês de referência para faturamento]]) + 1, DAY(Tab_Faturamento_RJ[[#This Row],[Mês de referência para faturamento]]) ) ), DATE( YEAR(Tab_Faturamento_RJ[[#This Row],[Mês de referência para faturamento]]), MONTH(Tab_Faturamento_RJ[[#This Row],[Mês de referência para faturamento]]) + 1, DAY(Tab_Faturamento_RJ[[#This Row],[Mês de referência para faturamento]]) ) )} -> 45992 | AJ71: =IFERROR(L71-M71,0) -> 0 | AK71: =AC71-AD71 -> 0 | AL71: =K71-V71 -> 0 | AN71: kaike.costa@atlasinovacoes.com.br
D72: Bangu Shopping | E72: Prensa | F72: Verzani | G72: 1 | H72: 1 | V72: =IFERROR((K72+M72+R72+S72+T72+O72)+IF(U72="Sim",P72+Q72,0),(K72+R72+S72+T72)+IF(U72="Sim",P72+Q72,0)) -> 0 | AA72: 45992 | AB72: {=IFERROR( IF( _xlfn.XLOOKUP( 1, ( ('Condições de Faturamento'!$C$2:$C$1000 = Tab_Faturamento_RJ[[#This Row],[Unidade]]) * ('Condições de Faturamento'!$D$2:$D$1000 = Tab_Faturamento_RJ[[#This Row],[Categoria]]) * ('Condições de Faturamento'!$E$2:$E$1000 = Tab_Faturamento_RJ[[#This Row],[Fornecedor]]) ), 'Condições de Faturamento'!$F$2:$F$1000 ) = "Emissão no mês da prestação do serviço", Tab_Faturamento_RJ[[#This Row],[Mês de referência para faturamento]], DATE( YEAR(Tab_Faturamento_RJ[[#This Row],[Mês de referência para faturamento]]), MONTH(Tab_Faturamento_RJ[[#This Row],[Mês de referência para faturamento]]) + 1, DAY(Tab_Faturamento_RJ[[#This Row],[Mês de referência para faturamento]]) ) ), DATE( YEAR(Tab_Faturamento_RJ[[#This Row],[Mês de referência para faturamento]]), MONTH(Tab_Faturamento_RJ[[#This Row],[Mês de referência para faturamento]]) + 1, DAY(Tab_Faturamento_RJ[[#This Row],[Mês de referência para faturamento]]) ) )} -> 46023 | AJ72: =IFERROR(L72-M72,0) -> 0 | AK72: =AC72-AD72 -> 0 | AL72: =K72-V72 -> 0 | AN72: kaike.costa@atlasinovacoes.com.br
C73: Não | D73: Bangu Shopping | E73: Resíduos | F73: Verzani | G73: 2 | H73: 2 | I73: 0 | J73: 0 | K73: 11606.08 | L73: 0 | M73: 0 | N73: 0 | O73: 0 | P73: 0 | Q73: 0 | R73: 0 | S73: 0 | T73: 0 | U73: Não | V73: =IFERROR((K73+M73+R73+S73+T73+O73)+IF(U73="Sim",P73+Q73,0),(K73+R73+S73+T73)+IF(U73="Sim",P73+Q73,0)) -> 11606.08 | AA73: 45658 | AB73: {=IFERROR( IF( _xlfn.XLOOKUP( 1, ( ('Condições de Faturamento'!$C$2:$C$1000 = Tab_Faturamento_RJ[[#This Row],[Unidade]]) * ('Condições de Faturamento'!$D$2:$D$1000 = Tab_Faturamento_RJ[[#This Row],[Categoria]]) * ('Condições de Faturamento'!$E$2:$E$1000 = Tab_Faturamento_RJ[[#This Row],[Fornecedor]]) ), 'Condições de Faturamento'!$F$2:$F$1000 ) = "Emissão no mês da prestação do serviço", Tab_Faturamento_RJ[[#This Row],[Mês de referência para faturamento]], DATE( YEAR(Tab_Faturamento_RJ[[#This Row],[Mês de referência para faturamento]]), MONTH(Tab_Faturamento_RJ[[#This Row],[Mês de referência para faturamento]]) + 1, DAY(Tab_Faturamento_RJ[[#This Row],[Mês de referência para faturamento]]) ) ), DATE( YEAR(Tab_Faturamento_RJ[[#This Row],[Mês de referência para faturamento]]), MONTH(Tab_Faturamento_RJ[[#This Row],[Mês de referência para faturamento]]) + 1, DAY(Tab_Faturamento_RJ[[#This Row],[Mês de referência para faturamento]]) ) )} -> 45658 | AJ73: =IFERROR(L73-M73,0) -> 0 | AK73: =AC73-AD73 -> 0 | AL73: =K73-V73 -> 0 | AN73: kaike.costa@atlasinovacoes.com.br
C74: Sim | D74: Bangu Shopping | E74: Resíduos | F74: Verzani | G74: 2 | H74: 2 | I74: 0 | J74: 0 | K74: 11606.08 | L74: 0 | M74: 0 | N74: 0 | O74: 0 | P74: 0 | Q74: 0 | R74: 0 | S74: 0 | T74: 0 | U74: Não | V74: =IFERROR((K74+M74+R74+S74+T74+O74)+IF(U74="Sim",P74+Q74,0),(K74+R74+S74+T74)+IF(U74="Sim",P74+Q74,0)) -> 11606.08 | AA74: 45689 | AB74: {=IFERROR( IF( _xlfn.XLOOKUP( 1, ( ('Condições de Faturamento'!$C$2:$C$1000 = Tab_Faturamento_RJ[[#This Row],[Unidade]]) * ('Condições de Faturamento'!$D$2:$D$1000 = Tab_Faturamento_RJ[[#This Row],[Categoria]]) * ('Condições de Faturamento'!$E$2:$E$1000 = Tab_Faturamento_RJ[[#This Row],[Fornecedor]]) ), 'Condições de Faturamento'!$F$2:$F$1000 ) = "Emissão no mês da prestação do serviço", Tab_Faturamento_RJ[[#This Row],[Mês de referência para faturamento]], DATE( YEAR(Tab_Faturamento_RJ[[#This Row],[Mês de referência para faturamento]]), MONTH(Tab_Faturamento_RJ[[#This Row],[Mês de referência para faturamento]]) + 1, DAY(Tab_Faturamento_RJ[[#This Row],[Mês de referência para faturamento]]) ) ), DATE( YEAR(Tab_Faturamento_RJ[[#This Row],[Mês de referência para faturamento]]), MONTH(Tab_Faturamento_RJ[[#This Row],[Mês de referência para faturamento]]) + 1, DAY(Tab_Faturamento_RJ[[#This Row],[Mês de referência para faturamento]]) ) )} -> 45689 | AJ74: =IFERROR(L74-M74,0) -> 0 | AK74: =AC74-AD74 -> 0 | AL74: =K74-V74 -> 0 | AN74: kaike.costa@atlasinovacoes.com.br
C75: Sim | D75: Bangu Shopping | E75: Resíduos | F75: Verzani | G75: 2 | H75: 2 | I75: 0 | J75: 0 | K75: 11606.08 | L75: 0 | M75: 0 | N75: 0 | O75: 0 | P75: 0 | Q75: 0 | R75: 0 | S75: 0 | T75: 0 | U75: Sim | V75: =IFERROR((K75+M75+R75+S75+T75+O75)+IF(U75="Sim",P75+Q75,0),(K75+R75+S75+T75)+IF(U75="Sim",P75+Q75,0)) -> 11606.08 | AA75: 45717 | AB75: {=IFERROR( IF( _xlfn.XLOOKUP( 1, ( ('Condições de Faturamento'!$C$2:$C$1000 = Tab_Faturamento_RJ[[#This Row],[Unidade]]) * ('Condições de Faturamento'!$D$2:$D$1000 = Tab_Faturamento_RJ[[#This Row],[Categoria]]) * ('Condições de Faturamento'!$E$2:$E$1000 = Tab_Faturamento_RJ[[#This Row],[Fornecedor]]) ), 'Condições de Faturamento'!$F$2:$F$1000 ) = "Emissão no mês da prestação do serviço", Tab_Faturamento_RJ[[#This Row],[Mês de referência para faturamento]], DATE( YEAR(Tab_Faturamento_RJ[[#This Row],[Mês de referência para faturamento]]), MONTH(Tab_Faturamento_RJ[[#This Row],[Mês de referência para faturamento]]) + 1, DAY(Tab_Faturamento_RJ[[#This Row],[Mês de referência para faturamento]]) ) ), DATE( YEAR(Tab_Faturamento_RJ[[#This Row],[Mês de referência para faturamento]]), MONTH(Tab_Faturamento_RJ[[#This Row],[Mês de referência para faturamento]]) + 1, DAY(Tab_Faturamento_RJ[[#This Row],[Mês de referência para faturamento]]) ) )} -> 45717 | AJ75: =IFERROR(L75-M75,0) -> 0 | AK75: =AC75-AD75 -> 0 | AL75: =K75-V75 -> 0 | AN75: kaike.costa@atlasinovacoes.com.br
B76: 45754 | C76: Sim | D76: Bangu Shopping | E76: Resíduos | F76: Verzani | G76: 2 | H76: 2 | I76: 0 | J76: 0 | K76: 11606.08 | L76: 0 | M76: 0 | N76: 0 | O76: 0 | P76: 0 | Q76: 0 | R76: 0 | S76: 0 | T76: 0 | V76: =IFERROR((K76+M76+R76+S76+T76+O76)+IF(U76="Sim",P76+Q76,0),(K76+R76+S76+T76)+IF(U76="Sim",P76+Q76,0)) -> 11606.08 | AA76: 45748 | AB76: {=IFERROR( IF( _xlfn.XLOOKUP( 1, ( ('Condições de Faturamento'!$C$2:$C$1000 = Tab_Faturamento_RJ[[#This Row],[Unidade]]) * ('Condições de Faturamento'!$D$2:$D$1000 = Tab_Faturamento_RJ[[#This Row],[Categoria]]) * ('Condições de Faturamento'!$E$2:$E$1000 = Tab_Faturamento_RJ[[#This Row],[Fornecedor]]) ), 'Condições de Faturamento'!$F$2:$F$1000 ) = "Emissão no mês da prestação do serviço", Tab_Faturamento_RJ[[#This Row],[Mês de referência para faturamento]], DATE( YEAR(Tab_Faturamento_RJ[[#This Row],[Mês de referência para faturamento]]), MONTH(Tab_Faturamento_RJ[[#This Row],[Mês de referência para faturamento]]) + 1, DAY(Tab_Faturamento_RJ[[#This Row],[Mês de referência para faturamento]]) ) ), DATE( YEAR(Tab_Faturamento_RJ[[#This Row],[Mês de referência para faturamento]]), MONTH(Tab_Faturamento_RJ[[#This Row],[Mês de referência para faturamento]]) + 1, DAY(Tab_Faturamento_RJ[[#This Row],[Mês de referência para faturamento]]) ) )} -> 45748 | AJ76: =IFERROR(L76-M76,0) -> 0 | AK76: =AC76-AD76 -> 0 | AL76: =K76-V76 -> 0 | AN76: kaike.costa@atlasinovacoes.com.br
B77: 45789 | C77: Sim | D77: Bangu Shopping | E77: Resíduos | F77: Verzani | G77: 2 | H77: 2 | I77: 0 | J77: 0 | K77: 11606.08 | L77: 0 | M77: 0 | N77: 0 | O77: 0 | P77: 0 | Q77: 0 | R77: 0 | S77: 0 | T77: 0 | U77: Não | V77: =IFERROR((K77+M77+R77+S77+T77+O77)+IF(U77="Sim",P77+Q77,0),(K77+R77+S77+T77)+IF(U77="Sim",P77+Q77,0)) -> 11606.08 | Y77: =2565.17176354316/4 -> 641.29294 | Z77: 1|4 | AA77: 45778 | AB77: {=IFERROR( IF( _xlfn.XLOOKUP( 1, ( ('Condições de Faturamento'!$C$2:$C$1000 = Tab_Faturamento_RJ[[#This Row],[Unidade]]) * ('Condições de Faturamento'!$D$2:$D$1000 = Tab_Faturamento_RJ[[#This Row],[Categoria]]) * ('Condições de Faturamento'!$E$2:$E$1000 = Tab_Faturamento_RJ[[#This Row],[Fornecedor]]) ), 'Condições de Faturamento'!$F$2:$F$1000 ) = "Emissão no mês da prestação do serviço", Tab_Faturamento_RJ[[#This Row],[Mês de referência para faturamento]], DATE( YEAR(Tab_Faturamento_RJ[[#This Row],[Mês de referência para faturamento]]), MONTH(Tab_Faturamento_RJ[[#This Row],[Mês de referência para faturamento]]) + 1, DAY(Tab_Faturamento_RJ[[#This Row],[Mês de referência para faturamento]]) ) ), DATE( YEAR(Tab_Faturamento_RJ[[#This Row],[Mês de referência para faturamento]]), MONTH(Tab_Faturamento_RJ[[#This Row],[Mês de referência para faturamento]]) + 1, DAY(Tab_Faturamento_RJ[[#This Row],[Mês de referência para faturamento]]) ) )} -> 45778 | AJ77: =IFERROR(L77-M77,0) -> 0 | AK77: =AC77-AD77 -> 0 | AL77: =K77-V77 -> 0 | AN77: kaike.costa@atlasinovacoes.com.br
B78: 45818 | C78: Sim | D78: Bangu Shopping | E78: Resíduos | F78: Verzani | G78: 2 | H78: 2 | I78: 0 | J78: 0 | K78: 12461.142 | L78: 0 | M78: 0 | N78: 0 | O78: 0 | P78: 0 | Q78: 0 | R78: 0 | S78: 0 | T78: 0 | U78: Sim | V78: =IFERROR((K78+M78+R78+S78+T78+O78)+IF(U78="Sim",P78+Q78,0),(K78+R78+S78+T78)+IF(U78="Sim",P78+Q78,0)) -> 12461.142 | Y78: =2565.17176354316/4 -> 641.29294 | Z78: 2|4 | AA78: 45809 | AB78: {=IFERROR( IF( _xlfn.XLOOKUP( 1, ( ('Condições de Faturamento'!$C$2:$C$1000 = Tab_Faturamento_RJ[[#This Row],[Unidade]]) * ('Condições de Faturamento'!$D$2:$D$1000 = Tab_Faturamento_RJ[[#This Row],[Categoria]]) * ('Condições de Faturamento'!$E$2:$E$1000 = Tab_Faturamento_RJ[[#This Row],[Fornecedor]]) ), 'Condições de Faturamento'!$F$2:$F$1000 ) = "Emissão no mês da prestação do serviço", Tab_Faturamento_RJ[[#This Row],[Mês de referência para faturamento]], DATE( YEAR(Tab_Faturamento_RJ[[#This Row],[Mês de referência para faturamento]]), MONTH(Tab_Faturamento_RJ[[#This Row],[Mês de referência para faturamento]]) + 1, DAY(Tab_Faturamento_RJ[[#This Row],[Mês de referência para faturamento]]) ) ), DATE( YEAR(Tab_Faturamento_RJ[[#This Row],[Mês de referência para faturamento]]), MONTH(Tab_Faturamento_RJ[[#This Row],[Mês de referência para faturamento]]) + 1, DAY(Tab_Faturamento_RJ[[#This Row],[Mês de referência para faturamento]]) ) )} -> 45809 | AJ78: =IFERROR(L78-M78,0) -> 0 | AK78: =AC78-AD78 -> 0 | AL78: =K78-V78 -> 0 | AN78: kaike.costa@atlasinovacoes.com.br
B79: 45887 | C79: Sim | D79: Bangu Shopping | E79: Vigilância | F79: GPS | G79: 20 | H79: 20 | I79: 0 | J79: 0 | K79: 133633.18 | L79: 0 | M79: 0 | N79: 0 | O79: 0 | P79: 0 | Q79: 0 | R79: 0 | S79: 0 | T79: 0 | U79: Sim | V79: =IFERROR((K79+M79+R79+S79+T79+O79)+IF(U79="Sim",P79+Q79,0),(K79+R79+S79+T79)+IF(U79="Sim",P79+Q79,0)) -> 133633.18 | Y79: =11183.19/2 -> 5591.595 | Z79: 1|2 | AA79: 45839 | AB79: {=IFERROR( IF( _xlfn.XLOOKUP( 1, ( ('Condições de Faturamento'!$C$2:$C$1000 = Tab_Faturamento_RJ[[#This Row],[Unidade]]) * ('Condições de Faturamento'!$D$2:$D$1000 = Tab_Faturamento_RJ[[#This Row],[Categoria]]) * ('Condições de Faturamento'!$E$2:$E$1000 = Tab_Faturamento_RJ[[#This Row],[Fornecedor]]) ), 'Condições de Faturamento'!$F$2:$F$1000 ) = "Emissão no mês da prestação do serviço", Tab_Faturamento_RJ[[#This Row],[Mês de referência para faturamento]], DATE( YEAR(Tab_Faturamento_RJ[[#This Row],[Mês de referência para faturamento]]), MONTH(Tab_Faturamento_RJ[[#This Row],[Mês de referência para faturamento]]) + 1, DAY(Tab_Faturamento_RJ[[#This Row],[Mês de referência para faturamento]]) ) ), DATE( YEAR(Tab_Faturamento_RJ[[#This Row],[Mês de referência para faturamento]]), MONTH(Tab_Faturamento_RJ[[#This Row],[Mês de referência para faturamento]]) + 1, DAY(Tab_Faturamento_RJ[[#This Row],[Mês de referência para faturamento]]) ) )} -> 45839 | AJ79: =IFERROR(L79-M79,0) -> 0 | AK79: =AC79-AD79 -> 0 | AL79: =K79-V79 -> 0 | AN79: kaike.costa@atlasinovacoes.com.br
B80: 45877 | C80: Sim | D80: Bangu Shopping | E80: Resíduos | F80: Verzani | G80: 3 | H80: 2 | I80: 0 | J80: 0 | K80: 12461.142 | L80: 0 | M80: 0 | N80: 0 | O80: 0 | P80: 0 | Q80: 0 | R80: 0 | S80: 0 | T80: 0 | U80: Sim | V80: =IFERROR((K80+M80+R80+S80+T80+O80)+IF(U80="Sim",P80+Q80,0),(K80+R80+S80+T80)+IF(U80="Sim",P80+Q80,0)) -> 12461.142 | Y80: =2565.17176354316/4 -> 641.29294 | Z80: 4|4 | AA80: 45870 | AB80: {=IFERROR( IF( _xlfn.XLOOKUP( 1, ( ('Condições de Faturamento'!$C$2:$C$1000 = Tab_Faturamento_RJ[[#This Row],[Unidade]]) * ('Condições de Faturamento'!$D$2:$D$1000 = Tab_Faturamento_RJ[[#This Row],[Categoria]]) * ('Condições de Faturamento'!$E$2:$E$1000 = Tab_Faturamento_RJ[[#This Row],[Fornecedor]]) ), 'Condições de Faturamento'!$F$2:$F$1000 ) = "Emissão no mês da prestação do serviço", Tab_Faturamento_RJ[[#This Row],[Mês de referência para faturamento]], DATE( YEAR(Tab_Faturamento_RJ[[#This Row],[Mês de referência para faturamento]]), MONTH(Tab_Faturamento_RJ[[#This Row],[Mês de referência para faturamento]]) + 1, DAY(Tab_Faturamento_RJ[[#This Row],[Mês de referência para faturamento]]) ) ), DATE( YEAR(Tab_Faturamento_RJ[[#This Row],[Mês de referência para faturamento]]), MONTH(Tab_Faturamento_RJ[[#This Row],[Mês de referência para faturamento]]) + 1, DAY(Tab_Faturamento_RJ[[#This Row],[Mês de referência para faturamento]]) ) )} -> 45870 | AJ80: =IFERROR(L80-M80,0) -> 0 | AK80: =AC80-AD80 -> 0 | AL80: =K80-V80 -> 0 | AN80: kaike.costa@atlasinovacoes.com.br
B81: 45908 | C81: Sim | D81: Bangu Shopping | E81: Resíduos | F81: Verzani | G81: 3 | H81: 2 | I81: 0 | J81: 0 | K81: 12461.142 | L81: 0 | M81: 0 | N81: 0 | O81: 0 | P81: 0 | Q81: 0 | R81: 0 | S81: 0 | T81: 0 | U81: Sim | V81: =IFERROR((K81+M81+R81+S81+T81+O81)+IF(U81="Sim",P81+Q81,0),(K81+R81+S81+T81)+IF(U81="Sim",P81+Q81,0)) -> 12461.142 | AA81: 45901 | AB81: {=IFERROR( IF( _xlfn.XLOOKUP( 1, ( ('Condições de Faturamento'!$C$2:$C$1000 = Tab_Faturamento_RJ[[#This Row],[Unidade]]) * ('Condições de Faturamento'!$D$2:$D$1000 = Tab_Faturamento_RJ[[#This Row],[Categoria]]) * ('Condições de Faturamento'!$E$2:$E$1000 = Tab_Faturamento_RJ[[#This Row],[Fornecedor]]) ), 'Condições de Faturamento'!$F$2:$F$1000 ) = "Emissão no mês da prestação do serviço", Tab_Faturamento_RJ[[#This Row],[Mês de referência para faturamento]], DATE( YEAR(Tab_Faturamento_RJ[[#This Row],[Mês de referência para faturamento]]), MONTH(Tab_Faturamento_RJ[[#This Row],[Mês de referência para faturamento]]) + 1, DAY(Tab_Faturamento_RJ[[#This Row],[Mês de referência para faturamento]]) ) ), DATE( YEAR(Tab_Faturamento_RJ[[#This Row],[Mês de referência para faturamento]]), MONTH(Tab_Faturamento_RJ[[#This Row],[Mês de referência para faturamento]]) + 1, DAY(Tab_Faturamento_RJ[[#This Row],[Mês de referência para faturamento]]) ) )} -> 45901 | AJ81: =IFERROR(L81-M81,0) -> 0 | AK81: =AC81-AD81 -> 0 | AL81: =K81-V81 -> 0 | AN81: kaike.costa@atlasinovacoes.com.br
B82: 45931 | C82: Sim | D82: Bangu Shopping | E82: Resíduos | F82: Verzani | G82: 3 | H82: 2 | I82: 0 | J82: 0 | K82: =(K81/30.44)*10 -> 4093.6733 | M82: 0 | O82: 0 | P82: 0 | Q82: 0 | R82: 0 | S82: 0 | T82: 0 | U82: Sim | V82: =IFERROR((K82+M82+R82+S82+T82+O82)+IF(U82="Sim",P82+Q82,0),(K82+R82+S82+T82)+IF(U82="Sim",P82+Q82,0)) -> 4093.6733 | AA82: 45931 | AB82: {=IFERROR( IF( _xlfn.XLOOKUP( 1, ( ('Condições de Faturamento'!$C$2:$C$1000 = Tab_Faturamento_RJ[[#This Row],[Unidade]]) * ('Condições de Faturamento'!$D$2:$D$1000 = Tab_Faturamento_RJ[[#This Row],[Categoria]]) * ('Condições de Faturamento'!$E$2:$E$1000 = Tab_Faturamento_RJ[[#This Row],[Fornecedor]]) ), 'Condições de Faturamento'!$F$2:$F$1000 ) = "Emissão no mês da prestação do serviço", Tab_Faturamento_RJ[[#This Row],[Mês de referência para faturamento]], DATE( YEAR(Tab_Faturamento_RJ[[#This Row],[Mês de referência para faturamento]]), MONTH(Tab_Faturamento_RJ[[#This Row],[Mês de referência para faturamento]]) + 1, DAY(Tab_Faturamento_RJ[[#This Row],[Mês de referência para faturamento]]) ) ), DATE( YEAR(Tab_Faturamento_RJ[[#This Row],[Mês de referência para faturamento]]), MONTH(Tab_Faturamento_RJ[[#This Row],[Mês de referência para faturamento]]) + 1, DAY(Tab_Faturamento_RJ[[#This Row],[Mês de referência para faturamento]]) ) )} -> 45931 | AJ82: =IFERROR(L82-M82,0) -> 0 | AK82: =AC82-AD82 -> 0 | AL82: =K82-V82 -> 0 | AN82: kaike.costa@atlasinovacoes.com.br
D83: Bangu Shopping | E83: Resíduos | F83: Verzani | G83: 3 | V83: =IFERROR((K83+M83+R83+S83+T83+O83)+IF(U83="Sim",P83+Q83,0),(K83+R83+S83+T83)+IF(U83="Sim",P83+Q83,0)) -> 0 | AA83: 45962 | AB83: {=IFERROR( IF( _xlfn.XLOOKUP( 1, ( ('Condições de Faturamento'!$C$2:$C$1000 = Tab_Faturamento_RJ[[#This Row],[Unidade]]) * ('Condições de Faturamento'!$D$2:$D$1000 = Tab_Faturamento_RJ[[#This Row],[Categoria]]) * ('Condições de Faturamento'!$E$2:$E$1000 = Tab_Faturamento_RJ[[#This Row],[Fornecedor]]) ), 'Condições de Faturamento'!$F$2:$F$1000 ) = "Emissão no mês da prestação do serviço", Tab_Faturamento_RJ[[#This Row],[Mês de referência para faturamento]], DATE( YEAR(Tab_Faturamento_RJ[[#This Row],[Mês de referência para faturamento]]), MONTH(Tab_Faturamento_RJ[[#This Row],[Mês de referência para faturamento]]) + 1, DAY(Tab_Faturamento_RJ[[#This Row],[Mês de referência para faturamento]]) ) ), DATE( YEAR(Tab_Faturamento_RJ[[#This Row],[Mês de referência para faturamento]]), MONTH(Tab_Faturamento_RJ[[#This Row],[Mês de referência para faturamento]]) + 1, DAY(Tab_Faturamento_RJ[[#This Row],[Mês de referência para faturamento]]) ) )} -> 45962 | AJ83: =IFERROR(L83-M83,0) -> 0 | AK83: =AC83-AD83 -> 0 | AL83: =K83-V83 -> 0 | AN83: kaike.costa@atlasinovacoes.com.br
D84: Bangu Shopping | E84: Resíduos | F84: Verzani | G84: 3 | V84: =IFERROR((K84+M84+R84+S84+T84+O84)+IF(U84="Sim",P84+Q84,0),(K84+R84+S84+T84)+IF(U84="Sim",P84+Q84,0)) -> 0 | AA84: 45992 | AB84: {=IFERROR( IF( _xlfn.XLOOKUP( 1, ( ('Condições de Faturamento'!$C$2:$C$1000 = Tab_Faturamento_RJ[[#This Row],[Unidade]]) * ('Condições de Faturamento'!$D$2:$D$1000 = Tab_Faturamento_RJ[[#This Row],[Categoria]]) * ('Condições de Faturamento'!$E$2:$E$1000 = Tab_Faturamento_RJ[[#This Row],[Fornecedor]]) ), 'Condições de Faturamento'!$F$2:$F$1000 ) = "Emissão no mês da prestação do serviço", Tab_Faturamento_RJ[[#This Row],[Mês de referência para faturamento]], DATE( YEAR(Tab_Faturamento_RJ[[#This Row],[Mês de referência para faturamento]]), MONTH(Tab_Faturamento_RJ[[#This Row],[Mês de referência para faturamento]]) + 1, DAY(Tab_Faturamento_RJ[[#This Row],[Mês de referência para faturamento]]) ) ), DATE( YEAR(Tab_Faturamento_RJ[[#This Row],[Mês de referência para faturamento]]), MONTH(Tab_Faturamento_RJ[[#This Row],[Mês de referência para faturamento]]) + 1, DAY(Tab_Faturamento_RJ[[#This Row],[Mês de referência para faturamento]]) ) )} -> 45992 | AJ84: =IFERROR(L84-M84,0) -> 0 | AK84: =AC84-AD84 -> 0 | AL84: =K84-V84 -> 0 | AN84: kaike.costa@atlasinovacoes.com.br
C85: Não | D85: Bangu Shopping | E85: Vigilância | F85: GPS | G85: 20 | H85: 20 | I85: Informação pendente | J85: Informação pendente | K85: 128079.26 | L85: 0 | M85: Informação pendente | N85: 0 | O85: Informação pendente | P85: 0 | Q85: 0 | R85: 0 | S85: 0 | T85: 0 | V85: =IFERROR((K85+M85+R85+S85+T85+O85)+IF(U85="Sim",P85+Q85,0),(K85+R85+S85+T85)+IF(U85="Sim",P85+Q85,0)) -> 128079.26 | AA85: 45658 | AB85: {=IFERROR( IF( _xlfn.XLOOKUP( 1, ( ('Condições de Faturamento'!$C$2:$C$1000 = Tab_Faturamento_RJ[[#This Row],[Unidade]]) * ('Condições de Faturamento'!$D$2:$D$1000 = Tab_Faturamento_RJ[[#This Row],[Categoria]]) * ('Condições de Faturamento'!$E$2:$E$1000 = Tab_Faturamento_RJ[[#This Row],[Fornecedor]]) ), 'Condições de Faturamento'!$F$2:$F$1000 ) = "Emissão no mês da prestação do serviço", Tab_Faturamento_RJ[[#This Row],[Mês de referência para faturamento]], DATE( YEAR(Tab_Faturamento_RJ[[#This Row],[Mês de referência para faturamento]]), MONTH(Tab_Faturamento_RJ[[#This Row],[Mês de referência para faturamento]]) + 1, DAY(Tab_Faturamento_RJ[[#This Row],[Mês de referência para faturamento]]) ) ), DATE( YEAR(Tab_Faturamento_RJ[[#This Row],[Mês de referência para faturamento]]), MONTH(Tab_Faturamento_RJ[[#This Row],[Mês de referência para faturamento]]) + 1, DAY(Tab_Faturamento_RJ[[#This Row],[Mês de referência para faturamento]]) ) )} -> 45658 | AJ85: =IFERROR(L85-M85,0) -> 0 | AK85: =AC85-AD85 -> 0 | AL85: =K85-V85 -> 0 | AN85: kaike.costa@atlasinovacoes.com.br
C86: Não | D86: Bangu Shopping | E86: Vigilância | F86: GPS | G86: 20 | H86: 20 | I86: Informação pendente | J86: Informação pendente | K86: 128079.26 | L86: 0 | M86: Informação pendente | N86: 0 | O86: Informação pendente | P86: 0 | Q86: 0 | R86: 0 | S86: 0 | T86: 0 | V86: =IFERROR((K86+M86+R86+S86+T86+O86)+IF(U86="Sim",P86+Q86,0),(K86+R86+S86+T86)+IF(U86="Sim",P86+Q86,0)) -> 128079.26 | AA86: 45689 | AB86: {=IFERROR( IF( _xlfn.XLOOKUP( 1, ( ('Condições de Faturamento'!$C$2:$C$1000 = Tab_Faturamento_RJ[[#This Row],[Unidade]]) * ('Condições de Faturamento'!$D$2:$D$1000 = Tab_Faturamento_RJ[[#This Row],[Categoria]]) * ('Condições de Faturamento'!$E$2:$E$1000 = Tab_Faturamento_RJ[[#This Row],[Fornecedor]]) ), 'Condições de Faturamento'!$F$2:$F$1000 ) = "Emissão no mês da prestação do serviço", Tab_Faturamento_RJ[[#This Row],[Mês de referência para faturamento]], DATE( YEAR(Tab_Faturamento_RJ[[#This Row],[Mês de referência para faturamento]]), MONTH(Tab_Faturamento_RJ[[#This Row],[Mês de referência para faturamento]]) + 1, DAY(Tab_Faturamento_RJ[[#This Row],[Mês de referência para faturamento]]) ) ), DATE( YEAR(Tab_Faturamento_RJ[[#This Row],[Mês de referência para faturamento]]), MONTH(Tab_Faturamento_RJ[[#This Row],[Mês de referência para faturamento]]) + 1, DAY(Tab_Faturamento_RJ[[#This Row],[Mês de referência para faturamento]]) ) )} -> 45689 | AJ86: =IFERROR(L86-M86,0) -> 0 | AK86: =AC86-AD86 -> 0 | AL86: =K86-V86 -> 0 | AN86: kaike.costa@atlasinovacoes.com.br
C87: Não | D87: Bangu Shopping | E87: Vigilância | F87: GPS | G87: 20 | H87: 20 | I87: 0 | J87: 0 | K87: 133633.18 | L87: 0 | M87: 0 | N87: 0 | O87: 0 | P87: 0 | Q87: 0 | R87: 0 | S87: 0 | T87: 0 | U87: Sim | V87: =IFERROR((K87+M87+R87+S87+T87+O87)+IF(U87="Sim",P87+Q87,0),(K87+R87+S87+T87)+IF(U87="Sim",P87+Q87,0)) -> 133633.18 | AA87: 45717 | AB87: {=IFERROR( IF( _xlfn.XLOOKUP( 1, ( ('Condições de Faturamento'!$C$2:$C$1000 = Tab_Faturamento_RJ[[#This Row],[Unidade]]) * ('Condições de Faturamento'!$D$2:$D$1000 = Tab_Faturamento_RJ[[#This Row],[Categoria]]) * ('Condições de Faturamento'!$E$2:$E$1000 = Tab_Faturamento_RJ[[#This Row],[Fornecedor]]) ), 'Condições de Faturamento'!$F$2:$F$1000 ) = "Emissão no mês da prestação do serviço", Tab_Faturamento_RJ[[#This Row],[Mês de referência para faturamento]], DATE( YEAR(Tab_Faturamento_RJ[[#This Row],[Mês de referência para faturamento]]), MONTH(Tab_Faturamento_RJ[[#This Row],[Mês de referência para faturamento]]) + 1, DAY(Tab_Faturamento_RJ[[#This Row],[Mês de referência para faturamento]]) ) ), DATE( YEAR(Tab_Faturamento_RJ[[#This Row],[Mês de referência para faturamento]]), MONTH(Tab_Faturamento_RJ[[#This Row],[Mês de referência para faturamento]]) + 1, DAY(Tab_Faturamento_RJ[[#This Row],[Mês de referência para faturamento]]) ) )} -> 45717 | AC87: 4491.37 | AD87: 4491.37 | AJ87: =IFERROR(L87-M87,0) -> 0 | AK87: =AC87-AD87 -> 0 | AL87: =K87-V87 -> 0 | AN87: kaike.costa@atlasinovacoes.com.br
C88: Não | D88: Bangu Shopping | E88: Vigilância | F88: GPS | G88: 20 | H88: 20 | I88: 0 | J88: 0 | K88: 133633.18 | L88: 0 | M88: 0 | N88: 0 | O88: 0 | P88: 0 | Q88: 0 | R88: 0 | S88: 0 | T88: 0 | V88: =IFERROR((K88+M88+R88+S88+T88+O88)+IF(U88="Sim",P88+Q88,0),(K88+R88+S88+T88)+IF(U88="Sim",P88+Q88,0)) -> 133633.18 | AA88: 45748 | AB88: {=IFERROR( IF( _xlfn.XLOOKUP( 1, ( ('Condições de Faturamento'!$C$2:$C$1000 = Tab_Faturamento_RJ[[#This Row],[Unidade]]) * ('Condições de Faturamento'!$D$2:$D$1000 = Tab_Faturamento_RJ[[#This Row],[Categoria]]) * ('Condições de Faturamento'!$E$2:$E$1000 = Tab_Faturamento_RJ[[#This Row],[Fornecedor]]) ), 'Condições de Faturamento'!$F$2:$F$1000 ) = "Emissão no mês da prestação do serviço", Tab_Faturamento_RJ[[#This Row],[Mês de referência para faturamento]], DATE( YEAR(Tab_Faturamento_RJ[[#This Row],[Mês de referência para faturamento]]), MONTH(Tab_Faturamento_RJ[[#This Row],[Mês de referência para faturamento]]) + 1, DAY(Tab_Faturamento_RJ[[#This Row],[Mês de referência para faturamento]]) ) ), DATE( YEAR(Tab_Faturamento_RJ[[#This Row],[Mês de referência para faturamento]]), MONTH(Tab_Faturamento_RJ[[#This Row],[Mês de referência para faturamento]]) + 1, DAY(Tab_Faturamento_RJ[[#This Row],[Mês de referência para faturamento]]) ) )} -> 45748 | AJ88: =IFERROR(L88-M88,0) -> 0 | AK88: =AC88-AD88 -> 0 | AL88: =K88-V88 -> 0 | AN88: kaike.costa@atlasinovacoes.com.br
C89: Não | D89: Bangu Shopping | E89: Vigilância | F89: GPS | G89: 20 | H89: 20 | I89: Informação pendente | J89: Informação pendente | K89: 133633.18 | L89: 0 | M89: Informação pendente | N89: 0 | O89: Informação pendente | P89: 0 | Q89: 0 | R89: 0 | S89: 0 | T89: 0 | V89: =IFERROR((K89+M89+R89+S89+T89+O89)+IF(U89="Sim",P89+Q89,0),(K89+R89+S89+T89)+IF(U89="Sim",P89+Q89,0)) -> 133633.18 | Y89: =11183.19/2 -> 5591.595 | Z89: 2|2 | AA89: 45870 | AB89: {=IFERROR( IF( _xlfn.XLOOKUP( 1, ( ('Condições de Faturamento'!$C$2:$C$1000 = Tab_Faturamento_RJ[[#This Row],[Unidade]]) * ('Condições de Faturamento'!$D$2:$D$1000 = Tab_Faturamento_RJ[[#This Row],[Categoria]]) * ('Condições de Faturamento'!$E$2:$E$1000 = Tab_Faturamento_RJ[[#This Row],[Fornecedor]]) ), 'Condições de Faturamento'!$F$2:$F$1000 ) = "Emissão no mês da prestação do serviço", Tab_Faturamento_RJ[[#This Row],[Mês de referência para faturamento]], DATE( YEAR(Tab_Faturamento_RJ[[#This Row],[Mês de referência para faturamento]]), MONTH(Tab_Faturamento_RJ[[#This Row],[Mês de referência para faturamento]]) + 1, DAY(Tab_Faturamento_RJ[[#This Row],[Mês de referência para faturamento]]) ) ), DATE( YEAR(Tab_Faturamento_RJ[[#This Row],[Mês de referência para faturamento]]), MONTH(Tab_Faturamento_RJ[[#This Row],[Mês de referência para faturamento]]) + 1, DAY(Tab_Faturamento_RJ[[#This Row],[Mês de referência para faturamento]]) ) )} -> 45870 | AJ89: =IFERROR(L89-M89,0) -> 0 | AK89: =AC89-AD89 -> 0 | AL89: =K89-V89 -> 0 | AN89: kaike.costa@atlasinovacoes.com.br
C90: Não | D90: Bangu Shopping | E90: Vigilância | F90: GPS | G90: 20 | H90: 20 | I90: 0 | J90: 0 | K90: 133633.18 | L90: 0 | M90: 0 | N90: 0 | O90: 0 | P90: 0 | Q90: 0 | R90: 0 | S90: 0 | T90: 0 | U90: Não | V90: =IFERROR((K90+M90+R90+S90+T90+O90)+IF(U90="Sim",P90+Q90,0),(K90+R90+S90+T90)+IF(U90="Sim",P90+Q90,0)) -> 133633.18 | AA90: 45778 | AB90: {=IFERROR( IF( _xlfn.XLOOKUP( 1, ( ('Condições de Faturamento'!$C$2:$C$1000 = Tab_Faturamento_RJ[[#This Row],[Unidade]]) * ('Condições de Faturamento'!$D$2:$D$1000 = Tab_Faturamento_RJ[[#This Row],[Categoria]]) * ('Condições de Faturamento'!$E$2:$E$1000 = Tab_Faturamento_RJ[[#This Row],[Fornecedor]]) ), 'Condições de Faturamento'!$F$2:$F$1000 ) = "Emissão no mês da prestação do serviço", Tab_Faturamento_RJ[[#This Row],[Mês de referência para faturamento]], DATE( YEAR(Tab_Faturamento_RJ[[#This Row],[Mês de referência para faturamento]]), MONTH(Tab_Faturamento_RJ[[#This Row],[Mês de referência para faturamento]]) + 1, DAY(Tab_Faturamento_RJ[[#This Row],[Mês de referência para faturamento]]) ) ), DATE( YEAR(Tab_Faturamento_RJ[[#This Row],[Mês de referência para faturamento]]), MONTH(Tab_Faturamento_RJ[[#This Row],[Mês de referência para faturamento]]) + 1, DAY(Tab_Faturamento_RJ[[#This Row],[Mês de referência para faturamento]]) ) )} -> 45778 | AJ90: =IFERROR(L90-M90,0) -> 0 | AK90: =AC90-AD90 -> 0 | AL90: =K90-V90 -> 0 | AN90: kaike.costa@atlasinovacoes.com.br
C91: Não | D91: Bangu Shopping | E91: Vigilância | F91: GPS | G91: 20 | H91: 20 | I91: Informação pendente | J91: Informação pendente | K91: 133633.18 | L91: 0 | M91: Informação pendente | N91: 0 | O91: Informação pendente | P91: Preenchimento pendente | Q91: 0 | R91: 0 | S91: 0 | T91: 0 | U91: Não | V91: =IFERROR((K91+M91+R91+S91+T91+O91)+IF(U91="Sim",P91+Q91,0),(K91+R91+S91+T91)+IF(U91="Sim",P91+Q91,0)) -> 133633.18 | AA91: 45809 | AB91: {=IFERROR( IF( _xlfn.XLOOKUP( 1, ( ('Condições de Faturamento'!$C$2:$C$1000 = Tab_Faturamento_RJ[[#This Row],[Unidade]]) * ('Condições de Faturamento'!$D$2:$D$1000 = Tab_Faturamento_RJ[[#This Row],[Categoria]]) * ('Condições de Faturamento'!$E$2:$E$1000 = Tab_Faturamento_RJ[[#This Row],[Fornecedor]]) ), 'Condições de Faturamento'!$F$2:$F$1000 ) = "Emissão no mês da prestação do serviço", Tab_Faturamento_RJ[[#This Row],[Mês de referência para faturamento]], DATE( YEAR(Tab_Faturamento_RJ[[#This Row],[Mês de referência para faturamento]]), MONTH(Tab_Faturamento_RJ[[#This Row],[Mês de referência para faturamento]]) + 1, DAY(Tab_Faturamento_RJ[[#This Row],[Mês de referência para faturamento]]) ) ), DATE( YEAR(Tab_Faturamento_RJ[[#This Row],[Mês de referência para faturamento]]), MONTH(Tab_Faturamento_RJ[[#This Row],[Mês de referência para faturamento]]) + 1, DAY(Tab_Faturamento_RJ[[#This Row],[Mês de referência para faturamento]]) ) )} -> 45809 | AJ91: =IFERROR(L91-M91,0) -> 0 | AK91: =AC91-AD91 -> 0 | AL91: =K91-V91 -> 0 | AN91: kaike.costa@atlasinovacoes.com.br
B92: 45874 | C92: Sim | D92: Carioca Shopping | E92: Resíduos | F92: Nova Rio | G92: 6 | H92: 6 | I92: 0 | J92: 0 | K92: 34666.01 | L92: 0 | M92: 0 | N92: 0 | O92: 0 | P92: 0 | Q92: 0 | R92: 0 | S92: 0 | T92: 0 | V92: =IFERROR((K92+M92+R92+S92+T92+O92)+IF(U92="Sim",P92+Q92,0),(K92+R92+S92+T92)+IF(U92="Sim",P92+Q92,0)) -> 34666.01 | AA92: 45839 | AB92: {=IFERROR( IF( _xlfn.XLOOKUP( 1, ( ('Condições de Faturamento'!$C$2:$C$1000 = Tab_Faturamento_RJ[[#This Row],[Unidade]]) * ('Condições de Faturamento'!$D$2:$D$1000 = Tab_Faturamento_RJ[[#This Row],[Categoria]]) * ('Condições de Faturamento'!$E$2:$E$1000 = Tab_Faturamento_RJ[[#This Row],[Fornecedor]]) ), 'Condições de Faturamento'!$F$2:$F$1000 ) = "Emissão no mês da prestação do serviço", Tab_Faturamento_RJ[[#This Row],[Mês de referência para faturamento]], DATE( YEAR(Tab_Faturamento_RJ[[#This Row],[Mês de referência para faturamento]]), MONTH(Tab_Faturamento_RJ[[#This Row],[Mês de referência para faturamento]]) + 1, DAY(Tab_Faturamento_RJ[[#This Row],[Mês de referência para faturamento]]) ) ), DATE( YEAR(Tab_Faturamento_RJ[[#This Row],[Mês de referência para faturamento]]), MONTH(Tab_Faturamento_RJ[[#This Row],[Mês de referência para faturamento]]) + 1, DAY(Tab_Faturamento_RJ[[#This Row],[Mês de referência para faturamento]]) ) )} -> 45870 | AJ92: =IFERROR(L92-M92,0) -> 0 | AK92: =AC92-AD92 -> 0 | AL92: =K92-V92 -> 0 | AN92: kaike.costa@atlasinovacoes.com.br
C93: Não | D93: Bangu Shopping | E93: Vigilância | F93: GPS | G93: 20 | H93: 20 | I93: Informação pendente | J93: Informação pendente | K93: 133633.18 | L93: 0 | M93: Informação pendente | N93: 0 | O93: Informação pendente | P93: Preenchimento pendente | Q93: 0 | R93: 0 | S93: 0 | T93: 0 | V93: =IFERROR((K93+M93+R93+S93+T93+O93)+IF(U93="Sim",P93+Q93,0),(K93+R93+S93+T93)+IF(U93="Sim",P93+Q93,0)) -> 133633.18 | AA93: 45901 | AB93: {=IFERROR( IF( _xlfn.XLOOKUP( 1, ( ('Condições de Faturamento'!$C$2:$C$1000 = Tab_Faturamento_RJ[[#This Row],[Unidade]]) * ('Condições de Faturamento'!$D$2:$D$1000 = Tab_Faturamento_RJ[[#This Row],[Categoria]]) * ('Condições de Faturamento'!$E$2:$E$1000 = Tab_Faturamento_RJ[[#This Row],[Fornecedor]]) ), 'Condições de Faturamento'!$F$2:$F$1000 ) = "Emissão no mês da prestação do serviço", Tab_Faturamento_RJ[[#This Row],[Mês de referência para faturamento]], DATE( YEAR(Tab_Faturamento_RJ[[#This Row],[Mês de referência para faturamento]]), MONTH(Tab_Faturamento_RJ[[#This Row],[Mês de referência para faturamento]]) + 1, DAY(Tab_Faturamento_RJ[[#This Row],[Mês de referência para faturamento]]) ) ), DATE( YEAR(Tab_Faturamento_RJ[[#This Row],[Mês de referência para faturamento]]), MONTH(Tab_Faturamento_RJ[[#This Row],[Mês de referência para faturamento]]) + 1, DAY(Tab_Faturamento_RJ[[#This Row],[Mês de referência para faturamento]]) ) )} -> 45901 | AJ93: =IFERROR(L93-M93,0) -> 0 | AK93: =AC93-AD93 -> 0 | AL93: =K93-V93 -> 0 | AN93: kaike.costa@atlasinovacoes.com.br
C94: Não | D94: Bangu Shopping | E94: Vigilância | F94: GPS | G94: 20 | H94: 20 | I94: Informação pendente | J94: Informação pendente | K94: 133633.18 | M94: Informação pendente | O94: Informação pendente | P94: Preenchimento pendente | V94: =IFERROR((K94+M94+R94+S94+T94+O94)+IF(U94="Sim",P94+Q94,0),(K94+R94+S94+T94)+IF(U94="Sim",P94+Q94,0)) -> 133633.18 | AA94: 45931 | AB94: {=IFERROR( IF( _xlfn.XLOOKUP( 1, ( ('Condições de Faturamento'!$C$2:$C$1000 = Tab_Faturamento_RJ[[#This Row],[Unidade]]) * ('Condições de Faturamento'!$D$2:$D$1000 = Tab_Faturamento_RJ[[#This Row],[Categoria]]) * ('Condições de Faturamento'!$E$2:$E$1000 = Tab_Faturamento_RJ[[#This Row],[Fornecedor]]) ), 'Condições de Faturamento'!$F$2:$F$1000 ) = "Emissão no mês da prestação do serviço", Tab_Faturamento_RJ[[#This Row],[Mês de referência para faturamento]], DATE( YEAR(Tab_Faturamento_RJ[[#This Row],[Mês de referência para faturamento]]), MONTH(Tab_Faturamento_RJ[[#This Row],[Mês de referência para faturamento]]) + 1, DAY(Tab_Faturamento_RJ[[#This Row],[Mês de referência para faturamento]]) ) ), DATE( YEAR(Tab_Faturamento_RJ[[#This Row],[Mês de referência para faturamento]]), MONTH(Tab_Faturamento_RJ[[#This Row],[Mês de referência para faturamento]]) + 1, DAY(Tab_Faturamento_RJ[[#This Row],[Mês de referência para faturamento]]) ) )} -> 45931 | AJ94: =IFERROR(L94-M94,0) -> 0 | AK94: =AC94-AD94 -> 0 | AL94: =K94-V94 -> 0 | AN94: kaike.costa@atlasinovacoes.com.br
D95: Bangu Shopping | E95: Vigilância | F95: GPS | G95: 20 | V95: =IFERROR((K95+M95+R95+S95+T95+O95)+IF(U95="Sim",P95+Q95,0),(K95+R95+S95+T95)+IF(U95="Sim",P95+Q95,0)) -> 0 | AA95: 45962 | AB95: {=IFERROR( IF( _xlfn.XLOOKUP( 1, ( ('Condições de Faturamento'!$C$2:$C$1000 = Tab_Faturamento_RJ[[#This Row],[Unidade]]) * ('Condições de Faturamento'!$D$2:$D$1000 = Tab_Faturamento_RJ[[#This Row],[Categoria]]) * ('Condições de Faturamento'!$E$2:$E$1000 = Tab_Faturamento_RJ[[#This Row],[Fornecedor]]) ), 'Condições de Faturamento'!$F$2:$F$1000 ) = "Emissão no mês da prestação do serviço", Tab_Faturamento_RJ[[#This Row],[Mês de referência para faturamento]], DATE( YEAR(Tab_Faturamento_RJ[[#This Row],[Mês de referência para faturamento]]), MONTH(Tab_Faturamento_RJ[[#This Row],[Mês de referência para faturamento]]) + 1, DAY(Tab_Faturamento_RJ[[#This Row],[Mês de referência para faturamento]]) ) ), DATE( YEAR(Tab_Faturamento_RJ[[#This Row],[Mês de referência para faturamento]]), MONTH(Tab_Faturamento_RJ[[#This Row],[Mês de referência para faturamento]]) + 1, DAY(Tab_Faturamento_RJ[[#This Row],[Mês de referência para faturamento]]) ) )} -> 45962 | AJ95: =IFERROR(L95-M95,0) -> 0 | AK95: =AC95-AD95 -> 0 | AL95: =K95-V95 -> 0 | AN95: kaike.costa@atlasinovacoes.com.br
D96: Bangu Shopping | E96: Vigilância | F96: GPS | G96: 20 | V96: =IFERROR((K96+M96+R96+S96+T96+O96)+IF(U96="Sim",P96+Q96,0),(K96+R96+S96+T96)+IF(U96="Sim",P96+Q96,0)) -> 0 | AA96: 45992 | AB96: {=IFERROR( IF( _xlfn.XLOOKUP( 1, ( ('Condições de Faturamento'!$C$2:$C$1000 = Tab_Faturamento_RJ[[#This Row],[Unidade]]) * ('Condições de Faturamento'!$D$2:$D$1000 = Tab_Faturamento_RJ[[#This Row],[Categoria]]) * ('Condições de Faturamento'!$E$2:$E$1000 = Tab_Faturamento_RJ[[#This Row],[Fornecedor]]) ), 'Condições de Faturamento'!$F$2:$F$1000 ) = "Emissão no mês da prestação do serviço", Tab_Faturamento_RJ[[#This Row],[Mês de referência para faturamento]], DATE( YEAR(Tab_Faturamento_RJ[[#This Row],[Mês de referência para faturamento]]), MONTH(Tab_Faturamento_RJ[[#This Row],[Mês de referência para faturamento]]) + 1, DAY(Tab_Faturamento_RJ[[#This Row],[Mês de referência para faturamento]]) ) ), DATE( YEAR(Tab_Faturamento_RJ[[#This Row],[Mês de referência para faturamento]]), MONTH(Tab_Faturamento_RJ[[#This Row],[Mês de referência para faturamento]]) + 1, DAY(Tab_Faturamento_RJ[[#This Row],[Mês de referência para faturamento]]) ) )} -> 45992 | AJ96: =IFERROR(L96-M96,0) -> 0 | AK96: =AC96-AD96 -> 0 | AL96: =K96-V96 -> 0 | AN96: kaike.costa@atlasinovacoes.com.br
C97: Não | D97: Carioca Shopping | E97: Resíduos | F97: Nova Rio | G97: 6 | H97: 6 | I97: Informação pendente | J97: Informação pendente | K97: 32285.475 | L97: 0 | M97: Informação pendente | N97: 0 | O97: Informação pendente | P97: 0 | Q97: 0 | R97: 0 | S97: 0 | T97: 0 | V97: =IFERROR((K97+M97+R97+S97+T97+O97)+IF(U97="Sim",P97+Q97,0),(K97+R97+S97+T97)+IF(U97="Sim",P97+Q97,0)) -> 32285.475 | AA97: 45658 | AB97: {=IFERROR( IF( _xlfn.XLOOKUP( 1, ( ('Condições de Faturamento'!$C$2:$C$1000 = Tab_Faturamento_RJ[[#This Row],[Unidade]]) * ('Condições de Faturamento'!$D$2:$D$1000 = Tab_Faturamento_RJ[[#This Row],[Categoria]]) * ('Condições de Faturamento'!$E$2:$E$1000 = Tab_Faturamento_RJ[[#This Row],[Fornecedor]]) ), 'Condições de Faturamento'!$F$2:$F$1000 ) = "Emissão no mês da prestação do serviço", Tab_Faturamento_RJ[[#This Row],[Mês de referência para faturamento]], DATE( YEAR(Tab_Faturamento_RJ[[#This Row],[Mês de referência para faturamento]]), MONTH(Tab_Faturamento_RJ[[#This Row],[Mês de referência para faturamento]]) + 1, DAY(Tab_Faturamento_RJ[[#This Row],[Mês de referência para faturamento]]) ) ), DATE( YEAR(Tab_Faturamento_RJ[[#This Row],[Mês de referência para faturamento]]), MONTH(Tab_Faturamento_RJ[[#This Row],[Mês de referência para faturamento]]) + 1, DAY(Tab_Faturamento_RJ[[#This Row],[Mês de referência para faturamento]]) ) )} -> 45689 | AJ97: =IFERROR(L97-M97,0) -> 0 | AK97: =AC97-AD97 -> 0 | AL97: =K97-V97 -> 0 | AN97: kaike.costa@atlasinovacoes.com.br
C98: Não | D98: Carioca Shopping | E98: Resíduos | F98: Nova Rio | G98: 6 | H98: 6 | I98: Informação pendente | J98: Informação pendente | K98: 32285.475 | L98: 0 | M98: Informação pendente | N98: 0 | O98: Informação pendente | P98: 0 | Q98: 0 | R98: 0 | S98: 0 | T98: 0 | V98: =IFERROR((K98+M98+R98+S98+T98+O98)+IF(U98="Sim",P98+Q98,0),(K98+R98+S98+T98)+IF(U98="Sim",P98+Q98,0)) -> 32285.475 | AA98: 45689 | AB98: {=IFERROR( IF( _xlfn.XLOOKUP( 1, ( ('Condições de Faturamento'!$C$2:$C$1000 = Tab_Faturamento_RJ[[#This Row],[Unidade]]) * ('Condições de Faturamento'!$D$2:$D$1000 = Tab_Faturamento_RJ[[#This Row],[Categoria]]) * ('Condições de Faturamento'!$E$2:$E$1000 = Tab_Faturamento_RJ[[#This Row],[Fornecedor]]) ), 'Condições de Faturamento'!$F$2:$F$1000 ) = "Emissão no mês da prestação do serviço", Tab_Faturamento_RJ[[#This Row],[Mês de referência para faturamento]], DATE( YEAR(Tab_Faturamento_RJ[[#This Row],[Mês de referência para faturamento]]), MONTH(Tab_Faturamento_RJ[[#This Row],[Mês de referência para faturamento]]) + 1, DAY(Tab_Faturamento_RJ[[#This Row],[Mês de referência para faturamento]]) ) ), DATE( YEAR(Tab_Faturamento_RJ[[#This Row],[Mês de referência para faturamento]]), MONTH(Tab_Faturamento_RJ[[#This Row],[Mês de referência para faturamento]]) + 1, DAY(Tab_Faturamento_RJ[[#This Row],[Mês de referência para faturamento]]) ) )} -> 45717 | AJ98: =IFERROR(L98-M98,0) -> 0 | AK98: =AC98-AD98 -> 0 | AL98: =K98-V98 -> 0 | AN98: kaike.costa@atlasinovacoes.com.br
C99: Não | D99: Carioca Shopping | E99: Resíduos | F99: Nova Rio | G99: 6 | H99: 6 | I99: Informação pendente | J99: Informação pendente | K99: 32285.475 | L99: 0 | M99: Informação pendente | N99: 0 | O99: Informação pendente | P99: 0 | Q99: 0 | R99: 0 | S99: 0 | T99: 0 | V99: =IFERROR((K99+M99+R99+S99+T99+O99)+IF(U99="Sim",P99+Q99,0),(K99+R99+S99+T99)+IF(U99="Sim",P99+Q99,0)) -> 32285.475 | AA99: 45717 | AB99: {=IFERROR( IF( _xlfn.XLOOKUP( 1, ( ('Condições de Faturamento'!$C$2:$C$1000 = Tab_Faturamento_RJ[[#This Row],[Unidade]]) * ('Condições de Faturamento'!$D$2:$D$1000 = Tab_Faturamento_RJ[[#This Row],[Categoria]]) * ('Condições de Faturamento'!$E$2:$E$1000 = Tab_Faturamento_RJ[[#This Row],[Fornecedor]]) ), 'Condições de Faturamento'!$F$2:$F$1000 ) = "Emissão no mês da prestação do serviço", Tab_Faturamento_RJ[[#This Row],[Mês de referência para faturamento]], DATE( YEAR(Tab_Faturamento_RJ[[#This Row],[Mês de referência para faturamento]]), MONTH(Tab_Faturamento_RJ[[#This Row],[Mês de referência para faturamento]]) + 1, DAY(Tab_Faturamento_RJ[[#This Row],[Mês de referência para faturamento]]) ) ), DATE( YEAR(Tab_Faturamento_RJ[[#This Row],[Mês de referência para faturamento]]), MONTH(Tab_Faturamento_RJ[[#This Row],[Mês de referência para faturamento]]) + 1, DAY(Tab_Faturamento_RJ[[#This Row],[Mês de referência para faturamento]]) ) )} -> 45748 | AJ99: =IFERROR(L99-M99,0) -> 0 | AK99: =AC99-AD99 -> 0 | AL99: =K99-V99 -> 0 | AN99: kaike.costa@atlasinovacoes.com.br
C100: Não | D100: Carioca Shopping | E100: Resíduos | F100: Nova Rio | G100: 6 | H100: 6 | I100: 0 | J100: 0 | K100: 32285.475 | L100: 0 | M100: 0 | N100: 0 | O100: 0 | P100: 0 | Q100: 0 | R100: 0 | S100: 0 | T100: 0 | V100: =IFERROR((K100+M100+R100+S100+T100+O100)+IF(U100="Sim",P100+Q100,0),(K100+R100+S100+T100)+IF(U100="Sim",P100+Q100,0)) -> 32285.475 | AA100: 45748 | AB100: {=IFERROR( IF( _xlfn.XLOOKUP( 1, ( ('Condições de Faturamento'!$C$2:$C$1000 = Tab_Faturamento_RJ[[#This Row],[Unidade]]) * ('Condições de Faturamento'!$D$2:$D$1000 = Tab_Faturamento_RJ[[#This Row],[Categoria]]) * ('Condições de Faturamento'!$E$2:$E$1000 = Tab_Faturamento_RJ[[#This Row],[Fornecedor]]) ), 'Condições de Faturamento'!$F$2:$F$1000 ) = "Emissão no mês da prestação do serviço", Tab_Faturamento_RJ[[#This Row],[Mês de referência para faturamento]], DATE( YEAR(Tab_Faturamento_RJ[[#This Row],[Mês de referência para faturamento]]), MONTH(Tab_Faturamento_RJ[[#This Row],[Mês de referência para faturamento]]) + 1, DAY(Tab_Faturamento_RJ[[#This Row],[Mês de referência para faturamento]]) ) ), DATE( YEAR(Tab_Faturamento_RJ[[#This Row],[Mês de referência para faturamento]]), MONTH(Tab_Faturamento_RJ[[#This Row],[Mês de referência para faturamento]]) + 1, DAY(Tab_Faturamento_RJ[[#This Row],[Mês de referência para faturamento]]) ) )} -> 45778 | AJ100: =IFERROR(L100-M100,0) -> 0 | AK100: =AC100-AD100 -> 0 | AL100: =K100-V100 -> 0 | AN100: kaike.costa@atlasinovacoes.com.br
...

Sheet Faltas | Cálculos
B1: Unidade | C1: Categoria | D1: Fornecedor | E1: Mês falta | F1: Função | G1: Escala | H1: Turno | I1: Horário fim | J1: Quantidade de horas de atraso | K1: Valor hora atraso | L1: Total atrasos | M1: Qtd de dias de faltas | N1: Valor falta | O1: Total faltas | P1: Equipamento | Q1: Dias inoperantes | R1: Valor contrato | S1: Valor do contrato sem o equipamento | T1: Valor pro rata dias sem equipamento | U1: Valor pro rata dias com equipamento | V1: Pro rata total | W1: Diferença | X1: Quantidade | Y1: Desconto equipamentos
B2: Shopping Vila Velha | C2: Limpeza | D2: GPS | E2: 45658 | F2: Operador de Máquina de Limpeza Tripulada* | G2: 12x36 | H2: 0.91666667 | I2: 10:00 | J2: 0 | K2: 19.5 | L2: =J2*K2 -> 0 | M2: 1 | N2: 140.97 | O2: =M2*N2 -> 140.97 | T2: =Tabela4[[#This Row],[Valor do contrato sem o equipamento]]/30.4375*3 -> 0 | U2: =Tabela4[[#This Row],[Valor contrato]]*(30.4375-Tabela4[[#This Row],[Dias inoperantes]])/30.4375 -> 0 | Y2: =Tabela4[[#This Row],[Diferença]]*Tabela4[[#This Row],[Quantidade]] -> 0
B3: Shopping Vila Velha | C3: Limpeza | D3: GPS | E3: 45658 | F3: Operador de Máquina de Limpeza Tripulada* | G3: 6x1 | H3: 0.58333333 | I3: 22:20 | J3: 0 | K3: 19.55 | L3: =J3*K3 -> 0 | M3: 23 | N3: 141.31 | O3: =M3*N3 -> 3250.13 | T3: =Tabela4[[#This Row],[Valor do contrato sem o equipamento]]/30.4375*3 -> 0 | U3: =Tabela4[[#This Row],[Valor contrato]]*(30.4375-Tabela4[[#This Row],[Dias inoperantes]])/30.4375 -> 0 | Y3: =Tabela4[[#This Row],[Diferença]]*Tabela4[[#This Row],[Quantidade]] -> 0
B4: Shopping Vila Velha | C4: Limpeza | D4: GPS | E4: 45658 | F4: Agente de Limpeza - coletor de lixo* | G4: 6x1 | H4: 10:00 | I4: 18:20 | J4: 0 | K4: 23.17 | L4: =J4*K4 -> 0 | M4: 5 | N4: 167.5 | O4: =M4*N4 -> 837.5 | T4: =Tabela4[[#This Row],[Valor do contrato sem o equipamento]]/30.4375*3 -> 0 | U4: =Tabela4[[#This Row],[Valor contrato]]*(30.4375-Tabela4[[#This Row],[Dias inoperantes]])/30.4375 -> 0 | Y4: =Tabela4[[#This Row],[Diferença]]*Tabela4[[#This Row],[Quantidade]] -> 0
B5: Shopping Vila Velha | C5: Limpeza | D5: GPS | E5: 45658 | F5: Auxiliar de Serviços Gerais | G5: 6x1 | H5: 06:00 | I5: 14:20 | J5: 0 | K5: 20.5 | L5: =J5*K5 -> 0 | M5: 16 | N5: 148.14 | O5: =M5*N5 -> 2370.24 | T5: =Tabela4[[#This Row],[Valor do contrato sem o equipamento]]/30.4375*3 -> 0 | U5: =Tabela4[[#This Row],[Valor contrato]]*(30.4375-Tabela4[[#This Row],[Dias inoperantes]])/30.4375 -> 0 | Y5: =Tabela4[[#This Row],[Diferença]]*Tabela4[[#This Row],[Quantidade]] -> 0
B6: Shopping Vila Velha | C6: Limpeza | D6: GPS | E6: 45658 | F6: Auxiliar de Serviços Gerais | G6: 6x1 | H6: 06:00 | I6: 14:20 | J6: 0 | K6: 20.5 | L6: =J6*K6 -> 0 | M6: 5 | N6: 148.14 | O6: =M6*N6 -> 740.7 | T6: =Tabela4[[#This Row],[Valor do contrato sem o equipamento]]/30.4375*3 -> 0 | U6: =Tabela4[[#This Row],[Valor contrato]]*(30.4375-Tabela4[[#This Row],[Dias inoperantes]])/30.4375 -> 0 | Y6: =Tabela4[[#This Row],[Diferença]]*Tabela4[[#This Row],[Quantidade]] -> 0
B7: Shopping Vila Velha | C7: Limpeza | D7: GPS | E7: 45658 | F7: Auxiliar de Serviços Gerais | G7: 6x1 | H7: 0.56944444 | I7: 22:00 | J7: 0 | K7: 20.5 | L7: =J7*K7 -> 0 | M7: 3 | N7: 148.14 | O7: =M7*N7 -> 444.42 | T7: =Tabela4[[#This Row],[Valor do contrato sem o equipamento]]/30.4375*3 -> 0 | U7: =Tabela4[[#This Row],[Valor contrato]]*(30.4375-Tabela4[[#This Row],[Dias inoperantes]])/30.4375 -> 0 | Y7: =Tabela4[[#This Row],[Diferença]]*Tabela4[[#This Row],[Quantidade]] -> 0
B8: Shopping Vila Velha | C8: Limpeza | D8: GPS | E8: 45658 | F8: Auxiliar de Serviços Gerais | G8: 6x1 | H8: 0.25 | I8: 14:20 | J8: 0 | K8: 20.5 | L8: =J8*K8 -> 0 | N8: 148.14 | O8: =M8*N8 -> 0 | T8: =Tabela4[[#This Row],[Valor do contrato sem o equipamento]]/30.4375*3 -> 0 | U8: =Tabela4[[#This Row],[Valor contrato]]*(30.4375-Tabela4[[#This Row],[Dias inoperantes]])/30.4375 -> 0 | Y8: =Tabela4[[#This Row],[Diferença]]*Tabela4[[#This Row],[Quantidade]] -> 0
B9: Shopping Vila Velha | C9: Limpeza | D9: GPS | E9: 45658 | F9: Auxiliar de Serviços Gerais | G9: 6x1 | H9: 13:40 | I9: 22:00 | J9: 0 | K9: 20.5 | L9: =J9*K9 -> 0 | M9: 17 | N9: 148.14 | O9: =M9*N9 -> 2518.38 | T9: =Tabela4[[#This Row],[Valor do contrato sem o equipamento]]/30.4375*3 -> 0 | U9: =Tabela4[[#This Row],[Valor contrato]]*(30.4375-Tabela4[[#This Row],[Dias inoperantes]])/30.4375 -> 0 | Y9: =Tabela4[[#This Row],[Diferença]]*Tabela4[[#This Row],[Quantidade]] -> 0
B10: Shopping Vila Velha | C10: Limpeza | D10: GPS | E10: 45658 | F10: Auxiliar de Serviços Gerais | G10: 6x1 | H10: 06:00 | I10: 14:20 | J10: 0 | K10: 20.5 | L10: =J10*K10 -> 0 | N10: 148.14 | O10: =M10*N10 -> 0 | T10: =Tabela4[[#This Row],[Valor do contrato sem o equipamento]]/30.4375*3 -> 0 | U10: =Tabela4[[#This Row],[Valor contrato]]*(30.4375-Tabela4[[#This Row],[Dias inoperantes]])/30.4375 -> 0 | Y10: =Tabela4[[#This Row],[Diferença]]*Tabela4[[#This Row],[Quantidade]] -> 0
B11: Shopping Vila Velha | C11: Limpeza | D11: GPS | E11: 45658 | F11: Banheiristas | G11: 12x36 | H11: 0.91666667 | I11: 10:00 | J11: 0 | K11: 24.53 | L11: =J11*K11 -> 0 | N11: 177.27 | O11: =M11*N11 -> 0 | T11: =Tabela4[[#This Row],[Valor do contrato sem o equipamento]]/30.4375*3 -> 0 | U11: =Tabela4[[#This Row],[Valor contrato]]*(30.4375-Tabela4[[#This Row],[Dias inoperantes]])/30.4375 -> 0 | Y11: =Tabela4[[#This Row],[Diferença]]*Tabela4[[#This Row],[Quantidade]] -> 0
B12: Shopping Vila Velha | C12: Limpeza | D12: GPS | E12: 45658 | F12: Auxiliar de Serviços Gerais | G12: 6x1 | H12: 06:00 | I12: 14:20 | J12: 0 | K12: 20.5 | L12: =J12*K12 -> 0 | N12: 148.14 | O12: =M12*N12 -> 0 | T12: =Tabela4[[#This Row],[Valor do contrato sem o equipamento]]/30.4375*3 -> 0 | U12: =Tabela4[[#This Row],[Valor contrato]]*(30.4375-Tabela4[[#This Row],[Dias inoperantes]])/30.4375 -> 0 | Y12: =Tabela4[[#This Row],[Diferença]]*Tabela4[[#This Row],[Quantidade]] -> 0
B13: Shopping Vila Velha | C13: Limpeza | D13: GPS | E13: 45658 | F13: Auxiliar de Serviços Gerais | G13: 6x1 | H13: 13:40 | I13: 22:00 | J13: 0 | K13: 20.5 | L13: =J13*K13 -> 0 | M13: 12 | N13: 148.14 | O13: =M13*N13 -> 1777.68 | T13: =Tabela4[[#This Row],[Valor do contrato sem o equipamento]]/30.4375*3 -> 0 | U13: =Tabela4[[#This Row],[Valor contrato]]*(30.4375-Tabela4[[#This Row],[Dias inoperantes]])/30.4375 -> 0 | Y13: =Tabela4[[#This Row],[Diferença]]*Tabela4[[#This Row],[Quantidade]] -> 0
B14: Shopping Vila Velha | C14: Limpeza | D14: GPS | E14: 45658 | F14: Banheiristas | G14: 12x36 | H14: 0.41666667 | I14: 22:00 | J14: 0 | K14: 22.66 | L14: =J14*K14 -> 0 | M14: 4 | N14: 163.77 | O14: =M14*N14 -> 655.08 | T14: =Tabela4[[#This Row],[Valor do contrato sem o equipamento]]/30.4375*3 -> 0 | U14: =Tabela4[[#This Row],[Valor contrato]]*(30.4375-Tabela4[[#This Row],[Dias inoperantes]])/30.4375 -> 0 | Y14: =Tabela4[[#This Row],[Diferença]]*Tabela4[[#This Row],[Quantidade]] -> 0
B15: Shopping Vila Velha | C15: Limpeza | D15: GPS | E15: 45658 | F15: Auxiliar de Serviços Gerais | G15: 6x1 | H15: 06:00 | I15: 14:20 | J15: 0 | K15: 3.26 | L15: =J15*K15 -> 0 | M15: 2 | N15: 23.56 | O15: =M15*N15 -> 47.12 | T15: =Tabela4[[#This Row],[Valor do contrato sem o equipamento]]/30.4375*3 -> 0 | U15: =Tabela4[[#This Row],[Valor contrato]]*(30.4375-Tabela4[[#This Row],[Dias inoperantes]])/30.4375 -> 0 | Y15: =Tabela4[[#This Row],[Diferença]]*Tabela4[[#This Row],[Quantidade]] -> 0
B16: Shopping Vila Velha | C16: Limpeza | D16: GPS | E16: 45717 | F16: Encarregado | G16: 12x36 | H16: 06:00 | I16: 18:00 | J16: 0 | K16: 22.78 | L16: =J16*K16 -> 0 | N16: 164.68 | O16: =M16*N16 -> 0 | T16: =Tabela4[[#This Row],[Valor do contrato sem o equipamento]]/30.4375*3 -> 0 | U16: =Tabela4[[#This Row],[Valor contrato]]*(30.4375-Tabela4[[#This Row],[Dias inoperantes]])/30.4375 -> 0 | Y16: =Tabela4[[#This Row],[Diferença]]*Tabela4[[#This Row],[Quantidade]] -> 0
B17: Shopping Vila Velha | C17: Limpeza | D17: GPS | E17: 45717 | F17: Encarregado | G17: 12x36 | H17: 06:00 | I17: 18:00 | J17: 0 | K17: 22.78 | L17: =J17*K17 -> 0 | N17: 164.68 | O17: =M17*N17 -> 0 | T17: =Tabela4[[#This Row],[Valor do contrato sem o equipamento]]/30.4375*3 -> 0 | U17: =Tabela4[[#This Row],[Valor contrato]]*(30.4375-Tabela4[[#This Row],[Dias inoperantes]])/30.4375 -> 0 | Y17: =Tabela4[[#This Row],[Diferença]]*Tabela4[[#This Row],[Quantidade]] -> 0
B18: Shopping Vila Velha | C18: Limpeza | D18: GPS | E18: 45717 | F18: Encarregado | G18: 12x36 | H18: 0.91666667 | I18: 10:00 | J18: 0 | K18: 24.77 | L18: =J18*K18 -> 0 | N18: 179.07 | O18: =M18*N18 -> 0 | T18: =Tabela4[[#This Row],[Valor do contrato sem o equipamento]]/30.4375*3 -> 0 | U18: =Tabela4[[#This Row],[Valor contrato]]*(30.4375-Tabela4[[#This Row],[Dias inoperantes]])/30.4375 -> 0 | Y18: =Tabela4[[#This Row],[Diferença]]*Tabela4[[#This Row],[Quantidade]] -> 0
B19: Shopping Vila Velha | C19: Limpeza | D19: GPS | E19: 45717 | F19: Operador de Máquina de Limpeza Tripulada* | G19: 12x36 | H19: 0.91666667 | I19: 10:00 | J19: 0 | K19: 19.5 | L19: =J19*K19 -> 0 | M19: 2 | N19: 140.97 | O19: =M19*N19 -> 281.94 | T19: =Tabela4[[#This Row],[Valor do contrato sem o equipamento]]/30.4375*3 -> 0 | U19: =Tabela4[[#This Row],[Valor contrato]]*(30.4375-Tabela4[[#This Row],[Dias inoperantes]])/30.4375 -> 0 | Y19: =Tabela4[[#This Row],[Diferença]]*Tabela4[[#This Row],[Quantidade]] -> 0
B20: Shopping Vila Velha | C20: Limpeza | D20: GPS | E20: 45717 | F20: Operador de Máquina de Limpeza Tripulada* | G20: 6x1 | H20: 0.58333333 | I20: 22:20 | J20: 0 | K20: 19.55 | L20: =J20*K20 -> 0 | N20: 141.31 | O20: =M20*N20 -> 0 | T20: =Tabela4[[#This Row],[Valor do contrato sem o equipamento]]/30.4375*3 -> 0 | U20: =Tabela4[[#This Row],[Valor contrato]]*(30.4375-Tabela4[[#This Row],[Dias inoperantes]])/30.4375 -> 0 | Y20: =Tabela4[[#This Row],[Diferença]]*Tabela4[[#This Row],[Quantidade]] -> 0
B21: Shopping Vila Velha | C21: Limpeza | D21: GPS | E21: 45717 | F21: Agente de Limpeza - coletor de lixo* | G21: 6x1 | H21: 10:00 | I21: 18:20 | J21: 0 | K21: 23.17 | L21: =J21*K21 -> 0 | N21: 167.5 | O21: =M21*N21 -> 0 | T21: =Tabela4[[#This Row],[Valor do contrato sem o equipamento]]/30.4375*3 -> 0 | U21: =Tabela4[[#This Row],[Valor contrato]]*(30.4375-Tabela4[[#This Row],[Dias inoperantes]])/30.4375 -> 0 | Y21: =Tabela4[[#This Row],[Diferença]]*Tabela4[[#This Row],[Quantidade]] -> 0
B22: Shopping Vila Velha | C22: Limpeza | D22: GPS | E22: 45717 | F22: Auxiliar de Serviços Gerais | G22: 6x1 | H22: 06:00 | I22: 14:20 | J22: 0 | K22: 20.5 | L22: =J22*K22 -> 0 | M22: 82 | N22: 148.14 | O22: =M22*N22 -> 12147.48 | T22: =Tabela4[[#This Row],[Valor do contrato sem o equipamento]]/30.4375*3 -> 0 | U22: =Tabela4[[#This Row],[Valor contrato]]*(30.4375-Tabela4[[#This Row],[Dias inoperantes]])/30.4375 -> 0 | Y22: =Tabela4[[#This Row],[Diferença]]*Tabela4[[#This Row],[Quantidade]] -> 0
B23: Shopping Vila Velha | C23: Limpeza | D23: GPS | E23: 45717 | F23: Auxiliar de Serviços Gerais | G23: 6x1 | H23: 06:00 | I23: 14:20 | J23: 0 | K23: 20.5 | L23: =J23*K23 -> 0 | N23: 148.14 | O23: =M23*N23 -> 0 | T23: =Tabela4[[#This Row],[Valor do contrato sem o equipamento]]/30.4375*3 -> 0 | U23: =Tabela4[[#This Row],[Valor contrato]]*(30.4375-Tabela4[[#This Row],[Dias inoperantes]])/30.4375 -> 0 | Y23: =Tabela4[[#This Row],[Diferença]]*Tabela4[[#This Row],[Quantidade]] -> 0
B24: Shopping Vila Velha | C24: Limpeza | D24: GPS | E24: 45717 | F24: Auxiliar de Serviços Gerais | G24: 6x1 | H24: 0.56944444 | I24: 22:00 | J24: 0 | K24: 20.5 | L24: =J24*K24 -> 0 | N24: 148.14 | O24: =M24*N24 -> 0 | T24: =Tabela4[[#This Row],[Valor do contrato sem o equipamento]]/30.4375*3 -> 0 | U24: =Tabela4[[#This Row],[Valor contrato]]*(30.4375-Tabela4[[#This Row],[Dias inoperantes]])/30.4375 -> 0 | Y24: =Tabela4[[#This Row],[Diferença]]*Tabela4[[#This Row],[Quantidade]] -> 0
B25: Shopping Vila Velha | C25: Limpeza | D25: GPS | E25: 45717 | F25: Auxiliar de Serviços Gerais | G25: 6x1 | H25: 0.25 | I25: 14:20 | J25: 0 | K25: 20.5 | L25: =J25*K25 -> 0 | N25: 148.14 | O25: =M25*N25 -> 0 | T25: =Tabela4[[#This Row],[Valor do contrato sem o equipamento]]/30.4375*3 -> 0 | U25: =Tabela4[[#This Row],[Valor contrato]]*(30.4375-Tabela4[[#This Row],[Dias inoperantes]])/30.4375 -> 0 | Y25: =Tabela4[[#This Row],[Diferença]]*Tabela4[[#This Row],[Quantidade]] -> 0
B26: Shopping Vila Velha | C26: Limpeza | D26: GPS | E26: 45717 | F26: Auxiliar de Serviços Gerais | G26: 6x1 | H26: 13:40 | I26: 22:00 | J26: 0 | K26: 20.5 | L26: =J26*K26 -> 0 | M26: 66 | N26: 148.14 | O26: =M26*N26 -> 9777.24 | T26: =Tabela4[[#This Row],[Valor do contrato sem o equipamento]]/30.4375*3 -> 0 | U26: =Tabela4[[#This Row],[Valor contrato]]*(30.4375-Tabela4[[#This Row],[Dias inoperantes]])/30.4375 -> 0 | Y26: =Tabela4[[#This Row],[Diferença]]*Tabela4[[#This Row],[Quantidade]] -> 0
B27: Shopping Vila Velha | C27: Limpeza | D27: GPS | E27: 45717 | F27: Auxiliar de Serviços Gerais | G27: 6x1 | H27: 06:00 | I27: 14:20 | J27: 0 | K27: 20.5 | L27: =J27*K27 -> 0 | N27: 148.14 | O27: =M27*N27 -> 0 | T27: =Tabela4[[#This Row],[Valor do contrato sem o equipamento]]/30.4375*3 -> 0 | U27: =Tabela4[[#This Row],[Valor contrato]]*(30.4375-Tabela4[[#This Row],[Dias inoperantes]])/30.4375 -> 0 | Y27: =Tabela4[[#This Row],[Diferença]]*Tabela4[[#This Row],[Quantidade]] -> 0
B28: Shopping Vila Velha | C28: Limpeza | D28: GPS | E28: 45717 | F28: Banheiristas | G28: 12x36 | H28: 0.91666667 | I28: 10:00 | J28: 0 | K28: 24.53 | L28: =J28*K28 -> 0 | M28: 17 | N28: 177.27 | O28: =M28*N28 -> 3013.59 | T28: =Tabela4[[#This Row],[Valor do contrato sem o equipamento]]/30.4375*3 -> 0 | U28: =Tabela4[[#This Row],[Valor contrato]]*(30.4375-Tabela4[[#This Row],[Dias inoperantes]])/30.4375 -> 0 | Y28: =Tabela4[[#This Row],[Diferença]]*Tabela4[[#This Row],[Quantidade]] -> 0
B29: Shopping Vila Velha | C29: Limpeza | D29: GPS | E29: 45717 | F29: Auxiliar de Serviços Gerais | G29: 6x1 | H29: 06:00 | I29: 14:20 | J29: 0 | K29: 20.5 | L29: =J29*K29 -> 0 | N29: 148.14 | O29: =M29*N29 -> 0 | T29: =Tabela4[[#This Row],[Valor do contrato sem o equipamento]]/30.4375*3 -> 0 | U29: =Tabela4[[#This Row],[Valor contrato]]*(30.4375-Tabela4[[#This Row],[Dias inoperantes]])/30.4375 -> 0 | Y29: =Tabela4[[#This Row],[Diferença]]*Tabela4[[#This Row],[Quantidade]] -> 0
B30: Shopping Vila Velha | C30: Limpeza | D30: GPS | E30: 45717 | F30: Auxiliar de Serviços Gerais | G30: 6x1 | H30: 13:40 | I30: 22:00 | J30: 0 | K30: 20.5 | L30: =J30*K30 -> 0 | N30: 148.14 | O30: =M30*N30 -> 0 | T30: =Tabela4[[#This Row],[Valor do contrato sem o equipamento]]/30.4375*3 -> 0 | U30: =Tabela4[[#This Row],[Valor contrato]]*(30.4375-Tabela4[[#This Row],[Dias inoperantes]])/30.4375 -> 0 | Y30: =Tabela4[[#This Row],[Diferença]]*Tabela4[[#This Row],[Quantidade]] -> 0
B31: Shopping Vila Velha | C31: Limpeza | D31: GPS | E31: 45717 | F31: Banheiristas | G31: 12x36 | H31: 0.41666667 | I31: 22:00 | J31: 0 | K31: 22.66 | L31: =J31*K31 -> 0 | M31: 18 | N31: 163.77 | O31: =M31*N31 -> 2947.86 | T31: =Tabela4[[#This Row],[Valor do contrato sem o equipamento]]/30.4375*3 -> 0 | U31: =Tabela4[[#This Row],[Valor contrato]]*(30.4375-Tabela4[[#This Row],[Dias inoperantes]])/30.4375 -> 0 | Y31: =Tabela4[[#This Row],[Diferença]]*Tabela4[[#This Row],[Quantidade]] -> 0
B32: Shopping Vila Velha | C32: Limpeza | D32: GPS | E32: 45717 | F32: Auxiliar de Serviços Gerais | G32: 6x1 | H32: 06:00 | I32: 14:20 | J32: 0 | K32: 3.26 | L32: =J32*K32 -> 0 | N32: 23.56 | O32: =M32*N32 -> 0 | T32: =Tabela4[[#This Row],[Valor do contrato sem o equipamento]]/30.4375*3 -> 0 | U32: =Tabela4[[#This Row],[Valor contrato]]*(30.4375-Tabela4[[#This Row],[Dias inoperantes]])/30.4375 -> 0 | Y32: =Tabela4[[#This Row],[Diferença]]*Tabela4[[#This Row],[Quantidade]] -> 0
B33: Shopping Vila Velha | C33: Limpeza | D33: GPS | E33: 45748 | F33: Encarregado | G33: 12x36 | H33: 10:00 | I33: 22:00 | K33: 25.69 | L33: =J33*K33 -> 0 | N33: 185.71 | O33: =M33*N33 -> 0 | T33: =Tabela4[[#This Row],[Valor do contrato sem o equipamento]]/30.4375*3 -> 0 | U33: =Tabela4[[#This Row],[Valor contrato]]*(30.4375-Tabela4[[#This Row],[Dias inoperantes]])/30.4375 -> 0 | Y33: =Tabela4[[#This Row],[Diferença]]*Tabela4[[#This Row],[Quantidade]] -> 0
B34: Shopping Vila Velha | C34: Limpeza | D34: GPS | E34: 45748 | F34: Encarregado | G34: 12x36 | H34: 10:00 | I34: 22:00 | K34: 2.15 | L34: =J34*K34 -> 0 | N34: 15.57 | O34: =M34*N34 -> 0 | T34: =Tabela4[[#This Row],[Valor do contrato sem o equipamento]]/30.4375*3 -> 0 | U34: =Tabela4[[#This Row],[Valor contrato]]*(30.4375-Tabela4[[#This Row],[Dias inoperantes]])/30.4375 -> 0 | Y34: =Tabela4[[#This Row],[Diferença]]*Tabela4[[#This Row],[Quantidade]] -> 0
B35: Shopping Vila Velha | C35: Limpeza | D35: GPS | E35: 45748 | F35: Encarregado | G35: 12x36 | H35: 22:00 | I35: 10:00 | K35: 27.93 | L35: =J35*K35 -> 0 | M35: 1 | N35: 201.87 | O35: =M35*N35 -> 201.87 | T35: =Tabela4[[#This Row],[Valor do contrato sem o equipamento]]/30.4375*3 -> 0 | U35: =Tabela4[[#This Row],[Valor contrato]]*(30.4375-Tabela4[[#This Row],[Dias inoperantes]])/30.4375 -> 0 | Y35: =Tabela4[[#This Row],[Diferença]]*Tabela4[[#This Row],[Quantidade]] -> 0
B36: Shopping Vila Velha | C36: Limpeza | D36: GPS | E36: 45748 | F36: Operador de Máquina de Limpeza Tripulada* | G36: 12x36 | H36: 22:00 | I36: 10:00 | K36: 27.96 | L36: =J36*K36 -> 0 | N36: 202.06 | O36: =M36*N36 -> 0 | T36: =Tabela4[[#This Row],[Valor do contrato sem o equipamento]]/30.4375*3 -> 0 | U36: =Tabela4[[#This Row],[Valor contrato]]*(30.4375-Tabela4[[#This Row],[Dias inoperantes]])/30.4375 -> 0 | Y36: =Tabela4[[#This Row],[Diferença]]*Tabela4[[#This Row],[Quantidade]] -> 0
B37: Shopping Vila Velha | C37: Limpeza | D37: GPS | E37: 45748 | F37: Agente de Limpeza - coletor de lixo* | G37: 12x36 | H37: 0.41666667 | I37: 22:00 | K37: 23.98 | L37: =J37*K37 -> 0 | N37: 173.31 | O37: =M37*N37 -> 0 | T37: =Tabela4[[#This Row],[Valor do contrato sem o equipamento]]/30.4375*3 -> 0 | U37: =Tabela4[[#This Row],[Valor contrato]]*(30.4375-Tabela4[[#This Row],[Dias inoperantes]])/30.4375 -> 0 | Y37: =Tabela4[[#This Row],[Diferença]]*Tabela4[[#This Row],[Quantidade]] -> 0
B38: Shopping Vila Velha | C38: Limpeza | D38: GPS | E38: 45748 | F38: Auxiliar de Serviços Gerais (limpador de vidros) | G38: 12x36 | H38: 0.29166667 | I38: 19:00 | K38: 21.1 | L38: =J38*K38 -> 0 | N38: 152.5 | O38: =M38*N38 -> 0 | T38: =Tabela4[[#This Row],[Valor do contrato sem o equipamento]]/30.4375*3 -> 0 | U38: =Tabela4[[#This Row],[Valor contrato]]*(30.4375-Tabela4[[#This Row],[Dias inoperantes]])/30.4375 -> 0 | Y38: =Tabela4[[#This Row],[Diferença]]*Tabela4[[#This Row],[Quantidade]] -> 0
B39: Shopping Vila Velha | C39: Limpeza | D39: GPS | E39: 45748 | F39: Auxiliar de Serviços Gerais | G39: 12x36 | H39: 0.25 | I39: 18:00 | K39: 21.1 | L39: =J39*K39 -> 0 | N39: 152.5 | O39: =M39*N39 -> 0 | T39: =Tabela4[[#This Row],[Valor do contrato sem o equipamento]]/30.4375*3 -> 0 | U39: =Tabela4[[#This Row],[Valor contrato]]*(30.4375-Tabela4[[#This Row],[Dias inoperantes]])/30.4375 -> 0 | Y39: =Tabela4[[#This Row],[Diferença]]*Tabela4[[#This Row],[Quantidade]] -> 0
B40: Shopping Vila Velha | C40: Limpeza | D40: GPS | E40: 45748 | F40: Auxiliar de Serviços Gerais | G40: 12x36 | H40: 0.41666667 | I40: 22:00 | K40: 21.1 | L40: =J40*K40 -> 0 | N40: 152.5 | O40: =M40*N40 -> 0 | T40: =Tabela4[[#This Row],[Valor do contrato sem o equipamento]]/30.4375*3 -> 0 | U40: =Tabela4[[#This Row],[Valor contrato]]*(30.4375-Tabela4[[#This Row],[Dias inoperantes]])/30.4375 -> 0 | Y40: =Tabela4[[#This Row],[Diferença]]*Tabela4[[#This Row],[Quantidade]] -> 0
B41: Shopping Vila Velha | C41: Limpeza | D41: GPS | E41: 45748 | F41: Auxiliar de Serviços Gerais | G41: 12x36 | H41: 0.45833333 | I41: 23:00 | K41: 21.39 | L41: =J41*K41 -> 0 | N41: 154.62 | O41: =M41*N41 -> 0 | T41: =Tabela4[[#This Row],[Valor do contrato sem o equipamento]]/30.4375*3 -> 0 | U41: =Tabela4[[#This Row],[Valor contrato]]*(30.4375-Tabela4[[#This Row],[Dias inoperantes]])/30.4375 -> 0 | Y41: =Tabela4[[#This Row],[Diferença]]*Tabela4[[#This Row],[Quantidade]] -> 0
B42: Shopping Vila Velha | C42: Limpeza | D42: GPS | E42: 45748 | F42: Auxiliar de Serviços Gerais (Banheirista) | G42: 12x36 | H42: 0.41666667 | I42: 22:00 | K42: 23.98 | L42: =J42*K42 -> 0 | M42: 12 | N42: 173.31 | O42: =M42*N42 -> 2079.72 | T42: =Tabela4[[#This Row],[Valor do contrato sem o equipamento]]/30.4375*3 -> 0 | U42: =Tabela4[[#This Row],[Valor contrato]]*(30.4375-Tabela4[[#This Row],[Dias inoperantes]])/30.4375 -> 0 | Y42: =Tabela4[[#This Row],[Diferença]]*Tabela4[[#This Row],[Quantidade]] -> 0
B43: Shopping Vila Velha | C43: Limpeza | D43: GPS | E43: 45748 | F43: Auxiliar de Serviços Gerais | G43: 12x36 | H43: 0.91666667 | I43: 10:00 | K43: 22.85 | L43: =J43*K43 -> 0 | N43: 165.18 | O43: =M43*N43 -> 0 | T43: =Tabela4[[#This Row],[Valor do contrato sem o equipamento]]/30.4375*3 -> 0 | U43: =Tabela4[[#This Row],[Valor contrato]]*(30.4375-Tabela4[[#This Row],[Dias inoperantes]])/30.4375 -> 0 | Y43: =Tabela4[[#This Row],[Diferença]]*Tabela4[[#This Row],[Quantidade]] -> 0
B44: Shopping Vila Velha | C44: Limpeza | D44: GPS | E44: 45748 | F44: Auxiliar de Serviços Gerais | G44: 12x36 | H44: 06:00 | I44: 18:00 | K44: 21.1 | L44: =J44*K44 -> 0 | N44: 152.5 | O44: =M44*N44 -> 0 | T44: =Tabela4[[#This Row],[Valor do contrato sem o equipamento]]/30.4375*3 -> 0 | U44: =Tabela4[[#This Row],[Valor contrato]]*(30.4375-Tabela4[[#This Row],[Dias inoperantes]])/30.4375 -> 0 | Y44: =Tabela4[[#This Row],[Diferença]]*Tabela4[[#This Row],[Quantidade]] -> 0
B45: Shopping Vila Velha | C45: Limpeza | D45: GPS | E45: 45748 | F45: Auxiliar de Serviços Gerais | G45: 12x36 | H45: 0.25 | I45: 18:00 | K45: 21.1 | L45: =J45*K45 -> 0 | N45: 152.5 | O45: =M45*N45 -> 0 | T45: =Tabela4[[#This Row],[Valor do contrato sem o equipamento]]/30.4375*3 -> 0 | U45: =Tabela4[[#This Row],[Valor contrato]]*(30.4375-Tabela4[[#This Row],[Dias inoperantes]])/30.4375 -> 0 | Y45: =Tabela4[[#This Row],[Diferença]]*Tabela4[[#This Row],[Quantidade]] -> 0
B46: Shopping Vila Velha | C46: Limpeza | D46: GPS | E46: 45748 | F46: Auxiliar de Serviços Gerais | G46: 12x36 | H46: 0.41666667 | I46: 22:00 | K46: 21.1 | L46: =J46*K46 -> 0 | N46: 152.5 | O46: =M46*N46 -> 0 | T46: =Tabela4[[#This Row],[Valor do contrato sem o equipamento]]/30.4375*3 -> 0 | U46: =Tabela4[[#This Row],[Valor contrato]]*(30.4375-Tabela4[[#This Row],[Dias inoperantes]])/30.4375 -> 0 | Y46: =Tabela4[[#This Row],[Diferença]]*Tabela4[[#This Row],[Quantidade]] -> 0
B47: Shopping Vila Velha | C47: Limpeza | D47: GPS | E47: 45748 | F47: Auxiliar de Serviços Gerais | G47: 12x36 | H47: 0.25 | I47: 18:00 | K47: 21.1 | L47: =J47*K47 -> 0 | N47: 152.5 | O47: =M47*N47 -> 0 | T47: =Tabela4[[#This Row],[Valor do contrato sem o equipamento]]/30.4375*3 -> 0 | U47: =Tabela4[[#This Row],[Valor contrato]]*(30.4375-Tabela4[[#This Row],[Dias inoperantes]])/30.4375 -> 0 | Y47: =Tabela4[[#This Row],[Diferença]]*Tabela4[[#This Row],[Quantidade]] -> 0
B48: Shopping Vila Velha | C48: Limpeza | D48: GPS | E48: 45748 | F48: Auxiliar de Serviços Gerais | G48: 12x36 | H48: 06:00 | I48: 18:00 | K48: 2.32 | L48: =J48*K48 -> 0 | N48: 16.79 | O48: =M48*N48 -> 0 | T48: =Tabela4[[#This Row],[Valor do contrato sem o equipamento]]/30.4375*3 -> 0 | U48: =Tabela4[[#This Row],[Valor contrato]]*(30.4375-Tabela4[[#This Row],[Dias inoperantes]])/30.4375 -> 0 | Y48: =Tabela4[[#This Row],[Diferença]]*Tabela4[[#This Row],[Quantidade]] -> 0
B49: Shopping Vila Velha | C49: Limpeza | D49: GPS | E49: 45778 | F49: Encarregado | G49: 12x36 | H49: 0.41666667 | I49: 0.91666667 | L49: =J49*K49 -> 0 | M49: 1 | N49: 185.71 | O49: =M49*N49 -> 185.71 | T49: =Tabela4[[#This Row],[Valor do contrato sem o equipamento]]/30.4375*3 -> 0 | U49: =Tabela4[[#This Row],[Valor contrato]]*(30.4375-Tabela4[[#This Row],[Dias inoperantes]])/30.4375 -> 0 | Y49: =Tabela4[[#This Row],[Diferença]]*Tabela4[[#This Row],[Quantidade]] -> 0
B50: Shopping Vila Velha | C50: Limpeza | D50: GPS | E50: 45778 | F50: Operador de Máquina de Limpeza Tripulada* | G50: 12x36 | H50: 0.91666667 | I50: 0.41666667 | L50: =J50*K50 -> 0 | M50: 17 | N50: 202.06 | O50: =M50*N50 -> 3435.02 | T50: =Tabela4[[#This Row],[Valor do contrato sem o equipamento]]/30.4375*3 -> 0 | U50: =Tabela4[[#This Row],[Valor contrato]]*(30.4375-Tabela4[[#This Row],[Dias inoperantes]])/30.4375 -> 0 | Y50: =Tabela4[[#This Row],[Diferença]]*Tabela4[[#This Row],[Quantidade]] -> 0
B51: Shopping Vila Velha | C51: Limpeza | D51: GPS | E51: 45778 | F51: Agente de Limpeza | G51: 12x36 | H51: 0.29166667 | I51: 0.79166667 | L51: =J51*K51 -> 0 | M51: 17 | N51: 152.5 | O51: =M51*N51 -> 2592.5 | T51: =Tabela4[[#This Row],[Valor do contrato sem o equipamento]]/30.4375*3 -> 0 | U51: =Tabela4[[#This Row],[Valor contrato]]*(30.4375-Tabela4[[#This Row],[Dias inoperantes]])/30.4375 -> 0 | Y51: =Tabela4[[#This Row],[Diferença]]*Tabela4[[#This Row],[Quantidade]] -> 0
B52: Shopping Vila Velha | C52: Limpeza | D52: GPS | E52: 45778 | F52: Agente de Limpeza | G52: 12x36 | H52: 0.41666667 | I52: 0.91666667 | L52: =J52*K52 -> 0 | M52: 6 | N52: 152.5 | O52: =M52*N52 -> 915 | T52: =Tabela4[[#This Row],[Valor do contrato sem o equipamento]]/30.4375*3 -> 0 | U52: =Tabela4[[#This Row],[Valor contrato]]*(30.4375-Tabela4[[#This Row],[Dias inoperantes]])/30.4375 -> 0 | Y52: =Tabela4[[#This Row],[Diferença]]*Tabela4[[#This Row],[Quantidade]] -> 0
B53: Shopping Vila Velha | C53: Limpeza | D53: GPS | E53: 45778 | F53: Banheirista | G53: 12x36 | H53: 0.41666667 | I53: 0.91666667 | L53: =J53*K53 -> 0 | M53: 14 | N53: 173.31 | O53: =M53*N53 -> 2426.34 | T53: =Tabela4[[#This Row],[Valor do contrato sem o equipamento]]/30.4375*3 -> 0 | U53: =Tabela4[[#This Row],[Valor contrato]]*(30.4375-Tabela4[[#This Row],[Dias inoperantes]])/30.4375 -> 0 | Y53: =Tabela4[[#This Row],[Diferença]]*Tabela4[[#This Row],[Quantidade]] -> 0
B54: Shopping Vila Velha | C54: Limpeza | D54: GPS | E54: 45778 | F54: Agente de Limpeza - lavação | G54: 12x36 | H54: 0.91666667 | I54: 0.41666667 | L54: =J54*K54 -> 0 | M54: 12 | N54: 165.18 | O54: =M54*N54 -> 1982.16 | T54: =Tabela4[[#This Row],[Valor do contrato sem o equipamento]]/30.4375*3 -> 0 | U54: =Tabela4[[#This Row],[Valor contrato]]*(30.4375-Tabela4[[#This Row],[Dias inoperantes]])/30.4375 -> 0 | Y54: =Tabela4[[#This Row],[Diferença]]*Tabela4[[#This Row],[Quantidade]] -> 0
B55: Shopping Vila Velha | C55: Limpeza | D55: GPS | E55: 45809 | F55: Encarregado | G55: 12x36 | H55: 22:00 | I55: 10:00 | K55: 27.93 | L55: =J55*K55 -> 0 | M55: 2 | N55: 201.87 | O55: =M55*N55 -> 403.74 | T55: =Tabela4[[#This Row],[Valor do contrato sem o equipamento]]/30.4375*3 -> 0 | U55: =Tabela4[[#This Row],[Valor contrato]]*(30.4375-Tabela4[[#This Row],[Dias inoperantes]])/30.4375 -> 0 | Y55: =Tabela4[[#This Row],[Diferença]]*Tabela4[[#This Row],[Quantidade]] -> 0
B56: Shopping Vila Velha | C56: Limpeza | D56: GPS | E56: 45809 | F56: Operador de Máquina de Limpeza Tripulada* | G56: 12x36 | H56: 22:00 | I56: 10:00 | K56: 27.96 | L56: =J56*K56 -> 0 | M56: 19 | N56: 202.06 | O56: =M56*N56 -> 3839.14 | T56: =Tabela4[[#This Row],[Valor do contrato sem o equipamento]]/30.4375*3 -> 0 | U56: =Tabela4[[#This Row],[Valor contrato]]*(30.4375-Tabela4[[#This Row],[Dias inoperantes]])/30.4375 -> 0 | Y56: =Tabela4[[#This Row],[Diferença]]*Tabela4[[#This Row],[Quantidade]] -> 0
B57: Shopping Vila Velha | C57: Limpeza | D57: GPS | E57: 45809 | F57: Agente de Limpeza - coletor de lixo* | G57: 12x36 | H57: 0.41666667 | I57: 22:00 | K57: 23.98 | L57: =J57*K57 -> 0 | M57: 1 | N57: 173.31 | O57: =M57*N57 -> 173.31 | T57: =Tabela4[[#This Row],[Valor do contrato sem o equipamento]]/30.4375*3 -> 0 | U57: =Tabela4[[#This Row],[Valor contrato]]*(30.4375-Tabela4[[#This Row],[Dias inoperantes]])/30.4375 -> 0 | Y57: =Tabela4[[#This Row],[Diferença]]*Tabela4[[#This Row],[Quantidade]] -> 0
B58: Shopping Vila Velha | C58: Limpeza | D58: GPS | E58: 45809 | F58: Auxiliar de Serviços Gerais (limpador de vidros) | G58: 12x36 | H58: 0.29166667 | I58: 19:00 | K58: 21.1 | L58: =J58*K58 -> 0 | M58: 15 | N58: 152.5 | O58: =M58*N58 -> 2287.5 | T58: =Tabela4[[#This Row],[Valor do contrato sem o equipamento]]/30.4375*3 -> 0 | U58: =Tabela4[[#This Row],[Valor contrato]]*(30.4375-Tabela4[[#This Row],[Dias inoperantes]])/30.4375 -> 0 | Y58: =Tabela4[[#This Row],[Diferença]]*Tabela4[[#This Row],[Quantidade]] -> 0
B59: Shopping Vila Velha | C59: Limpeza | D59: GPS | E59: 45809 | F59: Auxiliar de Serviços Gerais | G59: 12x36 | H59: 0.41666667 | I59: 22:00 | K59: 21.1 | L59: =J59*K59 -> 0 | M59: 16 | N59: 152.5 | O59: =M59*N59 -> 2440 | T59: =Tabela4[[#This Row],[Valor do contrato sem o equipamento]]/30.4375*3 -> 0 | U59: =Tabela4[[#This Row],[Valor contrato]]*(30.4375-Tabela4[[#This Row],[Dias inoperantes]])/30.4375 -> 0 | Y59: =Tabela4[[#This Row],[Diferença]]*Tabela4[[#This Row],[Quantidade]] -> 0
B60: Shopping Vila Velha | C60: Limpeza | D60: GPS | E60: 45809 | F60: Auxiliar de Serviços Gerais (Banheirista) | G60: 12x36 | H60: 0.41666667 | I60: 22:00 | K60: 23.98 | L60: =J60*K60 -> 0 | M60: 23 | N60: 173.31 | O60: =M60*N60 -> 3986.13 | T60: =Tabela4[[#This Row],[Valor do contrato sem o equipamento]]/30.4375*3 -> 0 | U60: =Tabela4[[#This Row],[Valor contrato]]*(30.4375-Tabela4[[#This Row],[Dias inoperantes]])/30.4375 -> 0 | Y60: =Tabela4[[#This Row],[Diferença]]*Tabela4[[#This Row],[Quantidade]] -> 0
B61: Shopping Vila Velha | C61: Limpeza | D61: GPS | E61: 45809 | F61: Auxiliar de Serviços Gerais | G61: 12x36 | H61: 0.91666667 | I61: 10:00 | K61: 22.85 | L61: =J61*K61 -> 0 | M61: =6+11 -> 17 | N61: 165.18 | O61: =M61*N61 -> 2808.06 | T61: =Tabela4[[#This Row],[Valor do contrato sem o equipamento]]/30.4375*3 -> 0 | U61: =Tabela4[[#This Row],[Valor contrato]]*(30.4375-Tabela4[[#This Row],[Dias inoperantes]])/30.4375 -> 0 | Y61: =Tabela4[[#This Row],[Diferença]]*Tabela4[[#This Row],[Quantidade]] -> 0
B62: Shopping Vila Velha | C62: Limpeza | D62: GPS | E62: 45839 | F62: Encarregado | G62: 12x36 | H62: 22:00 | I62: 10:00 | J62: 0 | K62: 27.93 | L62: =J62*K62 -> 0 | M62: 1 | N62: 201.87 | O62: =M62*N62 -> 201.87 | T62: =Tabela4[[#This Row],[Valor do contrato sem o equipamento]]/30.4375*3 -> 0 | U62: =Tabela4[[#This Row],[Valor contrato]]*(30.4375-Tabela4[[#This Row],[Dias inoperantes]])/30.4375 -> 0 | Y62: =Tabela4[[#This Row],[Diferença]]*Tabela4[[#This Row],[Quantidade]] -> 0
B63: Shopping Vila Velha | C63: Limpeza | D63: GPS | E63: 45839 | F63: Operador de Máquina de Limpeza Tripulada* | G63: 12x36 | H63: 22:00 | I63: 10:00 | J63: 0 | K63: 27.96 | L63: =J63*K63 -> 0 | M63: 15 | N63: 202.06 | O63: =M63*N63 -> 3030.9 | T63: =Tabela4[[#This Row],[Valor do contrato sem o equipamento]]/30.4375*3 -> 0 | U63: =Tabela4[[#This Row],[Valor contrato]]*(30.4375-Tabela4[[#This Row],[Dias inoperantes]])/30.4375 -> 0 | Y63: =Tabela4[[#This Row],[Diferença]]*Tabela4[[#This Row],[Quantidade]] -> 0
B64: Shopping Vila Velha | C64: Limpeza | D64: GPS | E64: 45839 | F64: Agente de Limpeza - coletor de lixo* | G64: 12x36 | H64: 0.41666667 | I64: 22:00 | J64: 0 | K64: 23.98 | L64: =J64*K64 -> 0 | M64: 1 | N64: 173.31 | O64: =M64*N64 -> 173.31 | T64: =Tabela4[[#This Row],[Valor do contrato sem o equipamento]]/30.4375*3 -> 0 | U64: =Tabela4[[#This Row],[Valor contrato]]*(30.4375-Tabela4[[#This Row],[Dias inoperantes]])/30.4375 -> 0 | Y64: =Tabela4[[#This Row],[Diferença]]*Tabela4[[#This Row],[Quantidade]] -> 0
B65: Shopping Vila Velha | C65: Limpeza | D65: GPS | E65: 45839 | F65: Agente de Limpeza | G65: 12x36 | H65: 0.29166667 | I65: 19:00 | J65: 0 | K65: 21.1 | L65: =J65*K65 -> 0 | M65: 19 | N65: 152.5 | O65: =M65*N65 -> 2897.5 | T65: =Tabela4[[#This Row],[Valor do contrato sem o equipamento]]/30.4375*3 -> 0 | U65: =Tabela4[[#This Row],[Valor contrato]]*(30.4375-Tabela4[[#This Row],[Dias inoperantes]])/30.4375 -> 0 | Y65: =Tabela4[[#This Row],[Diferença]]*Tabela4[[#This Row],[Quantidade]] -> 0
B66: Shopping Vila Velha | C66: Limpeza | D66: GPS | E66: 45839 | F66: Agente de Limpeza | G66: 12x36 | H66: 0.41666667 | I66: 22:00 | J66: 0 | K66: 21.1 | L66: =J66*K66 -> 0 | M66: 18 | N66: 152.5 | O66: =M66*N66 -> 2745 | T66: =Tabela4[[#This Row],[Valor do contrato sem o equipamento]]/30.4375*3 -> 0 | U66: =Tabela4[[#This Row],[Valor contrato]]*(30.4375-Tabela4[[#This Row],[Dias inoperantes]])/30.4375 -> 0 | Y66: =Tabela4[[#This Row],[Diferença]]*Tabela4[[#This Row],[Quantidade]] -> 0
B67: Shopping Vila Velha | C67: Limpeza | D67: GPS | E67: 45839 | F67: Banheirista | G67: 12x36 | H67: 0.41666667 | I67: 22:00 | J67: 0 | K67: 23.98 | L67: =J67*K67 -> 0 | M67: 16 | N67: 173.31 | O67: =M67*N67 -> 2772.96 | T67: =Tabela4[[#This Row],[Valor do contrato sem o equipamento]]/30.4375*3 -> 0 | U67: =Tabela4[[#This Row],[Valor contrato]]*(30.4375-Tabela4[[#This Row],[Dias inoperantes]])/30.4375 -> 0 | Y67: =Tabela4[[#This Row],[Diferença]]*Tabela4[[#This Row],[Quantidade]] -> 0
B68: Shopping Vila Velha | C68: Limpeza | D68: GPS | E68: 45839 | F68: Auxiliar de Serviços Gerais | G68: 12x36 | H68: 0.91666667 | I68: 10:00 | J68: 0 | K68: 22.85 | L68: =J68*K68 -> 0 | M68: 15 | N68: 165.18 | O68: =M68*N68 -> 2477.7 | T68: =Tabela4[[#This Row],[Valor do contrato sem o equipamento]]/30.4375*3 -> 0 | U68: =Tabela4[[#This Row],[Valor contrato]]*(30.4375-Tabela4[[#This Row],[Dias inoperantes]])/30.4375 -> 0 | Y68: =Tabela4[[#This Row],[Diferença]]*Tabela4[[#This Row],[Quantidade]] -> 0
B69: Shopping Leblon | C69: Manutenção | D69: GPS | E69: 45809 | F69: Auxiliar de Manutenção | G69: 5x2 | H69: 0.29166667 | I69: 0.7 | J69: =19/60 -> 0.31666667 | K69: 29.96 | L69: =J69*K69 -> 9.4873333 | O69: =M69*N69 -> 0 | T69: =Tabela4[[#This Row],[Valor do contrato sem o equipamento]]/30.4375*3 -> 0 | U69: =Tabela4[[#This Row],[Valor contrato]]*(30.4375-Tabela4[[#This Row],[Dias inoperantes]])/30.4375 -> 0 | Y69: =Tabela4[[#This Row],[Diferença]]*Tabela4[[#This Row],[Quantidade]] -> 0
B70: Shopping Leblon | C70: Manutenção | D70: GPS | E70: 45809 | F70: Pintor | G70: 5x2 | H70: 0.89583333 | I70: 0.2625 | J70: =59/60 -> 0.98333333 | K70: 39.23 | L70: =J70*K70 -> 38.576167 | O70: =M70*N70 -> 0 | T70: =Tabela4[[#This Row],[Valor do contrato sem o equipamento]]/30.4375*3 -> 0 | U70: =Tabela4[[#This Row],[Valor contrato]]*(30.4375-Tabela4[[#This Row],[Dias inoperantes]])/30.4375 -> 0 | Y70: =Tabela4[[#This Row],[Diferença]]*Tabela4[[#This Row],[Quantidade]] -> 0
B71: Shopping Leblon | C71: Manutenção | D71: GPS | E71: 45809 | F71: Pintor | G71: 5x2 | H71: 0.89583333 | I71: 0.2625 | J71: =3+7/60 -> 3.1166667 | K71: 42.49 | L71: =J71*K71 -> 132.42717 | O71: =M71*N71 -> 0 | T71: =Tabela4[[#This Row],[Valor do contrato sem o equipamento]]/30.4375*3 -> 0 | U71: =Tabela4[[#This Row],[Valor contrato]]*(30.4375-Tabela4[[#This Row],[Dias inoperantes]])/30.4375 -> 0 | Y71: =Tabela4[[#This Row],[Diferença]]*Tabela4[[#This Row],[Quantidade]] -> 0
B72: Shopping Leblon | C72: Manutenção | D72: GPS | E72: 45809 | F72: Civil | G72: 5x2 | H72: 0.29166667 | I72: 0.7 | J72: =1+18/60 -> 1.3 | K72: 31.63 | L72: =J72*K72 -> 41.119 | O72: =M72*N72 -> 0 | T72: =Tabela4[[#This Row],[Valor do contrato sem o equipamento]]/30.4375*3 -> 0 | U72: =Tabela4[[#This Row],[Valor contrato]]*(30.4375-Tabela4[[#This Row],[Dias inoperantes]])/30.4375 -> 0 | Y72: =Tabela4[[#This Row],[Diferença]]*Tabela4[[#This Row],[Quantidade]] -> 0
B73: Shopping Leblon | C73: Manutenção | D73: GPS | E73: 45870 | F73: Auxiliar de Manutenção | G73: 5x2 | H73: 0.29166667 | I73: 0.7 | J73: 7.32 | K73: 29.96 | L73: =J73*K73 -> 219.3072 | M73: 4 | N73: 216.58 | O73: =M73*N73 -> 866.32 | T73: =Tabela4[[#This Row],[Valor do contrato sem o equipamento]]/30.4375*3 -> 0 | U73: =Tabela4[[#This Row],[Valor contrato]]*(30.4375-Tabela4[[#This Row],[Dias inoperantes]])/30.4375 -> 0 | Y73: =Tabela4[[#This Row],[Diferença]]*Tabela4[[#This Row],[Quantidade]] -> 0
B74: Shopping Leblon | C74: Manutenção | D74: GPS | E74: 45870 | F74: Civil | G74: 5x2 | H74: 0.29166667 | I74: 0.7 | J74: 1.1166667 | K74: 29.28 | L74: =J74*K74 -> 32.696 | M74: 0 | N74: 211.63 | O74: =M74*N74 -> 0 | T74: =Tabela4[[#This Row],[Valor do contrato sem o equipamento]]/30.4375*3 -> 0 | U74: =Tabela4[[#This Row],[Valor contrato]]*(30.4375-Tabela4[[#This Row],[Dias inoperantes]])/30.4375 -> 0 | Y74: =Tabela4[[#This Row],[Diferença]]*Tabela4[[#This Row],[Quantidade]] -> 0
B75: Shopping Leblon | C75: Manutenção | D75: GPS | E75: 45901 | F75: Eletricista | G75: 5X2 | H75: 0.29166667 | I75: 0.7 | J75: 3.05 | K75: 39.66 | L75: =J75*K75 -> 120.963 | M75: 4 | N75: 286.63 | O75: =M75*N75 -> 1146.52 | T75: =Tabela4[[#This Row],[Valor do contrato sem o equipamento]]/30.4375*3 -> 0 | U75: =Tabela4[[#This Row],[Valor contrato]]*(30.4375-Tabela4[[#This Row],[Dias inoperantes]])/30.4375 -> 0 | Y75: =Tabela4[[#This Row],[Diferença]]*Tabela4[[#This Row],[Quantidade]] -> 0
B76: Shopping Leblon | C76: Manutenção | D76: GPS | E76: 45901 | F76: Pintor | G76: 5x2 | H76: 0.89583333 | I76: 0.2625 | J76: 4.3 | K76: 42.49 | L76: =J76*K76 -> 182.707 | M76: 0 | N76: 307.14 | O76: =M76*N76 -> 0 | T76: =Tabela4[[#This Row],[Valor do contrato sem o equipamento]]/30.4375*3 -> 0 | U76: =Tabela4[[#This Row],[Valor contrato]]*(30.4375-Tabela4[[#This Row],[Dias inoperantes]])/30.4375 -> 0 | Y76: =Tabela4[[#This Row],[Diferença]]*Tabela4[[#This Row],[Quantidade]] -> 0
B77: Shopping Leblon | C77: Manutenção | D77: GPS | E77: 45901 | F77: Civil | G77: 5x2 | H77: 0.29166667 | I77: 0.7 | J77: 4.1 | K77: 29.28 | L77: =J77*K77 -> 120.048 | M77: 0 | N77: 211.63 | O77: =M77*N77 -> 0 | T77: =Tabela4[[#This Row],[Valor do contrato sem o equipamento]]/30.4375*3 -> 0 | U77: =Tabela4[[#This Row],[Valor contrato]]*(30.4375-Tabela4[[#This Row],[Dias inoperantes]])/30.4375 -> 0 | Y77: =Tabela4[[#This Row],[Diferença]]*Tabela4[[#This Row],[Quantidade]] -> 0
B78: Shopping Leblon | C78: Manutenção | D78: GPS | E78: 45870 | F78: Pintor | G78: 5x2 | H78: 0.89583333 | I78: 0.2625 | J78: 3.88 | K78: 39.23 | L78: =J78*K78 -> 152.2124 | M78: 0 | N78: 283.54 | O78: =M78*N78 -> 0 | T78: =Tabela4[[#This Row],[Valor do contrato sem o equipamento]]/30.4375*3 -> 0 | U78: =Tabela4[[#This Row],[Valor contrato]]*(30.4375-Tabela4[[#This Row],[Dias inoperantes]])/30.4375 -> 0 | Y78: =Tabela4[[#This Row],[Diferença]]*Tabela4[[#This Row],[Quantidade]] -> 0
B79: Shopping Leblon | C79: Manutenção | D79: GPS | E79: 45809 | F79: Civil | G79: 5x2 | H79: 0.29166667 | I79: 0.7 | J79: =3+34/60 -> 3.5666667 | K79: 29.28 | L79: =J79*K79 -> 104.432 | O79: =M79*N79 -> 0 | T79: =Tabela4[[#This Row],[Valor do contrato sem o equipamento]]/30.4375*3 -> 0 | U79: =Tabela4[[#This Row],[Valor contrato]]*(30.4375-Tabela4[[#This Row],[Dias inoperantes]])/30.4375 -> 0 | Y79: =Tabela4[[#This Row],[Diferença]]*Tabela4[[#This Row],[Quantidade]] -> 0
B80: Shopping Grande Rio | C80: Estacionamento | D80: GPS | E80: 45658 | F80: Orientador de trafego | G80: 6x1 | H80: 0.5 | I80: 0.84722222 | J80: 1.46 | K80: 22.27 | L80: =J80*K80 -> 32.5142 | O80: =M80*N80 -> 0 | T80: =Tabela4[[#This Row],[Valor do contrato sem o equipamento]]/30.4375*3 -> 0 | U80: =Tabela4[[#This Row],[Valor contrato]]*(30.4375-Tabela4[[#This Row],[Dias inoperantes]])/30.4375 -> 0 | Y80: =Tabela4[[#This Row],[Diferença]]*Tabela4[[#This Row],[Quantidade]] -> 0
B81: Shopping Grande Rio | C81: Estacionamento | D81: GPS | E81: 45658 | F81: Orientador de trafego | G81: 12x36 | H81: 0.5 | I81: 0 | J81: 0 | K81: 18.29 | L81: =J81*K81 -> 0 | O81: =M81*N81 -> 0 | T81: =Tabela4[[#This Row],[Valor do contrato sem o equipamento]]/30.4375*3 -> 0 | U81: =Tabela4[[#This Row],[Valor contrato]]*(30.4375-Tabela4[[#This Row],[Dias inoperantes]])/30.4375 -> 0 | Y81: =Tabela4[[#This Row],[Diferença]]*Tabela4[[#This Row],[Quantidade]] -> 0
B82: Shopping Grande Rio | C82: Estacionamento | D82: GPS | E82: 45658 | F82: Orientador de trafego | G82: 12x36 | H82: 0.41666667 | I82: 0.91666667 | J82: 76 | K82: 17.77 | L82: =J82*K82 -> 1350.52 | O82: =M82*N82 -> 0 | T82: =Tabela4[[#This Row],[Valor do contrato sem o equipamento]]/30.4375*3 -> 0 | U82: =Tabela4[[#This Row],[Valor contrato]]*(30.4375-Tabela4[[#This Row],[Dias inoperantes]])/30.4375 -> 0 | Y82: =Tabela4[[#This Row],[Diferença]]*Tabela4[[#This Row],[Quantidade]] -> 0
B83: Shopping Grande Rio | C83: Portaria | D83: GPS | E83: 45658 | F83: Porteiro | G83: 12x36 | H83: 0.29166667 | I83: 0.79166667 | J83: 12 | L83: =J83*K83 -> 0 | O83: =M83*N83 -> 0 | T83: =Tabela4[[#This Row],[Valor do contrato sem o equipamento]]/30.4375*3 -> 0 | U83: =Tabela4[[#This Row],[Valor contrato]]*(30.4375-Tabela4[[#This Row],[Dias inoperantes]])/30.4375 -> 0 | Y83: =Tabela4[[#This Row],[Diferença]]*Tabela4[[#This Row],[Quantidade]] -> 0
B84: Shopping Grande Rio | C84: Portaria | D84: GPS | E84: 45658 | F84: Porteiro | G84: 12x36 | H84: 0.45833333 | I84: 0.95833333 | J84: 15 | L84: =J84*K84 -> 0 | O84: =M84*N84 -> 0 | T84: =Tabela4[[#This Row],[Valor do contrato sem o equipamento]]/30.4375*3 -> 0 | U84: =Tabela4[[#This Row],[Valor contrato]]*(30.4375-Tabela4[[#This Row],[Dias inoperantes]])/30.4375 -> 0 | Y84: =Tabela4[[#This Row],[Diferença]]*Tabela4[[#This Row],[Quantidade]] -> 0
B85: Shopping Grande Rio | C85: Portaria | D85: GPS | E85: 45658 | F85: Porteiro | G85: 12x36 | H85: 0.45833333 | I85: 0.95833333 | J85: 0 | L85: =J85*K85 -> 0 | R85: 0 | S85: 0 | W85: 0 | Y85: =Tabela4[[#This Row],[Diferença]]*Tabela4[[#This Row],[Quantidade]] -> 0
B86: Shopping Grande Rio | C86: Portaria | D86: GPS | E86: 45931 | F86: Porteiro | G86: 5X2 | H86: 0.33333333 | I86: 0.70833333 | J86: 6 | L86: =J86*K86 -> 0 | O86: =M86*N86 -> 0 | T86: =Tabela4[[#This Row],[Valor do contrato sem o equipamento]]/30.4375*3 -> 0 | U86: =Tabela4[[#This Row],[Valor contrato]]*(30.4375-Tabela4[[#This Row],[Dias inoperantes]])/30.4375 -> 0 | Y86: =Tabela4[[#This Row],[Diferença]]*Tabela4[[#This Row],[Quantidade]] -> 0
B87: Shopping Grande Rio | C87: Portaria | D87: GPS | E87: 45658 | F87: Porteiro | G87: 5X2 | H87: 0.33333333 | I87: 0.70833333 | J87: 8 | L87: =J87*K87 -> 0 | O87: =M87*N87 -> 0 | T87: =Tabela4[[#This Row],[Valor do contrato sem o equipamento]]/30.4375*3 -> 0 | U87: =Tabela4[[#This Row],[Valor contrato]]*(30.4375-Tabela4[[#This Row],[Dias inoperantes]])/30.4375 -> 0 | Y87: =Tabela4[[#This Row],[Diferença]]*Tabela4[[#This Row],[Quantidade]] -> 0
B88: Recreio Shopping | C88: Limpeza | D88: Seleto | E88: 45658 | F88: Agende de limpeza | G88: 6x1 | H88: 0.25 | I88: 0.59722222 | J88: 0 | K88: 18.41 | L88: =J88*K88 -> 0 | M88: 1 | N88: 133.08 | O88: =M88*N88 -> 133.08 | P88: Auto lavadora em formato MOP | T88: =Tabela4[[#This Row],[Valor do contrato sem o equipamento]]/30.4375*3 -> 0 | U88: =Tabela4[[#This Row],[Valor contrato]]*(30.4375-Tabela4[[#This Row],[Dias inoperantes]])/30.4375 -> 0 | V88: 317.5 | W88: 10.583333 | X88: 1 | Y88: =Tabela4[[#This Row],[Diferença]]*Tabela4[[#This Row],[Quantidade]] -> 10.583333
B89: Recreio Shopping | C89: Limpeza | D89: Seleto | E89: 45658 | F89: Agende de limpeza | G89: 6x1 | H89: 0.25 | I89: 0.59722222 | J89: 0 | K89: 18.41 | L89: =J89*K89 -> 0 | M89: 1 | N89: 133.08 | O89: =M89*N89 -> 133.08 | P89: Lavadora Manual - Piso (Bateria) | T89: =Tabela4[[#This Row],[Valor do contrato sem o equipamento]]/30.4375*3 -> 0 | U89: =Tabela4[[#This Row],[Valor contrato]]*(30.4375-Tabela4[[#This Row],[Dias inoperantes]])/30.4375 -> 0 | V89: 265.49 | W89: 8.8496667 | X89: 1 | Y89: =Tabela4[[#This Row],[Diferença]]*Tabela4[[#This Row],[Quantidade]] -> 8.8496667
B90: Recreio Shopping | C90: Limpeza | D90: Seleto | E90: 45658 | F90: Agende de limpeza - coletor de lixo | G90: 6x1 | H90: 0.25 | I90: 0.59722222 | J90: 0 | K90: 21.42 | L90: =J90*K90 -> 0 | M90: 1 | N90: 154.82 | O90: =M90*N90 -> 154.82 | T90: =Tabela4[[#This Row],[Valor do contrato sem o equipamento]]/30.4375*3 -> 0 | U90: =Tabela4[[#This Row],[Valor contrato]]*(30.4375-Tabela4[[#This Row],[Dias inoperantes]])/30.4375 -> 0 | Y90: =Tabela4[[#This Row],[Diferença]]*Tabela4[[#This Row],[Quantidade]] -> 0
B91: Recreio Shopping | C91: Limpeza | D91: Seleto | E91: 45658 | F91: Agende de limpeza | G91: 6x1 | H91: 0.5 | I91: 0.83333333 | J91: 0 | K91: 19.03 | L91: =J91*K91 -> 0 | M91: 1 | N91: 137.57 | O91: =M91*N91 -> 137.57 | T91: =Tabela4[[#This Row],[Valor do contrato sem o equipamento]]/30.4375*3 -> 0 | U91: =Tabela4[[#This Row],[Valor contrato]]*(30.4375-Tabela4[[#This Row],[Dias inoperantes]])/30.4375 -> 0 | Y91: =Tabela4[[#This Row],[Diferença]]*Tabela4[[#This Row],[Quantidade]] -> 0
B92: Recreio Shopping | C92: Limpeza | D92: Seleto | E92: 45658 | F92: Agende de limpeza | G92: 6x1 | H92: 0.4375 | I92: 0.9375 | J92: 4.5 | K92: 17.14 | L92: =J92*K92 -> 77.13 | M92: 0 | N92: 123.91 | O92: =M92*N92 -> 0 | T92: =Tabela4[[#This Row],[Valor do contrato sem o equipamento]]/30.4375*3 -> 0 | U92: =Tabela4[[#This Row],[Valor contrato]]*(30.4375-Tabela4[[#This Row],[Dias inoperantes]])/30.4375 -> 0 | Y92: =Tabela4[[#This Row],[Diferença]]*Tabela4[[#This Row],[Quantidade]] -> 0
B93: Recreio Shopping | C93: Limpeza - Barra Bonita | D93: Seleto | E93: 45689 | F93: Agente de Limpeza | G93: 12x36 | H93: 0.33333333 | I93: 0.83333333 | J93: =12+20/60 -> 12.333333 | K93: 17.22 | L93: =J93*K93 -> 212.38 | N93: 124.46 | O93: =M93*N93 -> 0 | T93: =Tabela4[[#This Row],[Valor do contrato sem o equipamento]]/30.4375*3 -> 0 | U93: =Tabela4[[#This Row],[Valor contrato]]*(30.4375-Tabela4[[#This Row],[Dias inoperantes]])/30.4375 -> 0 | Y93: =Tabela4[[#This Row],[Diferença]]*Tabela4[[#This Row],[Quantidade]] -> 0
B94: Recreio Shopping | C94: Limpeza | D94: Seleto | E94: 45717 | F94: Agente de Limpeza Líder | G94: 6x1 | H94: 0.41666667 | I94: 0.76388889 | J94: 0 | K94: 21.29 | L94: =J94*K94 -> 0 | N94: 153.87 | O94: =M94*N94 -> 0 | T94: =Tabela4[[#This Row],[Valor do contrato sem o equipamento]]/30.4375*3 -> 0 | U94: =Tabela4[[#This Row],[Valor contrato]]*(30.4375-Tabela4[[#This Row],[Dias inoperantes]])/30.4375 -> 0 | Y94: =Tabela4[[#This Row],[Diferença]]*Tabela4[[#This Row],[Quantidade]] -> 0
B95: Recreio Shopping | C95: Limpeza | D95: Seleto | E95: 45717 | F95: Agente de Limpeza | G95: 6x1 | H95: 0.25 | I95: 0.59722222 | J95: 0 | K95: 18.41 | L95: =J95*K95 -> 0 | M95: 2 | N95: 133.08 | O95: =M95*N95 -> 266.16 | T95: =Tabela4[[#This Row],[Valor do contrato sem o equipamento]]/30.4375*3 -> 0 | U95: =Tabela4[[#This Row],[Valor contrato]]*(30.4375-Tabela4[[#This Row],[Dias inoperantes]])/30.4375 -> 0 | Y95: =Tabela4[[#This Row],[Diferença]]*Tabela4[[#This Row],[Quantidade]] -> 0
B96: Recreio Shopping | C96: Limpeza | D96: Seleto | E96: 45717 | F96: Agente de Limpeza | G96: 6x1 | H96: 0.5 | I96: 0.84722222 | J96: 0 | K96: 19.03 | L96: =J96*K96 -> 0 | N96: 137.57 | O96: =M96*N96 -> 0 | T96: =Tabela4[[#This Row],[Valor do contrato sem o equipamento]]/30.4375*3 -> 0 | U96: =Tabela4[[#This Row],[Valor contrato]]*(30.4375-Tabela4[[#This Row],[Dias inoperantes]])/30.4375 -> 0 | Y96: =Tabela4[[#This Row],[Diferença]]*Tabela4[[#This Row],[Quantidade]] -> 0
B97: Recreio Shopping | C97: Limpeza | D97: Seleto | E97: 45717 | F97: Agente de Limpeza - Coletor de Lixo | G97: 12x36 | H97: 0.41666667 | I97: 0.91666667 | J97: 0 | K97: 20.01 | L97: =J97*K97 -> 0 | M97: 1 | N97: 144.62 | O97: =M97*N97 -> 144.62 | T97: =Tabela4[[#This Row],[Valor do contrato sem o equipamento]]/30.4375*3 -> 0 | U97: =Tabela4[[#This Row],[Valor contrato]]*(30.4375-Tabela4[[#This Row],[Dias inoperantes]])/30.4375 -> 0 | Y97: =Tabela4[[#This Row],[Diferença]]*Tabela4[[#This Row],[Quantidade]] -> 0
